Workbook
Name AST: #REF!
Name AST: #REF!
Name AST: #REF!
Name Bez: #REF!
Name Cneu: #REF!
Name Cost: #REF!
Name Cost: #REF!
Name Cost: #REF!
Name EANneu: #REF!
Name Finntest: #REF!
Name Finntest: #REF!
Name Finntest: #REF!
Name ICTP: #REF!
Name ICTP: #REF!
Name ICTP: #REF!
Name LP: #REF!
Name LP: #REF!
Name LP: #REF!
Name LPneu: #REF!
Name Miteral: #REF!
Name Miteral: #REF!
Name Miteral: #REF!
Name n: #REF!
Name n: #REF!
Name n: #REF!
Name New: #REF!
Name NR: #REF!
Name NRA: #REF!
Name PN: #REF!
Name PN: #REF!
Name PN: #REF!
Name Semler: #REF!
Name Semler: #REF!
Name Semler: #REF!
Name Sigl: #REF!
Name Sigl: #REF!
Name Sigl: #REF!
Name Spakko: #REF!
Name Spakko: #REF!
Name Spakko: #REF!
Name UVP: #REF!
Name UVP: #REF!
Name UVP: #REF!
Name UVPA: #REF!
Name UVPneu: #REF!
Name Z.Sigl: #REF!
Name Z.Sigl: #REF!
Name Z.Sigl: #REF!

Sheet Language
B1: CEE & CIS | C1: ENGLISH | D1: CUSTOMER CODE | E1: CUSTOMER NAME | F1: COUNTRY | G1: PAYMENT TERM | H1: REFERENCED PRICE LIST | I1: CURRENCY | J1: CREDIT LIMIT
A2: ENGLISH | B2: MEA | C2: FRANÇAIS | D2: RÉF. CLIENT | E2: NOM CLIENT | F2: PAYS | G2: CONDITIONS DE PAIEMENT | H2: TARIFS RELATIFS | I2: MONNAIE | J2: PLAFOND DE CRÉDIT
A3: DEUTSCH | B3: Iberica | C3: DEUTSCH | D3: KUNDENREF. | E3: KUNDENNAME | F3: LAND | G3: ZAHLUNGSBEDINGUNGEN | H3: PREISBASIS | I3: WÄHRUNG | J3: KREDITRAHMEN
A4: FRANÇAIS | B4: Benelux | C4: ESPAÑOL | D4: CÓDIGO DE CLIENTE | E4: NOMBRE DEL CLIENTE | F4: PAÍS | G4: FORMA DE PAGO | H4: LISTADO PRECIOS | I4: MONEDA | J4: LÍMITE DE CRÉDITO
A5: ESPAÑOL | B5: North CH | C5: ITALIANO | D5: CODICE CLIENTE | E5: NOME DEL CLIENTE | F5: PAESE | G5: TERMINE DI PAGAMENTO | H5: LISTINO PREZZI DI RIFERIMENTO | I5: MONETA | J5: LIMITE DI CREDITO
A6: ITALIANO | B6: Poland
B7: Italy
A11: ENGLISH | B11: Effective date: | C11: V.1 This price list supersedes all previous price lists | D11: Sales Manager: | E11: Validity | F11: Base Price
A12: FRANÇAIS | B12: Date actuelle: | C12: V.1 Les tarifs du présent document remplacent les tarifs précédents | D12: Responsable de ventes: | E12: Validité | F12: Prix ​​de base
A13: DEUTSCH | B13: Gültigkeitdatum: | C13: V.1 Diese Preisliste ersetzt alle vorherigen Preislisten | D13: Vertriebsleiter: | E13: Gültigkeit | F13: Preise ab Werk
A14: ESPAÑOL | B14: Fecha efectiva: | C14: V.1 Esta lista de precios reemplaza todas las listas de precios anteriores | D14: Gerente de ventas: | E14: Validez | F14: Precio Base
A15: ITALIANO | B15: Data effettiva: | C15: V.1 Questo listino prezzi sostituisce tutti i listini precedenti | D15: Direttore delle vendite: | E15: Validità | F15: Prezzo base
A19: ENGLISH | B19: PRODUCT IMAGE | C19: P/N | D19: MODEL | E19: VOLTAGE | F19: DESCRIPTION | G19: PRODUCT TYPE | H19: SUB-CATEGORY | I19: SOFTWARE | J19: List Price | K19: Discount | L19: Net Price | M19: OEM | N19: CATEGORY | O19: ITEM | P19: COMPATIBILITY | Q19: Discount 2
A20: FRANÇAIS | B20: IMAGE DU PRODUIT | C20: P/N | D20: MODÈLE | E20: TENSION | F20: DESCRIPTION | G20: TYPE DE PRODUIT | H20: SOUS-CATÉGORIE | I20: SOFTWARE | J20: Liste des prix | K20: Rabais | L20: Prix ​​Net | M20: OEM | N20: CATÉGORIE | O20: ARTICLE | P20: COMPATIBILITÉ | Q20: Rabais 2
A21: DEUTSCH | B21: PRODUKTBILD | C21: P/N | D21: MODELL | E21: STROMSPANNUNG | F21: BESCHREIBUNG | G21: PRODUKTART | H21: UNTERKATEGORIE | I21: LOGICEL | J21: Preisliste | K21: Rabatt | L21: Nettopreis | M21: OEM | N21: KATEGORIE | O21: ARTIKEL | P21: KOMPATIBILITÄT | Q21: Rabatt 2
A22: ESPAÑOL | B22: IMAGEN DEL PRODUCTO | C22: P/N | D22: MODELO | E22: VOLTAJE | F22: DESCRIPCIÓN | G22: TIPO DE PRODUCTO | H22: SUBCATEGORÍA | I22: SOFTWARE | J22: Precio de lista | K22: Descuento | L22: Precio Neto | M22: OEM | N22: CATEGORÍA | O22: ARTÍCULO | P22: COMPATIBILIDAD | Q22: Descuento 2
A23: ITALIANO | B23: IMMAGINE DEL PRODOTTO | C23: P/N | D23: MODELLO | E23: VOLTAGGIO | F23: DESCRIZIONE | G23: TIPOLOGIA DI PRODOTTO | H23: SOTTOCATEGORIA | I23: SOFTWARE | J23: Prezzo di listino | K23: Sconto | L23: Prezzo Netto | M23: OEM | N23: CATEGORIA | O23: ARTICOLO | P23: COMPATIBILITÀ | Q23: Sconto 2
A26: ENGLISH | B26: WHEEL ALIGNERS
A27: FRANÇAIS | B27: CONTROLEURS DE GÉOMÉTRIE
A28: DEUTSCH | B28: ACHSMESSGERÄTE
A29: ESPAÑOL | B29: ALINEADORES DE RUEDAS
A30: ITALIANO | B30: ASSETTI RUOTE
A32: ENGLISH | B32: 3D CAMERA TECHNOLOGY WITH NEXT GENERATION SOFTWARE | C32: NEXT GENERATION
A33: FRANÇAIS | B33: TECHNOLOGIE CAMÉRA 3D AVEC LOGICIEL NOUVELLE GÉNÉRATION | C33: NOUVELLE GÉNÉRATION
A34: DEUTSCH | B34: 3D-KAMERATECHNIK MIT SOFTWARE DER NÄCHSTEN GENERATION | C34: NÄCHSTEN GENERATION
A35: ESPAÑOL | B35: TECNOLOGÍA DE CÁMARA 3D CON SOFTWARE DE NUEVA GENERACIÓN | C35: NUEVA GENERACIÓN
A36: ITALIANO | B36: TECNOLOGIA TELECAMERA 3D CON SOFTWARE DI NUOVA GENERAZIONE | C36: NUOVA GENERAZIONE
A38: ENGLISH | B38: NOTE: all above mentioned machines in RAL 5015b, 3000, 7040 keep the same net price as showed in this list. All other colors may be available with a LP surcharge of 280€
A39: FRANÇAIS | B39: Note: Toutes les machines ci-dessus en RAL 5015b, 3000, 7040 ont les prix identiques comme indiqués dans cette liste. Toutes les autres couleurs peuvent être disponibles à un supplément sur le prix tarif de 280€.
A40: DEUTSCH | B40: ACHTUNG: Alle oben aufgeführten Maschinen in RAL 5015b, 3000, 7040 haben identische Preise wie in dieser Liste aufgeführt. Alle anderen Farben haben einen Mehrpreis (LP) von of 280€
A41: ESPAÑOL | B41: NOTA: todas las máquinas mencionadas anteriormente en RAL 5015b, 3000, 7040 mantienen el mismo precio neto que se muestra en esta lista. Todos los demás colores pueden estar disponibles con un recargo LP de 280€
A42: ITALIANO | B42: NOTA: tutte le macchine sopra menzionate in RAL 5015b, 3000, 7040 mantengono lo stesso prezzo netto indicato in questa inserzione. Tutti gli altri colori potrebbero essere disponibili con un supplemento di € 280 LP
A45: ENGLISH | B45: Standard discount on ACCESSORIES Price List:
A46: FRANÇAIS | B46: Remise standard sur tarifs ACCESSOIRES:
A47: DEUTSCH | B47: Standardrabatt auf ZUBEHÖR laut Preisliste:
A48: ESPAÑOL | B48: Descuento estándar en la Lista de Precios de ACCESORIOS:
A49: ITALIANO | B49: Sconto Standard su Listino ACCESSORI:
A51: ENGLISH | B51: Standard discount on SPARE PARTS Price List:
A52: FRANÇAIS | B52: Remise standard sur tarifs PIÈCES DÉTACHÉES:
... A83: ITALIANO | B83: Approvato da:

Sheet DB Equipment
A1: P/N | B1: FAMILY | C1: CATEGORY - EN | D1: CATEGORY - DE | E1: CATEGORY - FR | F1: CATEGORY - ES | G1: CATEGORY - IT | H1: MODEL | I1: LANGUAGE | J1: VOLTAGE | K1: VCI | L1: DESCRIPTION - EN | M1: DESCRIPTION - DE | N1: DESCRIPTION - FR | O1: DESCRIPTION - ES | P1: DESCRIPTION - IT
A2: EESCDE137A | B2: PDL 4200 | C2: PDL | D2: PDL | E2: PDL | F2: PDL | G2: PDL | H2: PDL 4200 German | I2: German | L2: Including latest software release + free-of-charge updates (2 minimum) for one year, German version | M2: Including latest software release + free-of-charge updates (2 minimum) for one year, German version | N2: Including latest software release + free-of-charge updates (2 minimum) for one year, German version | O2: Including latest software release + free-of-charge updates (2 minimum) for one year, German version | P2: Including latest software release + free-of-charge updates (2 minimum) for one year, German version
A3: EESCFR137A | B3: PDL 4200 | C3: PDL | D3: PDL | E3: PDL | F3: PDL | G3: PDL | H3: PDL 4200 French | I3: French | L3: Including latest software release + free-of-charge updates (2 minimum) for one year, French version | M3: Including latest software release + free-of-charge updates (2 minimum) for one year, French version | N3: Including latest software release + free-of-charge updates (2 minimum) for one year, French version | O3: Including latest software release + free-of-charge updates (2 minimum) for one year, French version | P3: Including latest software release + free-of-charge updates (2 minimum) for one year, French version
A4: EESCIT137A | B4: PDL 4200 | C4: PDL | D4: PDL | E4: PDL | F4: PDL | G4: PDL | H4: PDL 4200 Italian | I4: Italian | L4: Including latest software release + free-of-charge updates (2 minimum) for one year, Italian version | M4: Including latest software release + free-of-charge updates (2 minimum) for one year, Italian version | N4: Including latest software release + free-of-charge updates (2 minimum) for one year, Italian version | O4: Including latest software release + free-of-charge updates (2 minimum) for one year, Italian version | P4: Including latest software release + free-of-charge updates (2 minimum) for one year, Italian version
A5: EESCPL137A | B5: PDL 4200 | C5: PDL | D5: PDL | E5: PDL | F5: PDL | G5: PDL | H5: PDL 4200 Polish | I5: Polish | L5: Including latest software release + free-of-charge updates (2 minimum) for one year, Polish version | M5: Including latest software release + free-of-charge updates (2 minimum) for one year, Polish version | N5: Including latest software release + free-of-charge updates (2 minimum) for one year, Polish version | O5: Including latest software release + free-of-charge updates (2 minimum) for one year, Polish version | P5: Including latest software release + free-of-charge updates (2 minimum) for one year, Polish version
A6: EESCPL137A x 5 | B6: PDL 4200 | C6: PDL | D6: PDL | E6: PDL | F6: PDL | G6: PDL | H6: PDL 4200 Polish | I6: Polish | L6: 5 unit order
A7: EESCPL137A x 10 | B7: PDL 4200 | C7: PDL | D7: PDL | E7: PDL | F7: PDL | G7: PDL | H7: PDL 4200 Polish | I7: Polish | L7: 10 unit order
A8: EESCEG137A | B8: PDL 4200 | C8: PDL | D8: PDL | E8: PDL | F8: PDL | G8: PDL | H8: PDL 4200 English | I8: English | L8: Including latest software release + free-of-charge updates (2 minimum) for one year, English version | M8: Including latest software release + free-of-charge updates (2 minimum) for one year, English version | N8: Including latest software release + free-of-charge updates (2 minimum) for one year, English version | O8: Including latest software release + free-of-charge updates (2 minimum) for one year, English version | P8: Including latest software release + free-of-charge updates (2 minimum) for one year, English version
A9: EESCDE135A | B9: PDL 7100 | C9: PDL | D9: PDL | E9: PDL | F9: PDL | G9: PDL | H9: PDL 7100 German | I9: German | L9: Including latest software release + free-of-charge updates (2 minimum) for one year, German version | M9: Including latest software release + free-of-charge updates (2 minimum) for one year, German version | N9: Including latest software release + free-of-charge updates (2 minimum) for one year, German version | O9: Including latest software release + free-of-charge updates (2 minimum) for one year, German version | P9: Including latest software release + free-of-charge updates (2 minimum) for one year, German version
A10: EESCFR135A | B10: PDL 7100 | C10: PDL | D10: PDL | E10: PDL | F10: PDL | G10: PDL | H10: PDL 7100 French | I10: French | L10: Including latest software release + free-of-charge updates (2 minimum) for one year, French version | M10: Including latest software release + free-of-charge updates (2 minimum) for one year, French version | N10: Including latest software release + free-of-charge updates (2 minimum) for one year, French version | O10: Including latest software release + free-of-charge updates (2 minimum) for one year, French version | P10: Including latest software release + free-of-charge updates (2 minimum) for one year, French version
A11: EESCIT135A | B11: PDL 7100 | C11: PDL | D11: PDL | E11: PDL | F11: PDL | G11: PDL | H11: PDL 7100 Italian | I11: Italian | L11: Including latest software release + free-of-charge updates (2 minimum) for one year, Italian version | M11: Including latest software release + free-of-charge updates (2 minimum) for one year, Italian version | N11: Including latest software release + free-of-charge updates (2 minimum) for one year, Italian version | O11: Including latest software release + free-of-charge updates (2 minimum) for one year, Italian version | P11: Including latest software release + free-of-charge updates (2 minimum) for one year, Italian version
A12: EESCPL135A | B12: PDL 7100 | C12: PDL | D12: PDL | E12: PDL | F12: PDL | G12: PDL | H12: PDL 7100 Polish | I12: Polish | L12: Including latest software release + free-of-charge updates (2 minimum) for one year, Polish version | M12: Including latest software release + free-of-charge updates (2 minimum) for one year, Polish version | N12: Including latest software release + free-of-charge updates (2 minimum) for one year, Polish version | O12: Including latest software release + free-of-charge updates (2 minimum) for one year, Polish version | P12: Including latest software release + free-of-charge updates (2 minimum) for one year, Polish version
A13: EESCPL135A x 5 | B13: PDL 7100 | C13: PDL | D13: PDL | E13: PDL | F13: PDL | G13: PDL | H13: PDL 7100 Polish | I13: Polish | L13: 5 unit order
A14: EESCPL135A x 10 | B14: PDL 7100 | C14: PDL | D14: PDL | E14: PDL | F14: PDL | G14: PDL | H14: PDL 7100 Polish | I14: Polish | L14: 10 unit order
A15: EESCEG135A | B15: PDL 7100 | C15: PDL | D15: PDL | E15: PDL | F15: PDL | G15: PDL | H15: PDL 7100 English | I15: English | L15: Including latest software release + free-of-charge updates (2 minimum) for one year, English version | M15: Including latest software release + free-of-charge updates (2 minimum) for one year, English version | N15: Including latest software release + free-of-charge updates (2 minimum) for one year, English version | O15: Including latest software release + free-of-charge updates (2 minimum) for one year, English version | P15: Including latest software release + free-of-charge updates (2 minimum) for one year, English version
A16: EEMSDE143A | B16: PDL 8000 | C16: PDL | D16: PDL | E16: PDL | F16: PDL | G16: PDL | H16: PDL 8000 German | I16: German | L16: Including latest software release + free-of-charge updates (2 minimum) for one year, German version Inkl. neueste Softwareversion + kostenlose Updates (mindestens 2) für 1 Jahr, deutsche Version | M16: Including latest software release + free-of-charge updates (2 minimum) for one year, German version Inkl. neueste Softwareversion + kostenlose Updates (mindestens 2) für 1 Jahr, deutsche Version | N16: Including latest software release + free-of-charge updates (2 minimum) for one year, German version Inkl. neueste Softwareversion + kostenlose Updates (mindestens 2) für 1 Jahr, deutsche Version | O16: Including latest software release + free-of-charge updates (2 minimum) for one year, German version Inkl. neueste Softwareversion + kostenlose Updates (mindestens 2) für 1 Jahr, deutsche Version | P16: Including latest software release + free-of-charge updates (2 minimum) for one year, German version Inkl. neueste Softwareversion + kostenlose Updates (mindestens 2) für 1 Jahr, deutsche Version
A17: EEMSPL143A | B17: PDL 8000 | C17: PDL | D17: PDL | E17: PDL | F17: PDL | G17: PDL | H17: PDL 8000 Polish | I17: Polish | L17: Including latest software release + free-of-charge updates (2 minimum) for one year, Polish version | M17: Including latest software release + free-of-charge updates (2 minimum) for one year, Polish version | N17: Including latest software release + free-of-charge updates (2 minimum) for one year, Polish version | O17: Including latest software release + free-of-charge updates (2 minimum) for one year, Polish version | P17: Including latest software release + free-of-charge updates (2 minimum) for one year, Polish version
A18: EEMSPL143A x 5 | B18: PDL 8000 | C18: PDL | D18: PDL | E18: PDL | F18: PDL | G18: PDL | H18: PDL 8000 Polish | I18: Polish | L18: 5 unit order
A19: EEMSPL143A x 10 | B19: PDL 8000 | C19: PDL | D19: PDL | E19: PDL | F19: PDL | G19: PDL | H19: PDL 8000 Polish | I19: Polish | L19: 10 unit order
A20: EEMSIT143A | B20: PDL 8000 | C20: PDL | D20: PDL | E20: PDL | F20: PDL | G20: PDL | H20: PDL 8000 Italian | I20: Italian | L20: Including latest software release + free-of-charge updates (2 minimum) for one year, Italian version | M20: Including latest software release + free-of-charge updates (2 minimum) for one year, Italian version | N20: Including latest software release + free-of-charge updates (2 minimum) for one year, Italian version | O20: Including latest software release + free-of-charge updates (2 minimum) for one year, Italian version | P20: Including latest software release + free-of-charge updates (2 minimum) for one year, Italian version
A21: EEMSFR143A | B21: PDL 8000 | C21: PDL | D21: PDL | E21: PDL | F21: PDL | G21: PDL | H21: PDL 8000 French | I21: French | L21: Including latest software release + free-of-charge updates (2 minimum) for one year, French version | M21: Including latest software release + free-of-charge updates (2 minimum) for one year, French version | N21: Including latest software release + free-of-charge updates (2 minimum) for one year, French version | O21: Including latest software release + free-of-charge updates (2 minimum) for one year, French version | P21: Including latest software release + free-of-charge updates (2 minimum) for one year, French version
A22: EEMSDE149A | B22: PDL 8200 | C22: PDL | D22: PDL | E22: PDL | F22: PDL | G22: PDL | H22: PDL 8200 German | I22: German | L22: Including latest software release + free-of-charge updates (2 minimum) for one year, German version | M22: Inkl. neueste Softwareversion + kostenlose Updates (mindestens 2) für 1 Jahr, deutsche Version | N22: Including latest software release + free-of-charge updates (2 minimum) for one year, German version | O22: Including latest software release + free-of-charge updates (2 minimum) for one year, German version | P22: Including latest software release + free-of-charge updates (2 minimum) for one year, German version
A23: EEMSPL149A | B23: PDL 8200 | C23: PDL | D23: PDL | E23: PDL | F23: PDL | G23: PDL | H23: PDL 8200 Polish | I23: Polish | L23: Including latest software release + free-of-charge updates (2 minimum) for one year, Polish version | M23: Including latest software release + free-of-charge updates (2 minimum) for one year, Polish version | N23: Including latest software release + free-of-charge updates (2 minimum) for one year, Polish version | O23: Including latest software release + free-of-charge updates (2 minimum) for one year, Polish version | P23: Including latest software release + free-of-charge updates (2 minimum) for one year, Polish version
A24: EEMSPL149A x 5 | B24: PDL 8200 | C24: PDL | D24: PDL | E24: PDL | F24: PDL | G24: PDL | H24: PDL 8200 Polish | I24: Polish | L24: 5 unit order
A25: EEMSPL149A x 10 | B25: PDL 8200 | C25: PDL | D25: PDL | E25: PDL | F25: PDL | G25: PDL | H25: PDL 8200 Polish | I25: Polish | L25: 10 unit order
A26: EEMSIT149A | B26: PDL 8200 | C26: PDL | D26: PDL | E26: PDL | F26: PDL | G26: PDL | H26: PDL 8200 Italian | I26: Italian | L26: Including latest software release + free-of-charge updates (2 minimum) for one year, Italian version | M26: Including latest software release + free-of-charge updates (2 minimum) for one year, Italian version | N26: Including latest software release + free-of-charge updates (2 minimum) for one year, Italian version | O26: Including latest software release + free-of-charge updates (2 minimum) for one year, Italian version | P26: Including latest software release + free-of-charge updates (2 minimum) for one year, Italian version
A27: EEMSFR149A | B27: PDL 8200 | C27: PDL | D27: PDL | E27: PDL | F27: PDL | G27: PDL | H27: PDL 8200 French | I27: French | L27: Including latest software release + free-of-charge updates (2 minimum) for one year, French version | M27: Including latest software release + free-of-charge updates (2 minimum) for one year, French version | N27: Including latest software release + free-of-charge updates (2 minimum) for one year, French version | O27: Including latest software release + free-of-charge updates (2 minimum) for one year, French version | P27: Including latest software release + free-of-charge updates (2 minimum) for one year, French version
A28: EEMSEG149A | B28: PDL 8200 | C28: PDL | D28: PDL | E28: PDL | F28: PDL | G28: PDL | H28: PDL 8200 English | I28: English | L28: Including latest software release + free-of-charge updates (2 minimum) for one year, English version | M28: Including latest software release + free-of-charge updates (2 minimum) for one year, English version | N28: Including latest software release + free-of-charge updates (2 minimum) for one year, English version | O28: Including latest software release + free-of-charge updates (2 minimum) for one year, English version | P28: Including latest software release + free-of-charge updates (2 minimum) for one year, English version
A29: EEPVEU118A | B29: TPMX tool | C29: TPMX | D29: TPMX | E29: TPMX | F29: TPMX | G29: TPMX | H29: TPMX tool | L29: Languages: English, Italian, Dutch, German, French, Polish, Spanish | M29: Languages: English, Italian, Dutch, German, French, Polish, Spanish | N29: Languages: English, Italian, Dutch, German, French, Polish, Spanish | O29: Languages: English, Italian, Dutch, German, French, Polish, Spanish | P29: Languages: English, Italian, Dutch, German, French, Polish, Spanish
A30: DECKY2N20020S000 | B30: Breeze IV | C30: A/C | D30: A/C | E30: A/C | F30: A/C | G30: A/C | H30: BREEZE IV with printer | J30: 220-240V 50/60 Hz | L30: Fully automatic A/C service station for recovery, recycling and recharging of different types of refrigerants. The innovative and exclusive solution allows to set the R134a or the HFO1234yf gas directly during activation in the workshop. 4,3” touch screen display. Thermal printer included. With its modular features, the machine can be configured to meet the most specific needs. The upgrade with the Gas Analyser detects the different components of the refrigerant, and the result provides information about their percentages. C.A.R. method (Compressor Assisted Recharge) With the advanced technology based on an innovative solenoid valve system, BREEZE IV consumes 20% less energy than the previous models. Futuristic design. Less than 30” to open the revolving control panel. BREEZE IV grants excellent maneuverability as a result of the considerable axial distance between the two wheels. User-friendly | M30: Vollautomatisches Klimaservicegerät für die Rückgewinnung, das Recycling und das Nachfüllen verschiedener Kältemittel. Die innovative und exklusive Lösung macht es möglich, das gewünschte Kältemittel erst bei der Aktivierung in der Werkstatt festzulegen. 4,3 Zoll-Touchscreen-Display. Inklusive Thermodrucker Dank des modularen Aufbaus kann das Gerät entsprechend den spezifischen Anforderungen konfiguriert werden. Durch ein Upgrade mit der optionalen Gasanalyse werden die verschiedenen Bestandteile des Kältemittels erkannt und als Prozentsatz angezeigt. C.A.R.-Methode (Compressor Assisted Recharge). Die fortschrittliche Technologie basiert auf einem innovativen Magnetventilsystem, wodurch BREEZE IV im Vergleich zu Vorgängermodellen über 20% weniger Energie verbraucht. Futuristisches Design. In weniger als 30 Sekunden Zugriff auf das drehende Bedienpanel. BREEZE IV garantiert ausgezeichnete Lenkbarkeit dank großem Achsabstand zwischen den beiden Rädern. Benutzerfreundlich | N30: Fully automatic A/C service station for recovery, recycling and recharging of different types of refrigerants. The innovative and exclusive solution allows to set the R134a or the HFO1234yf gas directly during activation in the workshop. 4,3” touch screen display. Thermal printer included. With its modular features, the machine can be configured to meet the most specific needs. The upgrade with the Gas Analyser detects the different components of the refrigerant, and the result provides information about their percentages. C.A.R. method (Compressor Assisted Recharge) With the advanced technology based on an innovative solenoid valve system, BREEZE IV consumes 20% less energy than the previous models. Futuristic design. Less than 30” to open the revolving control panel. BREEZE IV grants excellent maneuverability as a result of the considerable axial distance between the two wheels. User-friendly | O30: Fully automatic A/C service station for recovery, recycling and recharging of different types of refrigerants. The innovative and exclusive solution allows to set the R134a or the HFO1234yf gas directly during activation in the workshop. 4,3” touch screen display. Thermal printer included. With its modular features, the machine can be configured to meet the most specific needs. The upgrade with the Gas Analyser detects the different components of the refrigerant, and the result provides information about their percentages. C.A.R. method (Compressor Assisted Recharge) With the advanced technology based on an innovative solenoid valve system, BREEZE IV consumes 20% less energy than the previous models. Futuristic design. Less than 30” to open the revolving control panel. BREEZE IV grants excellent maneuverability as a result of the considerable axial distance between the two wheels. User-friendly | P30: Fully automatic A/C service station for recovery, recycling and recharging of different types of refrigerants. The innovative and exclusive solution allows to set the R134a or the HFO1234yf gas directly during activation in the workshop. 4,3” touch screen display. Thermal printer included. With its modular features, the machine can be configured to meet the most specific needs. The upgrade with the Gas Analyser detects the different components of the refrigerant, and the result provides information about their percentages. C.A.R. method (Compressor Assisted Recharge) With the advanced technology based on an innovative solenoid valve system, BREEZE IV consumes 20% less energy than the previous models. Futuristic design. Less than 30” to open the revolving control panel. BREEZE IV grants excellent maneuverability as a result of the considerable axial distance between the two wheels. User-friendly
A31: DECKY2NR00000000 | B31: Breeze IV | C31: A/C | D31: A/C | E31: A/C | F31: A/C | G31: A/C | H31: KIT R134A for BREEZE IV | L31: Refrigerant Kit NEXT R134a | M31: Kühlmitttel-Kit NEXT R134a | N31: Refrigerant Kit NEXT R134a | O31: Refrigerant Kit NEXT R134a | P31: Refrigerant Kit NEXT R134a
A32: DECKY2NH00000000 | B32: Breeze IV | C32: A/C | D32: A/C | E32: A/C | F32: A/C | G32: A/C | H32: KIT HFO for BREEZE IV | L32: Refrigerant Kit NEXT HFO1234yf | M32: Kühlmittel-Kit NEXT HFO1234yf | N32: Refrigerant Kit NEXT HFO1234yf | O32: Refrigerant Kit NEXT HFO1234yf | P32: Refrigerant Kit NEXT HFO1234yf
A33: DECKY2F20020S000 | B33: Blizzard Qtech IV | C33: A/C | D33: A/C | E33: A/C | F33: A/C | G33: A/C | H33: BLIZZARD QTECH IV | J33: 220-240V 50/60 Hz | L33: Fully automatic A/C service station for recovery, recycling and recharging of different types of refrigerants. Menu navigation is intuitive, professional, designed for an easy and rapid work with the machine. 7’’ color touchscreen. WI-FI connectivity. Hybrid and Nitrogen leak detection. The unit can handle the hermetic oil and dye cartridges, as well as the hermetic and refillable containers. The result is easy serviceability: less than 30” to open the revolving control panel and less than 2 minutes to remove both plastic covers and access all the internal components. QTECH IV grants excellent maneuverability as a result of the considerable axial distance between the two wheels. User-friendly features: pressure gauges and touch screen are perfectly inclined for excellent ergonomics. | M33: Vollautomatisches Klimaservicegerät für die Rückgewinnung, das Recycling und das Nachfüllen verschiedener Kältemittel Die Menüführung ist intuitiv, professionell, einfach und für ein schnelles und sicheres Arbeiten mit dem Gerät ausgelegt 7‘‘ Farb-Touchscreen. WIFI-Konnektivität Hybrid- und Stickstoff-Lecksuche Das Gerät ist sowohl mit luftdicht verschlossenen Kartuschen als auch mit luftdicht verschlossenen wiederbefüllbaren Behältern für Öl und Kontrastmittel ausgestattet Insgesamt einfachere Wartung: in weniger als 30 Sekunden Zugriff auf das drehende Bedienpanel und in weniger als 2 Minuten Entfernen der beiden Kunststoffabdeckungen und Zugriff auf alle innenliegenden Komponenten. QTECH IV garantiert ausgezeichnete Lenkbarkeit dank großem Achsabstand zwischen den beiden Rädern. Benutzerfreundliche Merkmale: Druckmesser und Touchscreen sind ergonomisch angeordnet. | N33: Fully automatic A/C service station for recovery, recycling and recharging of different types of refrigerants. Menu navigation is intuitive, professional, designed for an easy and rapid work with the machine. 7’’ color touchscreen. WI-FI connectivity. Hybrid and Nitrogen leak detection. The unit can handle the hermetic oil and dye cartridges, as well as the hermetic and refillable containers. The result is easy serviceability: less than 30” to open the revolving control panel and less than 2 minutes to remove both plastic covers and access all the internal components. QTECH IV grants excellent maneuverability as a result of the considerable axial distance between the two wheels. User-friendly features: pressure gauges and touch screen are perfectly inclined for excellent ergonomics. | O33: Fully automatic A/C service station for recovery, recycling and recharging of different types of refrigerants. Menu navigation is intuitive, professional, designed for an easy and rapid work with the machine. 7’’ color touchscreen. WI-FI connectivity. Hybrid and Nitrogen leak detection. The unit can handle the hermetic oil and dye cartridges, as well as the hermetic and refillable containers. The result is easy serviceability: less than 30” to open the revolving control panel and less than 2 minutes to remove both plastic covers and access all the internal components. QTECH IV grants excellent maneuverability as a result of the considerable axial distance between the two wheels. User-friendly features: pressure gauges and touch screen are perfectly inclined for excellent ergonomics. | P33: Fully automatic A/C service station for recovery, recycling and recharging of different types of refrigerants. Menu navigation is intuitive, professional, designed for an easy and rapid work with the machine. 7’’ color touchscreen. WI-FI connectivity. Hybrid and Nitrogen leak detection. The unit can handle the hermetic oil and dye cartridges, as well as the hermetic and refillable containers. The result is easy serviceability: less than 30” to open the revolving control panel and less than 2 minutes to remove both plastic covers and access all the internal components. QTECH IV grants excellent maneuverability as a result of the considerable axial distance between the two wheels. User-friendly features: pressure gauges and touch screen are perfectly inclined for excellent ergonomics.
A34: DECKY2FR00000000 | B34: Blizzard Qtech IV | C34: A/C | D34: A/C | E34: A/C | F34: A/C | G34: A/C | H34: KIT R134A for QTECH IV | L34: Refrigerant Kit FLAG R134a | M34: Kühlmitttel-Kit FLAG R134a | N34: Refrigerant Kit FLAG R134a | O34: Refrigerant Kit FLAG R134a | P34: Refrigerant Kit FLAG R134a
A35: DECKY2FH00000000 | B35: Blizzard Qtech IV | C35: A/C | D35: A/C | E35: A/C | F35: A/C | G35: A/C | H35: KIT HFO for QTECH IV | L35: Refrigerant Kit FLAG HFO1234yf | M35: Kühlmittel-Kit FLAG HFO1234yf | N35: Refrigerant Kit FLAG HFO1234yf | O35: Refrigerant Kit FLAG HFO1234yf | P35: Refrigerant Kit FLAG HFO1234yf
A36: DECKK6T5A090S00B | B36: Koolkare Dual Gas 12 | C36: A/C | D36: A/C | E36: A/C | F36: A/C | G36: A/C | H36: KOOLKARE DUAL GAS 12 | J36: 220-240V 50/60 Hz | L36: Fully automatic air conditioning recycling unit for R134a and HFO12234yf. Separate tanks, compressors, gauges, hoses, couplers, oil and dye bottles for the two gases. Easy-to-read 7" display. Fully automatic or manual recycling procedure. Hermetic oil and dye bottle systems. Advanced database, 2x12 kg tank, prepared for flushing function (software). + Nitrogen or forming gas leak check enabled software. + Oil function for hybrid vehicles + Refrigerant identifier ready | M36: Vollautomatisches Klimaanlagen-Wartungs- und Servicegerät für R134a und HFO1234yf. Separate Tanks, Kompressoren, Manometer, Schläuche, Anschlüsse, Öl- und Kontrastmittelkartuschen für die beiden Gase. Gut leserliches 7" Display. Vollautomatischer oder manueller Recyclingablauf. Luftdicht verschlossene Öl- und Kontrastmittelbehälter, Komfortdatenbank, 2 x 12 kg Kältemitteltank, vorbereitet für Spülfunktion (Software). + Softwarevorbereitung für die Lecksuche mittels Stickstoff oder Formiergas + Ölfunktion für Hybrid-Fahrzeuge + vorbereitet für Kältemittelidentifizierungsgerät | N36: Fully automatic air conditioning recycling unit for R134a and HFO12234yf. Separate tanks, compressors, gauges, hoses, couplers, oil and dye bottles for the two gases. Easy-to-read 7" display. Fully automatic or manual recycling procedure. Hermetic oil and dye bottle systems. Advanced database, 2x12 kg tank, prepared for flushing function (software). + Nitrogen or forming gas leak check enabled software. + Oil function for hybrid vehicles + Refrigerant identifier ready | O36: Fully automatic air conditioning recycling unit for R134a and HFO12234yf. Separate tanks, compressors, gauges, hoses, couplers, oil and dye bottles for the two gases. Easy-to-read 7" display. Fully automatic or manual recycling procedure. Hermetic oil and dye bottle systems. Advanced database, 2x12 kg tank, prepared for flushing function (software). + Nitrogen or forming gas leak check enabled software. + Oil function for hybrid vehicles + Refrigerant identifier ready | P36: Fully automatic air conditioning recycling unit for R134a and HFO12234yf. Separate tanks, compressors, gauges, hoses, couplers, oil and dye bottles for the two gases. Easy-to-read 7" display. Fully automatic or manual recycling procedure. Hermetic oil and dye bottle systems. Advanced database, 2x12 kg tank, prepared for flushing function (software). + Nitrogen or forming gas leak check enabled software. + Oil function for hybrid vehicles + Refrigerant identifier ready
A37: DECKXK456A170S51 | B37: KoolKare HD-S | C37: A/C | D37: A/C | E37: A/C | F37: A/C | G37: A/C | H37: KoolKare HD-S | J37: 220-240V 50/60 Hz | L37: Ideally suited for large AIRCO systems. Robust design with easy mobility around the workshop, easy-to-use controls and displays, fully automatic or manual recycling procedure, large 40 kg tank, gear pump for quick charging of bigger systems, database, automatic dye injection. | M37: Ideal geeignet für große AIRCO Anlagen. Robustes werkstatttaugliches Design, leicht verständliche Displayanzeigen und Bedienungselemente, vollautomatischer und manueller Recyclingablauf, großer 40 kg Tank, Zahnradpumpe zum schnellen Befüllen größerer Anlagen, Datenbank, Kontrastmitteleinspritzung | N37: Ideally suited for large AIRCO systems. Robust design with easy mobility around the workshop, easy-to-use controls and displays, fully automatic or manual recycling procedure, large 40 kg tank, gear pump for quick charging of bigger systems, database, automatic dye injection. | O37: Ideally suited for large AIRCO systems. Robust design with easy mobility around the workshop, easy-to-use controls and displays, fully automatic or manual recycling procedure, large 40 kg tank, gear pump for quick charging of bigger systems, database, automatic dye injection. | P37: Ideally suited for large AIRCO systems. Robust design with easy mobility around the workshop, easy-to-use controls and displays, fully automatic or manual recycling procedure, large 40 kg tank, gear pump for quick charging of bigger systems, database, automatic dye injection.
A38: DECKY1R74420S000 | B38: ECO2KARE | C38: A/C | D38: A/C | E38: A/C | F38: A/C | G38: A/C | H38: ECO2KARE | J38: 220-240V 50/60 Hz | L38: Fully automatic air conditioning service unit for emptying, servicing and filling R744 air conditioning systems | M38: Fully automatic air conditioning service unit for emptying, servicing and filling R744 air conditioning systems | N38: Fully automatic air conditioning service unit for emptying, servicing and filling R744 air conditioning systems | O38: Fully automatic air conditioning service unit for emptying, servicing and filling R744 air conditioning systems | P38: Fully automatic air conditioning service unit for emptying, servicing and filling R744 air conditioning systems
A39: DECKY1ATF020S000 | B39: ATF Gearkare | C39: ATF | D39: ATF | E39: ATF | F39: ATF | G39: ATF | H39: ATF Gearkare | J39: 220-240V 50/60 Hz | L39: ATF Gearkare | M39: ATF Gearkare | N39: ATF Gearkare | O39: ATF Gearkare | P39: ATF Gearkare
A40: DECKY1ATF0000SIM | B40: ATF Gearkare | C40: ATF | D40: ATF | E40: ATF | F40: ATF | G40: ATF | H40: ATF Gearkare Simulator | J40: 220-240V 50/60 Hz | L40: ATF Gearkare Simulator | M40: ATF Gearkare Simulator | N40: ATF Gearkare Simulator | O40: ATF Gearkare Simulator | P40: ATF Gearkare Simulator

Sheet DB Accessori
A1: P/N | B1: CATEGORY - EN | C1: CATEGORY - DE | D1: CATEGORY - FR | E1: CATEGORY - ES | F1: CATEGORY - IT | G1: MODEL - EN | H1: MODEL - DE | I1: MODEL - FR | J1: MODEL - ES | K1: MODEL - IT | L1: DESCRIPTION - EN | M1: DESCRIPTION - DE | N1: DESCRIPTION - FR | O1: DESCRIPTION - ES | P1: DESCRIPTION - IT | Q1: COMPATIBILITY - EN | R1: COMPATIBILITY - DE | S1: COMPATIBILITY - FR | T1: COMPATIBILITY - ES | U1: COMPATIBILITY - IT
A2: PDL
A3: EAX0068L01A | B3: PDL | C3: PDL | D3: PDL | E3: PDL | F3: PDL | G3: Adaptor cable DA-5 | H3: Adapterkabel DA-5 zum Anschluss der alten Adapterkabel | I3: Adaptor cable DA-7 | J3: Adaptor cable DA-8 | K3: Adaptor cable DA-9 | L3: Adaptor cable DA-10 | M3: Adapterkabel DA-5 zum Anschluss der alten Adapterkabel | N3: Adaptor cable DA-12 | O3: Adaptor cable DA-13 | P3: Adaptor cable DA-14 | Q3: PDL 3000, 3200, 4000, 4100, 5000, 5500, 5600, 7100, 8000, 8100 | R3: PDL 3000, 3200, 4000, 4100, 5000, 5500, 5600, 7100, 8000, 8100 | S3: PDL 3000, 3200, 4000, 4100, 5000, 5500, 5600, 7100, 8000, 8100 | T3: PDL 3000, 3200, 4000, 4100, 5000, 5500, 5600, 7100, 8000, 8100 | U3: PDL 3000, 3200, 4000, 4100, 5000, 5500, 5600, 7100, 8000, 8100
A4: EAX0068L00C | B4: PDL | C4: PDL | D4: PDL | E4: PDL | F4: PDL | G4: OBDII data cable w/o light (16-pin cable) | H4: OBDII Datenkabel ohne Licht (16-adriges Kabel) | I4: OBDII data cable w/o light (16-pin cable) | J4: OBDII data cable w/o light (16-pin cable) | K4: OBDII data cable w/o light (16-pin cable) | L4: OBDII data cable w/o light (16-pin cable) | M4: OBDII Datenkabel ohne Licht (16-adriges Kabel) | N4: OBDII data cable w/o light (16-pin cable) | O4: OBDII data cable w/o light (16-pin cable) | P4: OBDII data cable w/o light (16-pin cable) | Q4: PDL 3000, 3200, 4000, 4100, 5000, 5500, 7100 | R4: PDL 3000, 3200, 4000, 4100, 5000, 5500, 7100 | S4: PDL 3000, 3200, 4000, 4100, 5000, 5500, 7100 | T4: PDL 3000, 3200, 4000, 4100, 5000, 5500, 7100 | U4: PDL 3000, 3200, 4000, 4100, 5000, 5500, 7100
A5: EAX0068L26A | B5: PDL | C5: PDL | D5: PDL | E5: PDL | F5: PDL | G5: OBDII data cable w/ light (16-pin cable) | H5: OBDII Datenkabel mit Licht (16-adriges Kabel) | I5: OBDII data cable w/ light (16-pin cable) | J5: OBDII data cable w/ light (16-pin cable) | K5: OBDII data cable w/ light (16-pin cable) | L5: OBDII data cable w/ light (16-pin cable) | M5: OBDII Datenkabel mit Licht (16-adriges Kabel) | N5: OBDII data cable w/ light (16-pin cable) | O5: OBDII data cable w/ light (16-pin cable) | P5: OBDII data cable w/ light (16-pin cable) | Q5: PDL 4000, 4100, 5000, 5500, 5600, 7100, 8000, 8100 | R5: PDL 4000, 4100, 5000, 5500, 5600, 7100, 8000, 8100 | S5: PDL 4000, 4100, 5000, 5500, 5600, 7100, 8000, 8100 | T5: PDL 4000, 4100, 5000, 5500, 5600, 7100, 8000, 8100 | U5: PDL 4000, 4100, 5000, 5500, 5600, 7100, 8000, 8100
A6: EAX0072L17A | B6: PDL | C6: PDL | D6: PDL | E6: PDL | F6: PDL | G6: DA-4EA Ethernet DOIP data cable | H6: DA-4EA Ethernet DOIP Datenkabel | I6: DA-4EA Ethernet DOIP data cable | J6: DA-4EA Ethernet DOIP data cable | K6: DA-4EA Ethernet DOIP data cable | L6: DA-4EA Ethernet DOIP data cable | M6: DA-4EA Ethernet DOIP Datenkabel | N6: DA-4EA Ethernet DOIP data cable | O6: DA-4EA Ethernet DOIP data cable | P6: DA-4EA Ethernet DOIP data cable | Q6: PDL 3200, 4100, 5500, 5600, 7100, 8000, 8100 | R6: PDL 3200, 4100, 5500, 5600, 7100, 8000, 8100 | S6: PDL 3200, 4100, 5500, 5600, 7100, 8000, 8100 | T6: PDL 3200, 4100, 5500, 5600, 7100, 8000, 8100 | U6: PDL 3200, 4100, 5500, 5600, 7100, 8000, 8100
A7: 2-03965A | B7: PDL | C7: PDL | D7: PDL | E7: PDL | F7: PDL | G7: Soft Case | H7: Transportkoffer (Soft Case) | I7: Soft Case | J7: Soft Case | K7: Soft Case | L7: Soft Case | M7: Transportkoffer (Soft Case) | N7: Soft Case | O7: Soft Case | P7: Soft Case | Q7: PDL 3200, 4100, 5600, 7100, 8000, 8100 | R7: PDL 3200, 4100, 5600, 7100, 8000, 8100 | S7: PDL 3200, 4100, 5600, 7100, 8000, 8100 | T7: PDL 3200, 4100, 5600, 7100, 8000, 8100 | U7: PDL 3200, 4100, 5600, 7100, 8000, 8100
A8: EAC0111L76A3 | B8: PDL | C8: PDL | D8: PDL | E8: PDL | F8: PDL | G8: Screen Protector 3 Pack | H8: Bildschirmschutz (3 Satz) | I8: Screen Protector 3 Pack | J8: Screen Protector 3 Pack | K8: Screen Protector 3 Pack | L8: Screen Protector 3 Pack | M8: Bildschirmschutz (3 Satz) | N8: Screen Protector 3 Pack | O8: Screen Protector 3 Pack | P8: Screen Protector 3 Pack | Q8: PDL 4000, 4100, 5600, 8000, 8100 | R8: PDL 4000, 4100, 5600, 8000, 8100 | S8: PDL 4000, 4100, 5600, 8000, 8100 | T8: PDL 4000, 4100, 5600, 8000, 8100 | U8: PDL 4000, 4100, 5600, 8000, 8100
A9: EESP115A-3.2 | B9: PDL | C9: PDL | D9: PDL | E9: PDL | F9: PDL | G9: PDL 3200 Software update for 1 year (2 minimum per year) | H9: PDL 3200 Software-Update für 1 Jahr (mindestens 2 pro Jahr) | I9: PDL 3200 Software update for 1 year (2 minimum per year) | J9: PDL 3200 Software update for 1 year (2 minimum per year) | K9: PDL 3200 Software update for 1 year (2 minimum per year) | L9: PDL 3200 Software update for 1 year (2 minimum per year) | M9: PDL 3200 Software-Update für 1 Jahr (mindestens 2 pro Jahr) | N9: PDL 3200 Software update for 1 year (2 minimum per year) | O9: PDL 3200 Software update for 1 year (2 minimum per year) | P9: PDL 3200 Software update for 1 year (2 minimum per year) | Q9: PDL 3200 | R9: PDL 3200 | S9: PDL 3200 | T9: PDL 3200 | U9: PDL 3200
A10: EESP116A-3.2 | B10: PDL | C10: PDL | D10: PDL | E10: PDL | F10: PDL | G10: PDL 3200 Software update for 1 year (2 minimum per year) after termination plus charge for re-activation | H10: PDL 3200 Software-Update für 1 Jahr (mindestens 2 pro Jahr) nach Kündigung, plus Gebühr für Reaktivierung | I10: PDL 3200 Software update for 1 year (2 minimum per year) after termination plus charge for re-activation | J10: PDL 3200 Software update for 1 year (2 minimum per year) after termination plus charge for re-activation | K10: PDL 3200 Software update for 1 year (2 minimum per year) after termination plus charge for re-activation | L10: PDL 3200 Software update for 1 year (2 minimum per year) after termination plus charge for re-activation | M10: PDL 3200 Software-Update für 1 Jahr (mindestens 2 pro Jahr) nach Kündigung, plus Gebühr für Reaktivierung | N10: PDL 3200 Software update for 1 year (2 minimum per year) after termination plus charge for re-activation | O10: PDL 3200 Software update for 1 year (2 minimum per year) after termination plus charge for re-activation | P10: PDL 3200 Software update for 1 year (2 minimum per year) after termination plus charge for re-activation | Q10: PDL 3200 | R10: PDL 3200 | S10: PDL 3200 | T10: PDL 3200 | U10: PDL 3200
A11: EESP118A-3.2 | B11: PDL | C11: PDL | D11: PDL | E11: PDL | F11: PDL | G11: PDL 3200 Software update for 2 years (2 minimum per year) | H11: PDL 3200 Software-Update für 2 Jahre (mindestens 2 pro Jahr) | I11: PDL 3200 Software update for 2 years (2 minimum per year) | J11: PDL 3200 Software update for 2 years (2 minimum per year) | K11: PDL 3200 Software update for 2 years (2 minimum per year) | L11: PDL 3200 Software update for 2 years (2 minimum per year) | M11: PDL 3200 Software-Update für 2 Jahre (mindestens 2 pro Jahr) | N11: PDL 3200 Software update for 2 years (2 minimum per year) | O11: PDL 3200 Software update for 2 years (2 minimum per year) | P11: PDL 3200 Software update for 2 years (2 minimum per year) | Q11: PDL 3200 | R11: PDL 3200 | S11: PDL 3200 | T11: PDL 3200 | U11: PDL 3200
A12: EESP115A-4.1 | B12: PDL | C12: PDL | D12: PDL | E12: PDL | F12: PDL | G12: PDL 4100 Software update for 1 year (2 minimum per year) | H12: PDL 4100 Software-Update für 1 Jahr (mindestens 2 pro Jahr) | I12: PDL 4100 Software update for 1 year (2 minimum per year) | J12: PDL 4100 Software update for 1 year (2 minimum per year) | K12: PDL 4100 Software update for 1 year (2 minimum per year) | L12: PDL 4100 Software update for 1 year (2 minimum per year) | M12: PDL 4100 Software-Update für 1 Jahr (mindestens 2 pro Jahr) | N12: PDL 4100 Software update for 1 year (2 minimum per year) | O12: PDL 4100 Software update for 1 year (2 minimum per year) | P12: PDL 4100 Software update for 1 year (2 minimum per year) | Q12: PDL 4100 | R12: PDL 4100 | S12: PDL 4100 | T12: PDL 4100 | U12: PDL 4100
A13: EESP116A-4.1 | B13: PDL | C13: PDL | D13: PDL | E13: PDL | F13: PDL | G13: PDL 4100 Software update for 1 year (2 minimum per year) after termination plus charge for re-activation | H13: PDL 4100Software-Update für 1 Jahr (mindestens 2 pro Jahr) nach Kündigung, plus Gebühr für Reaktivierung | I13: PDL 4100 Software update for 1 year (2 minimum per year) after termination plus charge for re-activation | J13: PDL 4100 Software update for 1 year (2 minimum per year) after termination plus charge for re-activation | K13: PDL 4100 Software update for 1 year (2 minimum per year) after termination plus charge for re-activation | L13: PDL 4100 Software update for 1 year (2 minimum per year) after termination plus charge for re-activation | M13: PDL 4100Software-Update für 1 Jahr (mindestens 2 pro Jahr) nach Kündigung, plus Gebühr für Reaktivierung | N13: PDL 4100 Software update for 1 year (2 minimum per year) after termination plus charge for re-activation | O13: PDL 4100 Software update for 1 year (2 minimum per year) after termination plus charge for re-activation | P13: PDL 4100 Software update for 1 year (2 minimum per year) after termination plus charge for re-activation | Q13: PDL 4100 | R13: PDL 4100 | S13: PDL 4100 | T13: PDL 4100 | U13: PDL 4100
A14: EESP118A-4.1 | B14: PDL | C14: PDL | D14: PDL | E14: PDL | F14: PDL | G14: PDL 4100 Software update for 2 years (2 minimum per year) | H14: PDL 4100 Software-Update für 2 Jahre (mindestens 2 pro Jahr) | I14: PDL 4100 Software update for 2 years (2 minimum per year) | J14: PDL 4100 Software update for 2 years (2 minimum per year) | K14: PDL 4100 Software update for 2 years (2 minimum per year) | L14: PDL 4100 Software update for 2 years (2 minimum per year) | M14: PDL 4100 Software-Update für 2 Jahre (mindestens 2 pro Jahr) | N14: PDL 4100 Software update for 2 years (2 minimum per year) | O14: PDL 4100 Software update for 2 years (2 minimum per year) | P14: PDL 4100 Software update for 2 years (2 minimum per year) | Q14: PDL 4100 | R14: PDL 4100 | S14: PDL 4100 | T14: PDL 4100 | U14: PDL 4100
... A42: EAK0294B22A | B42: PDL | C42: PDL | D42: PDL | E42: PDL | F42: PDL | G42: Set of 4 probes for lab scope | H42: Prüfspitzensatz für Laborskop, 4 Stück | I42: Set of 4 probes for lab scope | J42: Set of 4 probes for lab scope | K42: Set of 4 probes for lab scope | L42: Set of 4 probes for lab scope | M42: Prüfspitzensatz für Laborskop, 4 Stück | N42: Set of 4 probes for lab scope | O42: Set of 4 probes for lab scope | P42: Set of 4 probes for lab scope | Q42: PDL 5500, PDL 5600, PDL 8000 | R42: PDL 5500, PDL 5600, PDL 8000 | S42: PDL 5500, PDL 5600, PDL 8000 | T42: PDL 5500, PDL 5600, PDL 8000 | U42: PDL 5500, PDL 5600, PDL 8000
B43: AC
A44: DECKKIT.HYBRID | B44: A/C | C44: A/C | D44: A/C | E44: A/C | F44: A/C | G44: Kit Hybrid Upgrade option HFO1234yf and R134a | H44: Hybrid-Upgradekit für HFO1234yf und R134a | I44: Kit Hybrid Upgrade option HFO1234yf and R134a | J44: Kit Hybrid Upgrade option HFO1234yf and R134a | K44: Kit Hybrid Upgrade option HFO1234yf and R134a | L44: Kit Hybrid Upgrade option HFO1234yf and R134a | M44: Hybrid-Upgradekit für HFO1234yf und R134a | N44: Kit Hybrid Upgrade option HFO1234yf and R134a | O44: Kit Hybrid Upgrade option HFO1234yf and R134a | P44: Kit Hybrid Upgrade option HFO1234yf and R134a | Q44: Breeze IV | R44: Breeze IV | S44: Breeze IV | T44: Breeze IV | U44: Breeze IV
A45: DECKXS180.000000 | B45: A/C | C45: A/C | D45: A/C | E45: A/C | F45: A/C | G45: Gas identifier HFO for single and dual gas units | H45: Kältemittelidentifizierungsgerät HFO für Ein- und Dualgas-Geräte | I45: Gas identifier HFO for single and dual gas units | J45: Gas identifier HFO for single and dual gas units | K45: Gas identifier HFO for single and dual gas units | L45: Gas identifier HFO for single and dual gas units | M45: Kältemittelidentifizierungsgerät HFO für Ein- und Dualgas-Geräte | N45: Gas identifier HFO for single and dual gas units | O45: Gas identifier HFO for single and dual gas units | P45: Gas identifier HFO for single and dual gas units | Q45: Dual Gas, Qtech III | R45: Dual Gas, Qtech III | S45: Dual Gas, Qtech III | T45: Dual Gas, Qtech III | U45: Dual Gas, Qtech III
A46: DECKKIT.GAS.R134 | B46: A/C | C46: A/C | D46: A/C | E46: A/C | F46: A/C | G46: Adapter kit R134a for gas analiser KIT.GAS | H46: Adapterkit R134a für Gastester | I46: Adapter kit R134a for gas analiser KIT.GAS | J46: Adapter kit R134a for gas analiser KIT.GAS | K46: Adapter kit R134a for gas analiser KIT.GAS | L46: Adapter kit R134a for gas analiser KIT.GAS | M46: Adapterkit R134a für Gastester | N46: Adapter kit R134a for gas analiser KIT.GAS | O46: Adapter kit R134a for gas analiser KIT.GAS | P46: Adapter kit R134a for gas analiser KIT.GAS | Q46: Breeze IV, Qtech IV | R46: Breeze IV, Qtech IV | S46: Breeze IV, Qtech IV | T46: Breeze IV, Qtech IV | U46: Breeze IV, Qtech IV
A47: DECKKIT.WIFI-N | B47: A/C | C47: A/C | D47: A/C | E47: A/C | F47: A/C | G47: Connectivity kit EVO | H47: Vernetzungskit EVO | I47: Connectivity kit EVO | J47: Connectivity kit EVO | K47: Connectivity kit EVO | L47: Connectivity kit EVO | M47: Vernetzungskit EVO | N47: Connectivity kit EVO | O47: Connectivity kit EVO | P47: Connectivity kit EVO | Q47: Breeze IV | R47: Breeze IV | S47: Breeze IV | T47: Breeze IV | U47: Breeze IV
A48: DECKTUB1148 | B48: A/C | C48: A/C | D48: A/C | E48: A/C | F48: A/C | G48: R134A Service hose 6 m, red, for QTECH II / III units and Breeze, male/female | H48: Serviceschlauch 6 m | I48: R134A Service hose 6 m, red, for QTECH II / III units and Breeze, male/female | J48: R134A Service hose 6 m, red, for QTECH II / III units and Breeze, male/female | K48: R134A Service hose 6 m, red, for QTECH II / III units and Breeze, male/female | L48: R134A Service hose 6 m, red, for QTECH II / III units and Breeze, male/female | M48: Serviceschlauch 6 m | N48: R134A Service hose 6 m, red, for QTECH II / III units and Breeze, male/female | O48: R134A Service hose 6 m, red, for QTECH II / III units and Breeze, male/female | P48: R134A Service hose 6 m, red, for QTECH II / III units and Breeze, male/female | Q48: All A/C machines | R48: All A/C machines | S48: All A/C machines | T48: All A/C machines | U48: All A/C machines
A49: DECKTUB1149 | B49: A/C | C49: A/C | D49: A/C | E49: A/C | F49: A/C | G49: R134A Service hose 6 m, blue, for QTECH II / III units and Breeze, male/female | H49: Serviceschlauch 6 m | I49: R134A Service hose 6 m, blue, for QTECH II / III units and Breeze, male/female | J49: R134A Service hose 6 m, blue, for QTECH II / III units and Breeze, male/female | K49: R134A Service hose 6 m, blue, for QTECH II / III units and Breeze, male/female | L49: R134A Service hose 6 m, blue, for QTECH II / III units and Breeze, male/female | M49: Serviceschlauch 6 m | N49: R134A Service hose 6 m, blue, for QTECH II / III units and Breeze, male/female | O49: R134A Service hose 6 m, blue, for QTECH II / III units and Breeze, male/female | P49: R134A Service hose 6 m, blue, for QTECH II / III units and Breeze, male/female | Q49: All A/C machines | R49: All A/C machines | S49: All A/C machines | T49: All A/C machines | U49: All A/C machines
A50: DECKGRTUB0001 | B50: A/C | C50: A/C | D50: A/C | E50: A/C | F50: A/C | G50: KoolKare nitogen/forming gas hose kit; for connection to a nitrogen or forming gas fitting, equipment end with hose and quick coupling. Spare parts, accessories as standard option with a Koolkare nitrogen/forming gas option | H50: KoolKare Schlauchsatz ; zum Anschluss an eine Stickstoff- bzw. Formiergasarmatur, inkl. Schlauch und Schnellkupplung geräteseitig. Ersatzteil, da Standardzubehör eines KK mit Stickstoff-/Formiergasoption. | I50: KoolKare nitogen/forming gas hose kit; for connection to a nitrogen or forming gas fitting, equipment end with hose and quick coupling. Spare parts, accessories as standard option with a Koolkare nitrogen/forming gas option | J50: KoolKare nitogen/forming gas hose kit; for connection to a nitrogen or forming gas fitting, equipment end with hose and quick coupling. Spare parts, accessories as standard option with a Koolkare nitrogen/forming gas option | K50: KoolKare nitogen/forming gas hose kit; for connection to a nitrogen or forming gas fitting, equipment end with hose and quick coupling. Spare parts, accessories as standard option with a Koolkare nitrogen/forming gas option | L50: KoolKare nitogen/forming gas hose kit; for connection to a nitrogen or forming gas fitting, equipment end with hose and quick coupling. Spare parts, accessories as standard option with a Koolkare nitrogen/forming gas option | M50: KoolKare Schlauchsatz ; zum Anschluss an eine Stickstoff- bzw. Formiergasarmatur, inkl. Schlauch und Schnellkupplung geräteseitig. Ersatzteil, da Standardzubehör eines KK mit Stickstoff-/Formiergasoption. | N50: KoolKare nitogen/forming gas hose kit; for connection to a nitrogen or forming gas fitting, equipment end with hose and quick coupling. Spare parts, accessories as standard option with a Koolkare nitrogen/forming gas option | O50: KoolKare nitogen/forming gas hose kit; for connection to a nitrogen or forming gas fitting, equipment end with hose and quick coupling. Spare parts, accessories as standard option with a Koolkare nitrogen/forming gas option | P50: KoolKare nitogen/forming gas hose kit; for connection to a nitrogen or forming gas fitting, equipment end with hose and quick coupling. Spare parts, accessories as standard option with a Koolkare nitrogen/forming gas option | Q50: Qtech IV, Dual Gas, Qtech III | R50: Qtech IV, Dual Gas, Qtech III | S50: Qtech IV, Dual Gas, Qtech III | T50: Qtech IV, Dual Gas, Qtech III | U50: Qtech IV, Dual Gas, Qtech III
A51: DECKAEK322 | B51: A/C | C51: A/C | D51: A/C | E51: A/C | F51: A/C | G51: Bottle of Saniflux liquid (1000 ml) | H51: Flasche Saniflux Liquid (1000 ml) | I51: Bottle of Saniflux liquid (1000 ml) | J51: Bottle of Saniflux liquid (1000 ml) | K51: Bottle of Saniflux liquid (1000 ml) | L51: Bottle of Saniflux liquid (1000 ml) | M51: Flasche Saniflux Liquid (1000 ml) | N51: Bottle of Saniflux liquid (1000 ml) | O51: Bottle of Saniflux liquid (1000 ml) | P51: Bottle of Saniflux liquid (1000 ml) | Q51: All A/C machines | R51: All A/C machines | S51: All A/C machines | T51: All A/C machines | U51: All A/C machines
A52: DECKAEK275 | B52: A/C | C52: A/C | D52: A/C | E52: A/C | F52: A/C | G52: Oil bottle PAG100, R134, HFO1234yf, mechanical and electrical compressor, 6 x 250 ml | H52: Ölbehälter PAG100, R134, HFO1234yf, 6 x 250 ml | I52: Oil bottle PAG100, R134, HFO1234yf, mechanical and electrical compressor, 6 x 250 ml | J52: Oil bottle PAG100, R134, HFO1234yf, mechanical and electrical compressor, 6 x 250 ml | K52: Oil bottle PAG100, R134, HFO1234yf, mechanical and electrical compressor, 6 x 250 ml | L52: Oil bottle PAG100, R134, HFO1234yf, mechanical and electrical compressor, 6 x 250 ml | M52: Ölbehälter PAG100, R134, HFO1234yf, 6 x 250 ml | N52: Oil bottle PAG100, R134, HFO1234yf, mechanical and electrical compressor, 6 x 250 ml | O52: Oil bottle PAG100, R134, HFO1234yf, mechanical and electrical compressor, 6 x 250 ml | P52: Oil bottle PAG100, R134, HFO1234yf, mechanical and electrical compressor, 6 x 250 ml | Q52: All A/C machines | R52: All A/C machines | S52: All A/C machines | T52: All A/C machines | U52: All A/C machines
A53: DECKAEK275-N | B53: A/C | C53: A/C | D53: A/C | E53: A/C | F53: A/C | G53: Sealed oil cartridge PAG100 - 250ml for R134a, HFO1234yf mechanical and electric compressor | H53: Hermetische Ölpatrone, PAG100, 250 ml für HFO1234yf und R134a, mechanischer und elektrischer Kompressor | I53: Sealed oil cartridge PAG100 - 250ml for R134a, HFO1234yf mechanical and electric compressor | J53: Sealed oil cartridge PAG100 - 250ml for R134a, HFO1234yf mechanical and electric compressor | K53: Sealed oil cartridge PAG100 - 250ml for R134a, HFO1234yf mechanical and electric compressor | L53: Sealed oil cartridge PAG100 - 250ml for R134a, HFO1234yf mechanical and electric compressor | M53: Hermetische Ölpatrone, PAG100, 250 ml für HFO1234yf und R134a, mechanischer und elektrischer Kompressor | N53: Sealed oil cartridge PAG100 - 250ml for R134a, HFO1234yf mechanical and electric compressor | O53: Sealed oil cartridge PAG100 - 250ml for R134a, HFO1234yf mechanical and electric compressor | P53: Sealed oil cartridge PAG100 - 250ml for R134a, HFO1234yf mechanical and electric compressor | Q53: All A/C machines | R53: All A/C machines | S53: All A/C machines | T53: All A/C machines | U53: All A/C machines
A54: DECKAEK276 | B54: A/C | C54: A/C | D54: A/C | E54: A/C | F54: A/C | G54: Oil bottle PAG46, R134, HFO1234yf, mechanical and electrical compressor, 6 x 250 ml | H54: Ölbehälter PAG45, R134, HFO1234yf, 6 x 250 ml | I54: Oil bottle PAG46, R134, HFO1234yf, mechanical and electrical compressor, 6 x 250 ml | J54: Oil bottle PAG46, R134, HFO1234yf, mechanical and electrical compressor, 6 x 250 ml | K54: Oil bottle PAG46, R134, HFO1234yf, mechanical and electrical compressor, 6 x 250 ml | L54: Oil bottle PAG46, R134, HFO1234yf, mechanical and electrical compressor, 6 x 250 ml | M54: Ölbehälter PAG45, R134, HFO1234yf, 6 x 250 ml | N54: Oil bottle PAG46, R134, HFO1234yf, mechanical and electrical compressor, 6 x 250 ml | O54: Oil bottle PAG46, R134, HFO1234yf, mechanical and electrical compressor, 6 x 250 ml | P54: Oil bottle PAG46, R134, HFO1234yf, mechanical and electrical compressor, 6 x 250 ml | Q54: All A/C machines | R54: All A/C machines | S54: All A/C machines | T54: All A/C machines | U54: All A/C machines
A55: DECKAEK276-N | B55: A/C | C55: A/C | D55: A/C | E55: A/C | F55: A/C | G55: Sealed oil cartridge PAG46 - 250ml for R134a, HFO1234yf mechanical and electric compressor | H55: Hermetische Ölpatrone, PAG46, 250 ml für HFO1234yf und R134a, mechanischer und elektrischer Kompressor | I55: Sealed oil cartridge PAG46 - 250ml for R134a, HFO1234yf mechanical and electric compressor | J55: Sealed oil cartridge PAG46 - 250ml for R134a, HFO1234yf mechanical and electric compressor | K55: Sealed oil cartridge PAG46 - 250ml for R134a, HFO1234yf mechanical and electric compressor | L55: Sealed oil cartridge PAG46 - 250ml for R134a, HFO1234yf mechanical and electric compressor | M55: Hermetische Ölpatrone, PAG46, 250 ml für HFO1234yf und R134a, mechanischer und elektrischer Kompressor | N55: Sealed oil cartridge PAG46 - 250ml for R134a, HFO1234yf mechanical and electric compressor | O55: Sealed oil cartridge PAG46 - 250ml for R134a, HFO1234yf mechanical and electric compressor | P55: Sealed oil cartridge PAG46 - 250ml for R134a, HFO1234yf mechanical and electric compressor | Q55: All A/C machines | R55: All A/C machines | S55: All A/C machines | T55: All A/C machines | U55: All A/C machines
... A92: DECKKIT.STM | B92: A/C (service) | C92: A/C (service) | D92: A/C (service) | E92: A/C (service) | F92: A/C (service) | G92: Thermal Printer Upgrade option | H92: Thermodrucker-Upgrade | I92: Thermal Printer Upgrade option | J92: Thermal Printer Upgrade option | K92: Thermal Printer Upgrade option | L92: Thermal Printer Upgrade option | M92: Thermodrucker-Upgrade | N92: Thermal Printer Upgrade option | O92: Thermal Printer Upgrade option | P92: Thermal Printer Upgrade option | Q92: Breeze IV | R92: Breeze IV | S92: Breeze IV | T92: Breeze IV | U92: Breeze IV
B93: ATF | C93: WECHSELFLANSCHE | D93: CONTRE-BRIDES | E93: PLATOS DE SOPORTE POR LOS PERNOS | F93: PERNI PER FLANGE A COLONNE | G93: AC | H93: Zentrierbolzen Für Universal-Wechselflansch 32052 | I93: Boulon de centrage pour contre-bride universel 32052 | J93: Pernos de centrado para placa de plato universal 32052 | K93: Bulloni di centraggio per flangia universale 32052 | L93: 1 Set = 5 off - Ø 24 mm - L 100 mm Centring cone, spring-suspended | M93: 1 Satz = 5 Stück Ø 24 mm - L 100 mm Zentrierkegel, gefedert | N93: 1 jeu = 5 pièces Ø 24 mm - L 100 mm Tête conique à ressort | O93: 1 Juego = 5 unidades Ø 24 mm - L 100 mm Cono de centrado, suspendido por resorte | P93: 1 set = 5 unità - Ø 24 mm - L 100 mm Cono di centraggio, con molla
A94: DECKKIT.ATF | B94: ATF | C94: ATF | D94: ATF | E94: ATF | F94: ATF | G94: ATF BASE KIT ADAPTERS | H94: ATF BASIS KIT ADAPTER | I94: ATF BASE KIT ADAPTERS | J94: ATF BASE KIT ADAPTERS | K94: ATF BASE KIT ADAPTERS | L94: ATF BASE KIT ADAPTERS | M94: ATF BASIS KIT ADAPTER | N94: ATF BASE KIT ADAPTERS | O94: ATF BASE KIT ADAPTERS | P94: ATF BASE KIT ADAPTERS | Q94: ATF | R94: ATF | S94: ATF | T94: ATF | U94: ATF
A95: DECKLEVELKIT-ATF | B95: ATF | C95: ATF | D95: ATF | E95: ATF | F95: ATF | G95: OIL LEVEL CONNECTORS | H95: KIT ADAPTER FÜR ÖLSTAND | I95: OIL LEVEL CONNECTORS | J95: OIL LEVEL CONNECTORS | K95: OIL LEVEL CONNECTORS | L95: OIL LEVEL CONNECTORS | M95: KIT ADAPTER FÜR ÖLSTAND | N95: OIL LEVEL CONNECTORS | O95: OIL LEVEL CONNECTORS | P95: OIL LEVEL CONNECTORS | Q95: ATF | R95: ATF | S95: ATF | T95: ATF | U95: ATF
A96: DECKDB.ATF | B96: ATF | C96: ATF | D96: ATF | E96: ATF | F96: ATF | G96: LOCAL DATABASE UPDATE | H96: LOKALES DATENBANK-UPDATE | I96: LOCAL DATABASE UPDATE | J96: LOCAL DATABASE UPDATE | K96: LOCAL DATABASE UPDATE | L96: LOCAL DATABASE UPDATE | M96: LOKALES DATENBANK-UPDATE | N96: LOCAL DATABASE UPDATE | O96: LOCAL DATABASE UPDATE | P96: LOCAL DATABASE UPDATE | Q96: ATF | R96: ATF | S96: ATF | T96: ATF | U96: ATF
A97: DECKDB.ATF-LICENSE | B97: ATF | C97: ATF | D97: ATF | E97: ATF | F97: ATF | G97: LOCAL DATABASE UPDATE + WEB LICENSE | H97: LOCAL DATABASE UPDATE + WEB LICENSE | I97: LOCAL DATABASE UPDATE + WEB LICENSE | J97: LOCAL DATABASE UPDATE + WEB LICENSE | K97: LOCAL DATABASE UPDATE + WEB LICENSE | L97: LOCAL DATABASE UPDATE + WEB LICENSE | M97: LOCAL DATABASE UPDATE + WEB LICENSE | N97: LOCAL DATABASE UPDATE + WEB LICENSE | O97: LOCAL DATABASE UPDATE + WEB LICENSE | P97: LOCAL DATABASE UPDATE + WEB LICENSE | Q97: ATF | R97: ATF | S97: ATF | T97: ATF | U97: ATF
A98: DECKCNT0031 | B98: ATF | C98: ATF | D98: ATF | E98: ATF | F98: ATF | G98: NEW CANISTER 20 liters | H98: NEUER KANISTER 20 Liter | I98: NEW CANISTER 20 liters | J98: NEW CANISTER 20 liters | K98: NEW CANISTER 20 liters | L98: NEW CANISTER 20 liters | M98: NEUER KANISTER 20 Liter | N98: NEW CANISTER 20 liters | O98: NEW CANISTER 20 liters | P98: NEW CANISTER 20 liters | Q98: ATF | R98: ATF | S98: ATF | T98: ATF | U98: ATF
A99: DECKFLT.ATF.1000 | B99: ATF | C99: ATF | D99: ATF | E99: ATF | F99: ATF | G99: 2 x FILTER CARTRIDGE | H99: 3 x FILTERPATRONE | I99: 2 x FILTER CARTRIDGE | J99: 2 x FILTER CARTRIDGE | K99: 2 x FILTER CARTRIDGE | L99: 2 x FILTER CARTRIDGE | M99: 8 x FILTERPATRONE | N99: 2 x FILTER CARTRIDGE | O99: 2 x FILTER CARTRIDGE | P99: 2 x FILTER CARTRIDGE | Q99: ATF | R99: ATF | S99: ATF | T99: ATF | U99: ATF
A100: DECKRAC8201 | B100: ATF | C100: ATF | D100: ATF | E100: ATF | F100: ATF | G100: A1 | H100: A1 | I100: A1 | J100: A1 | K100: A1 | L100: A1-FITTING FOR JAGUAR, MERCEDES-BENZ, MITSUBISHI, SSANGYONG | M100: A1-ADAPTER FÜR JAGUAR, MERCEDES-BENZ, MITSUBISHI, SSANGYONG | N100: A1-FITTING FOR JAGUAR, MERCEDES-BENZ, MITSUBISHI, SSANGYONG | O100: A1-FITTING FOR JAGUAR, MERCEDES-BENZ, MITSUBISHI, SSANGYONG | P100: A1-FITTING FOR JAGUAR, MERCEDES-BENZ, MITSUBISHI, SSANGYONG | Q100: ATF | R100: ATF | S100: ATF | T100: ATF | U100: ATF
A101: DECKRAC8202 | B101: ATF | C101: ATF | D101: ATF | E101: ATF | F101: ATF | G101: A2 | H101: A2 | I101: A2 | J101: A2 | K101: A2 | L101: A2-FITTING FOR JAGUAR, MERCEDES-BENZ, SSANGYONG | M101: A2-ADAPTER FÜR JAGUAR, MERCEDES-BENZ, SSANGYONG | N101: A2-FITTING FOR JAGUAR, MERCEDES-BENZ, SSANGYONG | O101: A2-FITTING FOR JAGUAR, MERCEDES-BENZ, SSANGYONG | P101: A2-FITTING FOR JAGUAR, MERCEDES-BENZ, SSANGYONG | Q101: ATF | R101: ATF | S101: ATF | T101: ATF | U101: ATF
A102: DECKRAC8203 | B102: ATF | C102: ATF | D102: ATF | E102: ATF | F102: ATF | G102: A3 | H102: A3 | I102: A3 | J102: A3 | K102: A3 | L102: A3-FITTING FOR JEEP, FIAT, ALFA ROMEO, OPEL, CITROEN | M102: A3-ADAPTER FÜR JEEP, FIAT, ALFA ROMEO, OPEL, CITROEN | N102: A3-FITTING FOR JEEP, FIAT, ALFA ROMEO, OPEL, CITROEN | O102: A3-FITTING FOR JEEP, FIAT, ALFA ROMEO, OPEL, CITROEN | P102: A3-FITTING FOR JEEP, FIAT, ALFA ROMEO, OPEL, CITROEN | Q102: ATF | R102: ATF | S102: ATF | T102: ATF | U102: ATF
A103: DECKRAC8204 | B103: ATF | C103: ATF | D103: ATF | E103: ATF | F103: ATF | G103: A4 | H103: A4 | I103: A4 | J103: A4 | K103: A4 | L103: A4-FITTING FOR DSG AUDI, VOLKSWAGEN, SKODA | M103: A4-ADAPTER FÜR DSG AUDI, VOLKSWAGEN, SKODA | N103: A4-FITTING FOR DSG AUDI, VOLKSWAGEN, SKODA | O103: A4-FITTING FOR DSG AUDI, VOLKSWAGEN, SKODA | P103: A4-FITTING FOR DSG AUDI, VOLKSWAGEN, SKODA | Q103: ATF | R103: ATF | S103: ATF | T103: ATF | U103: ATF
A104: DECKRAC8205 | B104: ATF | C104: ATF | D104: ATF | E104: ATF | F104: ATF | G104: A5 | H104: A5 | I104: A5 | J104: A5 | K104: A5 | L104: A5-FITTING FOR AUDI, VOLKSWAGEN, JEEP | M104: A5-ADAPTER FÜR AUDI, VOLKSWAGEN, JEEP | N104: A5-FITTING FOR AUDI, VOLKSWAGEN, JEEP | O104: A5-FITTING FOR AUDI, VOLKSWAGEN, JEEP | P104: A5-FITTING FOR AUDI, VOLKSWAGEN, JEEP | Q104: ATF | R104: ATF | S104: ATF | T104: ATF | U104: ATF
A105: DECKRAC8206 | B105: ATF | C105: ATF | D105: ATF | E105: ATF | F105: ATF | G105: A6 | H105: A6 | I105: A6 | J105: A6 | K105: A6 | L105: A6-FITTING FOR AUDI, PORSCHE, OPEL, SUBARU, MAZDA, CITROEN, RENAUL, ALFA ROMEO, LANCIA | M105: A6-ADAPTER FÜR AUDI, PORSCHE, OPEL, SUBARU, MAZDA, CITROEN, RENAUL, ALFA ROMEO, LANCIA | N105: A6-FITTING FOR AUDI, PORSCHE, OPEL, SUBARU, MAZDA, CITROEN, RENAUL, ALFA ROMEO, LANCIA | O105: A6-FITTING FOR AUDI, PORSCHE, OPEL, SUBARU, MAZDA, CITROEN, RENAUL, ALFA ROMEO, LANCIA | P105: A6-FITTING FOR AUDI, PORSCHE, OPEL, SUBARU, MAZDA, CITROEN, RENAUL, ALFA ROMEO, LANCIA | Q105: ATF | R105: ATF | S105: ATF | T105: ATF | U105: ATF
... A207: DECKRAC8287 | B207: ATF | C207: ATF | D207: ATF | E207: ATF | F207: ATF | G207: A87 | H207: A87 | I207: A87 | J207: A87 | K207: A87 | L207: A87 - ALFAROMEO GEARBOX ZF8HP75, ZF8HP50 (STELVIO, GIULIA) | M207: A87 - ALFAROMEO GEARBOX ZF8HP75, ZF8HP50 (STELVIO, GIULIA) | N207: A87 - ALFAROMEO GEARBOX ZF8HP75, ZF8HP50 (STELVIO, GIULIA) | O207: A87 - ALFAROMEO GEARBOX ZF8HP75, ZF8HP50 (STELVIO, GIULIA) | P207: A87 - ALFAROMEO GEARBOX ZF8HP75, ZF8HP50 (STELVIO, GIULIA) | Q207: ATF | R207: ATF | S207: ATF | T207: ATF | U207: ATF

Sheet Prices
C1: List Price 2025 | D1: CEE & CISD | E1: CEE & CIS2 | F1: CEE & CISN | G1: MEAD | H1: MEA2 | I1: MEAN | J1: IbericaD | K1: Iberica2 | L1: IbericaN | M1: BeneluxD | N1: Benelux2 | O1: BeneluxN | P1: North CHD | Q1: North CH2 | R1: North CHN | S1: PolandD | T1: Poland2 | U1: PolandN | V1: ItalyD | W1: Italy2 | X1: ItalyN
D2: 4 | E2: 5 | F2: 6 | G2: 7 | H2: 8 | I2: 9 | J2: 10 | K2: 11 | L2: 12 | M2: 13 | N2: 14 | O2: 15 | P2: 16 | Q2: 17 | R2: 18 | S2: 19 | T2: 20 | U2: 21 | V2: 22 | W2: 23 | X2: 24
A3: EQUIPMENT | C3: List Price | D3: Discount | F3: Net Price | G3: Discount | I3: Net Price | J3: Discount | L3: Net Price | M3: Discount | O3: Net Price | P3: Discount | R3: Net Price | S3: Discount | T3: 2nd discount | U3: Net Price | V3: Discount | X3: Net Price
A4: EESCDE137A | B4: =VLOOKUP(A4,'DB Equipment'!A:H,8,0) -> PDL 4200 German | C4: 3785 | D4: 0.3 | F4: =+(1-D4)*$C4 -> 2649.5 | G4: 0.58 | I4: =+(1-G4)*$C4 -> 1589.7 | J4: 0.4 | L4: =+(1-J4)*$C4 -> 2271 | M4: 0.4 | O4: =+(1-M4)*$C4 -> 2271 | P4: 0.4 | R4: =+(1-P4)*$C4 -> 2271 | S4: 0.49 | U4: =+(1-S4)*$C4 -> 1930.35 | V4: 0.5054 | X4: =+(1-V4)*$C4 -> 1872.061
A5: EESCFR137A | B5: =VLOOKUP(A5,'DB Equipment'!A:H,8,0) -> PDL 4200 French | C5: 3785 | D5: 0.3 | F5: =+(1-D5)*$C5 -> 2649.5 | G5: 0.58 | I5: =+(1-G5)*$C5 -> 1589.7 | J5: 0.4 | L5: =+(1-J5)*$C5 -> 2271 | M5: 0.4 | O5: =+(1-M5)*$C5 -> 2271 | P5: 0.4 | R5: =+(1-P5)*$C5 -> 2271 | S5: 0.49 | U5: =+(1-S5)*$C5 -> 1930.35 | V5: 0.5054 | X5: =+(1-V5)*$C5 -> 1872.061
A6: EESCIT137A | B6: =VLOOKUP(A6,'DB Equipment'!A:H,8,0) -> PDL 4200 Italian | C6: 3785 | D6: 0.3 | F6: =+(1-D6)*$C6 -> 2649.5 | I6: =+(1-G6)*$C6 -> 3785 | J6: 0.4 | L6: =+(1-J6)*$C6 -> 2271 | O6: =+(1-M6)*$C6 -> 3785 | P6: 0.4 | R6: =+(1-P6)*$C6 -> 2271 | U6: =+(1-S6)*$C6 -> 3785 | V6: 0.665 | X6: =+(1-V6)*$C6 -> 1267.975
A7: EESCPL137A | B7: =VLOOKUP(A7,'DB Equipment'!A:H,8,0) -> PDL 4200 Polish | C7: 3785 | D7: 0.3 | F7: =+(1-D7)*$C7 -> 2649.5 | G7: 0.58 | I7: =+(1-G7)*$C7 -> 1589.7 | J7: 0.4 | L7: =+(1-J7)*$C7 -> 2271 | M7: 0.4 | O7: =+(1-M7)*$C7 -> 2271 | P7: 0.4 | R7: =+(1-P7)*$C7 -> 2271 | S7: 0.49 | U7: =+(1-S7)*$C7 -> 1930.35 | V7: 0.5054 | X7: =+(1-V7)*$C7 -> 1872.061
A8: EESCPL137A x 5 | B8: =VLOOKUP(A8,'DB Equipment'!A:H,8,0) -> PDL 4200 Polish | C8: 3785 | S8: 0.49 | T8: 0.0784 | U8: =+C8*(1-Y8)*(1-Z8) -> 1779.0106 | Y8: 0.49 | Z8: 0.0784
A9: EESCPL137A x 10 | B9: =VLOOKUP(A9,'DB Equipment'!A:H,8,0) -> PDL 4200 Polish | C9: 3785 | S9: 0.49 | T9: 0.1373 | U9: =+C9*(1-Y9)*(1-Z9) -> 1665.3129 | Y9: 0.49 | Z9: 0.1373
A10: EESCEG137A | B10: =VLOOKUP(A10,'DB Equipment'!A:H,8,0) -> PDL 4200 English | C10: 3785 | D10: 0.3 | F10: =+(1-D10)*$C10 -> 2649.5 | G10: 0.58 | I10: =+(1-G10)*$C10 -> 1589.7 | J10: 0.4 | L10: =+(1-J10)*$C10 -> 2271 | M10: 0.4 | O10: =+(1-M10)*$C10 -> 2271 | P10: 0.4 | R10: =+(1-P10)*$C10 -> 2271 | S10: 0.49 | U10: =+(1-S10)*$C10 -> 1930.35 | V10: 0.5054 | X10: =+(1-V10)*$C10 -> 1872.061
A11: EESCDE135A | B11: =VLOOKUP(A11,'DB Equipment'!A:H,8,0) -> PDL 7100 German | C11: 4210 | D11: 0.3 | F11: =+(1-D11)*$C11 -> 2947 | G11: 0.58 | I11: =+(1-G11)*$C11 -> 1768.2 | J11: 0.4 | L11: =+(1-J11)*$C11 -> 2526 | M11: 0.4 | O11: =+(1-M11)*$C11 -> 2526 | P11: 0.4 | R11: =+(1-P11)*$C11 -> 2526 | S11: 0.49 | U11: =+(1-S11)*$C11 -> 2147.1 | V11: 0.449 | X11: =+(1-V11)*$C11 -> 2319.71
A12: EESCFR135A | B12: =VLOOKUP(A12,'DB Equipment'!A:H,8,0) -> PDL 7100 French | C12: 4210 | D12: 0.3 | F12: =+(1-D12)*$C12 -> 2947 | G12: 0.58 | I12: =+(1-G12)*$C12 -> 1768.2 | J12: 0.4 | L12: =+(1-J12)*$C12 -> 2526 | M12: 0.4 | O12: =+(1-M12)*$C12 -> 2526 | P12: 0.4 | R12: =+(1-P12)*$C12 -> 2526 | S12: 0.49 | U12: =+(1-S12)*$C12 -> 2147.1 | V12: 0.449 | X12: =+(1-V12)*$C12 -> 2319.71
A13: EESCIT135A | B13: =VLOOKUP(A13,'DB Equipment'!A:H,8,0) -> PDL 7100 Italian | C13: 4210 | D13: 0.3 | F13: =+(1-D13)*$C13 -> 2947 | I13: =+(1-G13)*$C13 -> 4210 | J13: 0.4 | L13: =+(1-J13)*$C13 -> 2526 | O13: =+(1-M13)*$C13 -> 4210 | P13: 0.4 | R13: =+(1-P13)*$C13 -> 2526 | U13: =+(1-S13)*$C13 -> 4210 | V13: 0.673 | X13: =+(1-V13)*$C13 -> 1376.67
A14: EESCPL135A | B14: =VLOOKUP(A14,'DB Equipment'!A:H,8,0) -> PDL 7100 Polish | C14: 4210 | D14: 0.3 | F14: =+(1-D14)*$C14 -> 2947 | G14: 0.58 | I14: =+(1-G14)*$C14 -> 1768.2 | J14: 0.4 | L14: =+(1-J14)*$C14 -> 2526 | M14: 0.4 | O14: =+(1-M14)*$C14 -> 2526 | P14: 0.4 | R14: =+(1-P14)*$C14 -> 2526 | S14: 0.49 | U14: =+(1-S14)*$C14 -> 2147.1 | V14: 0.449 | X14: =+(1-V14)*$C14 -> 2319.71
A15: EESCPL135A x 5 | B15: =VLOOKUP(A15,'DB Equipment'!A:H,8,0) -> PDL 7100 Polish | C15: 4210 | S15: 0.49 | T15: 0.0784 | U15: =+C15*(1-Y15)*(1-Z15) -> 1978.7674 | Y15: 0.49 | Z15: 0.0784
A16: EESCPL135A x 10 | B16: =VLOOKUP(A16,'DB Equipment'!A:H,8,0) -> PDL 7100 Polish | C16: 4210 | S16: 0.49 | T16: 0.1373 | U16: =+C16*(1-Y16)*(1-Z16) -> 1852.3032 | Y16: 0.49 | Z16: 0.1373
A17: EESCEG135A | B17: =VLOOKUP(A17,'DB Equipment'!A:H,8,0) -> PDL 7100 English | C17: 4210 | D17: 0.3 | F17: =+(1-D17)*$C17 -> 2947 | G17: 0.58 | I17: =+(1-G17)*$C17 -> 1768.2 | J17: 0.4 | L17: =+(1-J17)*$C17 -> 2526 | M17: 0.4 | O17: =+(1-M17)*$C17 -> 2526 | P17: 0.4 | R17: =+(1-P17)*$C17 -> 2526 | S17: 0.49 | U17: =+(1-S17)*$C17 -> 2147.1 | V17: 0.449 | X17: =+(1-V17)*$C17 -> 2319.71
A18: EEMSDE143A | B18: =VLOOKUP(A18,'DB Equipment'!A:H,8,0) -> PDL 8000 German | C18: 6355 | D18: 0.3 | F18: =+(1-D18)*$C18 -> 4448.5 | G18: 0.58 | I18: =+(1-G18)*$C18 -> 2669.1 | J18: 0.4 | L18: =+(1-J18)*$C18 -> 3813 | M18: 0.4 | O18: =+(1-M18)*$C18 -> 3813 | P18: 0.4 | R18: =+(1-P18)*$C18 -> 3813 | S18: 0.45 | U18: =+(1-S18)*$C18 -> 3495.25 | V18: 0.5053 | X18: =+(1-V18)*$C18 -> 3143.8185
A19: EEMSIT143A | B19: =VLOOKUP(A19,'DB Equipment'!A:H,8,0) -> PDL 8000 Italian | C19: 6355 | D19: 0.3 | F19: =+(1-D19)*$C19 -> 4448.5 | I19: =+(1-G19)*$C19 -> 6355 | J19: 0.4 | L19: =+(1-J19)*$C19 -> 3813 | O19: =+(1-M19)*$C19 -> 6355 | P19: 0.4 | R19: =+(1-P19)*$C19 -> 3813 | U19: =+(1-S19)*$C19 -> 6355 | V19: 0.7 | X19: =+(1-V19)*$C19 -> 1906.5
A20: EEMSPL143A | B20: =VLOOKUP(A20,'DB Equipment'!A:H,8,0) -> PDL 8000 Polish | C20: 6355 | D20: 0.3 | F20: =+(1-D20)*$C20 -> 4448.5 | G20: 0.58 | I20: =+(1-G20)*$C20 -> 2669.1 | J20: 0.4 | L20: =+(1-J20)*$C20 -> 3813 | M20: 0.4 | O20: =+(1-M20)*$C20 -> 3813 | P20: 0.4 | R20: =+(1-P20)*$C20 -> 3813 | S20: 0.45 | U20: =+(1-S20)*$C20 -> 3495.25 | V20: 0.5053 | X20: =+(1-V20)*$C20 -> 3143.8185
A21: EEMSPL143A x 5 | B21: =VLOOKUP(A21,'DB Equipment'!A:H,8,0) -> PDL 8000 Polish | C21: 6355 | S21: 0.45 | T21: 0.0909 | U21: =+C21*(1-Y21)*(1-Z21) -> 3177.5318 | Y21: 0.45 | Z21: 0.0909
A22: EEMSPL143A x 10 | B22: =VLOOKUP(A22,'DB Equipment'!A:H,8,0) -> PDL 8000 Polish | C22: 6355 | S22: 0.45 | T22: 0.1818 | U22: =+C22*(1-Y22)*(1-Z22) -> 2859.8136 | Y22: 0.45 | Z22: 0.1818
A23: EEMSFR143A | B23: =VLOOKUP(A23,'DB Equipment'!A:H,8,0) -> PDL 8000 French | C23: 6355 | D23: 0.3 | F23: =+(1-D23)*$C23 -> 4448.5 | G23: 0.58 | I23: =+(1-G23)*$C23 -> 2669.1 | J23: 0.4 | L23: =+(1-J23)*$C23 -> 3813 | M23: 0.4 | O23: =+(1-M23)*$C23 -> 3813 | P23: 0.4 | R23: =+(1-P23)*$C23 -> 3813 | S23: 0.45 | U23: =+(1-S23)*$C23 -> 3495.25 | V23: 0.5053 | X23: =+(1-V23)*$C23 -> 3143.8185
A24: EEMSDE149A | B24: =VLOOKUP(A24,'DB Equipment'!A:H,8,0) -> PDL 8200 German | C24: 6815 | D24: 0.3 | F24: =+(1-D24)*$C24 -> 4770.5 | G24: 0.58 | I24: =+(1-G24)*$C24 -> 2862.3 | J24: 0.4 | L24: =+(1-J24)*$C24 -> 4089 | M24: 0.4 | O24: =+(1-M24)*$C24 -> 4089 | P24: 0.4 | R24: =+(1-P24)*$C24 -> 4089 | S24: 0.45 | U24: =+(1-S24)*$C24 -> 3748.25 | V24: 0.5053 | X24: =+(1-V24)*$C24 -> 3371.3805
A25: EEMSIT149A | B25: =VLOOKUP(A25,'DB Equipment'!A:H,8,0) -> PDL 8200 Italian | C25: 6815 | D25: 0.3 | F25: =+(1-D25)*$C25 -> 4770.5 | I25: =+(1-G25)*$C25 -> 6815 | J25: 0.4 | L25: =+(1-J25)*$C25 -> 4089 | O25: =+(1-M25)*$C25 -> 6815 | P25: 0.4 | R25: =+(1-P25)*$C25 -> 4089 | U25: =+(1-S25)*$C25 -> 6815 | V25: 0.7 | X25: =+(1-V25)*$C25 -> 2044.5
A26: EEMSPL149A | B26: =VLOOKUP(A26,'DB Equipment'!A:H,8,0) -> PDL 8200 Polish | C26: 6815 | D26: 0.3 | F26: =+(1-D26)*$C26 -> 4770.5 | G26: 0.58 | I26: =+(1-G26)*$C26 -> 2862.3 | J26: 0.4 | L26: =+(1-J26)*$C26 -> 4089 | M26: 0.4 | O26: =+(1-M26)*$C26 -> 4089 | P26: 0.4 | R26: =+(1-P26)*$C26 -> 4089 | S26: 0.45 | U26: =+(1-S26)*$C26 -> 3748.25 | V26: 0.5053 | X26: =+(1-V26)*$C26 -> 3371.3805
A27: EEMSPL149A x 5 | B27: =VLOOKUP(A27,'DB Equipment'!A:H,8,0) -> PDL 8200 Polish | C27: 6815 | S27: 0.45 | T27: 0.0909 | U27: =+C27*(1-Y27)*(1-Z27) -> 3407.5341 | Y27: 0.45 | Z27: 0.0909
A28: EEMSPL149A x 10 | B28: =VLOOKUP(A28,'DB Equipment'!A:H,8,0) -> PDL 8200 Polish | C28: 6815 | S28: 0.45 | T28: 0.1818 | U28: =+C28*(1-Y28)*(1-Z28) -> 3066.8182 | Y28: 0.45 | Z28: 0.1818
A29: EEMSFR149A | B29: =VLOOKUP(A29,'DB Equipment'!A:H,8,0) -> PDL 8200 French | C29: 6815 | D29: 0.3 | F29: =+(1-D29)*$C29 -> 4770.5 | G29: 0.58 | I29: =+(1-G29)*$C29 -> 2862.3 | J29: 0.4 | L29: =+(1-J29)*$C29 -> 4089 | M29: 0.4 | O29: =+(1-M29)*$C29 -> 4089 | P29: 0.4 | R29: =+(1-P29)*$C29 -> 4089 | S29: 0.45 | U29: =+(1-S29)*$C29 -> 3748.25 | V29: 0.5053 | X29: =+(1-V29)*$C29 -> 3371.3805
A30: EEMSEG149A | B30: =VLOOKUP(A30,'DB Equipment'!A:H,8,0) -> PDL 8200 English | C30: 6815 | D30: 0.3 | F30: =+(1-D30)*$C30 -> 4770.5 | G30: 0.58 | I30: =+(1-G30)*$C30 -> 2862.3 | J30: 0.4 | L30: =+(1-J30)*$C30 -> 4089 | M30: 0.4 | O30: =+(1-M30)*$C30 -> 4089 | P30: 0.4 | R30: =+(1-P30)*$C30 -> 4089 | S30: 0.45 | U30: =+(1-S30)*$C30 -> 3748.25 | V30: 0.5053 | X30: =+(1-V30)*$C30 -> 3371.3805
A31: EEPVEU118A | B31: =VLOOKUP(A31,'DB Equipment'!A:H,8,0) -> TPMX tool | C31: 1200 | D31: 0.3 | F31: =+(1-D31)*$C31 -> 840 | G31: 0.37 | I31: =+(1-G31)*$C31 -> 756 | L31: =+(1-J31)*$C31 -> 1200 | O31: =+(1-M31)*$C31 -> 1200 | R31: =+(1-P31)*$C31 -> 1200 | S31: 0.4 | U31: =+(1-S31)*$C31 -> 720 | V31: 0.4 | X31: =+(1-V31)*$C31 -> 720
A32: DECKY2N20020S000 | B32: =VLOOKUP(A32,'DB Equipment'!A:H,8,0) -> BREEZE IV with printer | C32: 4575 | D32: 0.6 | F32: =+(1-D32)*$C32 -> 1830 | G32: 0.55 | I32: =+(1-G32)*$C32 -> 2058.75 | J32: 0.6 | L32: =+(1-J32)*$C32 -> 1830 | M32: 0.6 | O32: =+(1-M32)*$C32 -> 1830 | P32: 0.6 | R32: =+(1-P32)*$C32 -> 1830 | S32: 0.6 | U32: =+(1-S32)*$C32 -> 1830 | V32: 0.605 | X32: =+(1-V32)*$C32 -> 1807.125
A33: DECKY2F20020S000 | B33: =VLOOKUP(A33,'DB Equipment'!A:H,8,0) -> BLIZZARD QTECH IV | C33: 7050 | D33: 0.65 | F33: =+(1-D33)*$C33 -> 2467.5 | G33: 0.67 | I33: =+(1-G33)*$C33 -> 2326.5 | J33: 0.6 | L33: =+(1-J33)*$C33 -> 2820 | M33: 0.6 | O33: =+(1-M33)*$C33 -> 2820 | P33: 0.6 | R33: =+(1-P33)*$C33 -> 2820 | S33: 0.65 | U33: =+(1-S33)*$C33 -> 2467.5 | V33: 0.66 | X33: =+(1-V33)*$C33 -> 2397
A34: DECKK6T5A090S00B | B34: =VLOOKUP(A34,'DB Equipment'!A:H,8,0) -> KOOLKARE DUAL GAS 12 | C34: 10030 | D34: 0.6 | F34: =+(1-D34)*$C34 -> 4012 | G34: 0.59 | I34: =+(1-G34)*$C34 -> 4112.3 | J34: 0.6 | L34: =+(1-J34)*$C34 -> 4012 | M34: 0.6 | O34: =+(1-M34)*$C34 -> 4012 | P34: 0.6 | R34: =+(1-P34)*$C34 -> 4012 | S34: 0.6 | U34: =+(1-S34)*$C34 -> 4012 | V34: 0.61 | X34: =+(1-V34)*$C34 -> 3911.7
A35: DECKXK456A170S51 | B35: =VLOOKUP(A35,'DB Equipment'!A:H,8,0) -> KoolKare HD-S | C35: 8335 | D35: 0.6 | F35: =+(1-D35)*$C35 -> 3334 | G35: 0.59 | I35: =+(1-G35)*$C35 -> 3417.35 | J35: 0.6 | L35: =+(1-J35)*$C35 -> 3334 | M35: 0.6 | O35: =+(1-M35)*$C35 -> 3334 | P35: 0.6 | R35: =+(1-P35)*$C35 -> 3334 | S35: 0.6 | U35: =+(1-S35)*$C35 -> 3334 | V35: 0.58 | X35: =+(1-V35)*$C35 -> 3500.7
A36: DECKY1R74420S000 | B36: =VLOOKUP(A36,'DB Equipment'!A:H,8,0) -> ECO2KARE | C36: 8495 | D36: 0.5051 | F36: =+(1-D36)*$C36 -> 4204.1755 | G36: 0.5051 | I36: =+(1-G36)*$C36 -> 4204.1755 | J36: 0.5051 | L36: =+(1-J36)*$C36 -> 4204.1755 | M36: 0.5051 | O36: =+(1-M36)*$C36 -> 4204.1755 | P36: 0.5051 | R36: =+(1-P36)*$C36 -> 4204.1755 | S36: 0.5051 | U36: =+(1-S36)*$C36 -> 4204.1755 | V36: 0.5051 | X36: =+(1-V36)*$C36 -> 4204.1755
A37: DECKY1ATF020S000 | B37: =VLOOKUP(A37,'DB Equipment'!A:H,8,0) -> ATF Gearkare | C37: 6070 | D37: 0.55 | F37: =+(1-D37)*$C37 -> 2731.5 | G37: 0.55 | I37: =+(1-G37)*$C37 -> 2731.5 | J37: 0.55 | L37: =+(1-J37)*$C37 -> 2731.5 | M37: 0.55 | O37: =+(1-M37)*$C37 -> 2731.5 | P37: 0.55 | R37: =+(1-P37)*$C37 -> 2731.5 | S37: 0.55 | U37: =+(1-S37)*$C37 -> 2731.5 | V37: 0.55 | X37: =+(1-V37)*$C37 -> 2731.5
A38: DECKY1ATF0000SIM | B38: =VLOOKUP(A38,'DB Equipment'!A:H,8,0) -> ATF Gearkare Simulator | C38: 1950 | D38: 0.55 | F38: =+(1-D38)*$C38 -> 877.5 | G38: 0.55 | I38: =+(1-G38)*$C38 -> 877.5 | J38: 0.55 | L38: =+(1-J38)*$C38 -> 877.5 | M38: 0.55 | O38: =+(1-M38)*$C38 -> 877.5 | P38: 0.55 | R38: =+(1-P38)*$C38 -> 877.5 | S38: 0.55 | U38: =+(1-S38)*$C38 -> 877.5 | V38: 0.55 | X38: =+(1-V38)*$C38 -> 877.5
A39: ACCESSORIES
A40: EAX0068L01A | B40: =VLOOKUP(A40,'DB Accessori'!A:G,7,0) -> Adaptor cable DA-5 | C40: 114 | D40: 0.4 | F40: =+(1-D40)*$C40 -> 68.4 | G40: 0.45 | I40: =+(1-G40)*$C40 -> 62.7 | J40: 0.4 | L40: =+(1-J40)*$C40 -> 68.4 | M40: 0.4 | O40: =+(1-M40)*$C40 -> 68.4 | P40: 0.4 | R40: =+(1-P40)*$C40 -> 68.4 | S40: 0.35 | U40: =+(1-S40)*$C40 -> 74.1 | V40: 0.4 | X40: =+(1-V40)*$C40 -> 68.4
A41: EAX0068L00C | B41: =VLOOKUP(A41,'DB Accessori'!A:G,7,0) -> OBDII data cable w/o light (16-pin cable) | C41: 72 | D41: 0.4 | F41: =+(1-D41)*$C41 -> 43.2 | G41: 0.45 | I41: =+(1-G41)*$C41 -> 39.6 | J41: 0.4 | L41: =+(1-J41)*$C41 -> 43.2 | M41: 0.4 | O41: =+(1-M41)*$C41 -> 43.2 | P41: 0.4 | R41: =+(1-P41)*$C41 -> 43.2 | S41: 0.35 | U41: =+(1-S41)*$C41 -> 46.8 | V41: 0.4 | X41: =+(1-V41)*$C41 -> 43.2
A42: EAX0068L26A | B42: =VLOOKUP(A42,'DB Accessori'!A:G,7,0) -> OBDII data cable w/ light (16-pin cable) | C42: 156 | D42: 0.4 | F42: =+(1-D42)*$C42 -> 93.6 | G42: 0.45 | I42: =+(1-G42)*$C42 -> 85.8 | J42: 0.4 | L42: =+(1-J42)*$C42 -> 93.6 | M42: 0.4 | O42: =+(1-M42)*$C42 -> 93.6 | P42: 0.4 | R42: =+(1-P42)*$C42 -> 93.6 | S42: 0.35 | U42: =+(1-S42)*$C42 -> 101.4 | V42: 0.4 | X42: =+(1-V42)*$C42 -> 93.6
A43: EAX0072L17A | B43: =VLOOKUP(A43,'DB Accessori'!A:G,7,0) -> DA-4EA Ethernet DOIP data cable | C43: 240 | D43: 0.4 | F43: =+(1-D43)*$C43 -> 144 | G43: 0.45 | I43: =+(1-G43)*$C43 -> 132 | J43: 0.4 | L43: =+(1-J43)*$C43 -> 144 | M43: 0.4 | O43: =+(1-M43)*$C43 -> 144 | P43: 0.4 | R43: =+(1-P43)*$C43 -> 144 | S43: 0.35 | U43: =+(1-S43)*$C43 -> 156 | V43: 0.4 | X43: =+(1-V43)*$C43 -> 144
A44: 2-03965A | B44: =VLOOKUP(A44,'DB Accessori'!A:G,7,0) -> Soft Case | C44: 28 | D44: 0.4 | F44: =+(1-D44)*$C44 -> 16.8 | G44: 0.45 | I44: =+(1-G44)*$C44 -> 15.4 | J44: 0.4 | L44: =+(1-J44)*$C44 -> 16.8 | M44: 0.4 | O44: =+(1-M44)*$C44 -> 16.8 | P44: 0.4 | R44: =+(1-P44)*$C44 -> 16.8 | S44: 0.35 | U44: =+(1-S44)*$C44 -> 18.2 | V44: 0.4 | X44: =+(1-V44)*$C44 -> 16.8
A45: EAC0111L76A3 | B45: =VLOOKUP(A45,'DB Accessori'!A:G,7,0) -> Screen Protector 3 Pack | C45: 36 | D45: 0.4 | F45: =+(1-D45)*$C45 -> 21.6 | G45: 0.45 | I45: =+(1-G45)*$C45 -> 19.8 | J45: 0.4 | L45: =+(1-J45)*$C45 -> 21.6 | M45: 0.4 | O45: =+(1-M45)*$C45 -> 21.6 | P45: 0.4 | R45: =+(1-P45)*$C45 -> 21.6 | S45: 0.35 | U45: =+(1-S45)*$C45 -> 23.4 | V45: 0.4 | X45: =+(1-V45)*$C45 -> 21.6
A46: EESP115A-3.2 | B46: =VLOOKUP(A46,'DB Accessori'!A:G,7,0) -> PDL 3200 Software update for 1 year (2 minimum per year) | C46: 705 | D46: 0.4 | F46: =+(1-D46)*$C46 -> 423 | G46: 0.46 | I46: =+(1-G46)*$C46 -> 380.7 | J46: 0.4 | L46: =+(1-J46)*$C46 -> 423 | M46: 0.4 | O46: =+(1-M46)*$C46 -> 423 | P46: 0.4 | R46: =+(1-P46)*$C46 -> 423 | S46: 0.35 | U46: =+(1-S46)*$C46 -> 458.25 | V46: 0.4 | X46: =+(1-V46)*$C46 -> 423
A47: EESP116A-3.2 | B47: =VLOOKUP(A47,'DB Accessori'!A:G,7,0) -> PDL 3200 Software update for 1 year (2 minimum per year) after termination plus charge for re-activation | C47: 1088 | D47: 0.4 | F47: =+(1-D47)*$C47 -> 652.8 | G47: 0.46 | I47: =+(1-G47)*$C47 -> 587.52 | J47: 0.4 | L47: =+(1-J47)*$C47 -> 652.8 | M47: 0.4 | O47: =+(1-M47)*$C47 -> 652.8 | P47: 0.4 | R47: =+(1-P47)*$C47 -> 652.8 | S47: 0.35 | U47: =+(1-S47)*$C47 -> 707.2 | V47: 0.4 | X47: =+(1-V47)*$C47 -> 652.8
A48: EESP118A-3.2 | B48: =VLOOKUP(A48,'DB Accessori'!A:G,7,0) -> PDL 3200 Software update for 2 years (2 minimum per year) | C48: 1267 | D48: 0.4 | F48: =+(1-D48)*$C48 -> 760.2 | G48: 0.55 | I48: =+(1-G48)*$C48 -> 570.15 | J48: 0.4 | L48: =+(1-J48)*$C48 -> 760.2 | M48: 0.4 | O48: =+(1-M48)*$C48 -> 760.2 | P48: 0.4 | R48: =+(1-P48)*$C48 -> 760.2 | S48: 0.35 | U48: =+(1-S48)*$C48 -> 823.55 | V48: 0.4 | X48: =+(1-V48)*$C48 -> 760.2
A49: EESP115A-4.1 | B49: =VLOOKUP(A49,'DB Accessori'!A:G,7,0) -> PDL 4100 Software update for 1 year (2 minimum per year) | C49: 818 | D49: 0.4 | F49: =+(1-D49)*$C49 -> 490.8 | G49: 0.46 | I49: =+(1-G49)*$C49 -> 441.72 | J49: 0.4 | L49: =+(1-J49)*$C49 -> 490.8 | M49: 0.4 | O49: =+(1-M49)*$C49 -> 490.8 | P49: 0.4 | R49: =+(1-P49)*$C49 -> 490.8 | S49: 0.35 | U49: =+(1-S49)*$C49 -> 531.7 | V49: 0.4 | X49: =+(1-V49)*$C49 -> 490.8
A50: EESP116A-4.1 | B50: =VLOOKUP(A50,'DB Accessori'!A:G,7,0) -> PDL 4100 Software update for 1 year (2 minimum per year) after termination plus charge for re-activation | C50: 1172 | D50: 0.4 | F50: =+(1-D50)*$C50 -> 703.2 | G50: 0.46 | I50: =+(1-G50)*$C50 -> 632.88 | J50: 0.4 | L50: =+(1-J50)*$C50 -> 703.2 | M50: 0.4 | O50: =+(1-M50)*$C50 -> 703.2 | P50: 0.4 | R50: =+(1-P50)*$C50 -> 703.2 | S50: 0.35 | U50: =+(1-S50)*$C50 -> 761.8 | V50: 0.4 | X50: =+(1-V50)*$C50 -> 703.2
A51: EESP118A-4.1 | B51: =VLOOKUP(A51,'DB Accessori'!A:G,7,0) -> PDL 4100 Software update for 2 years (2 minimum per year) | C51: 1474 | D51: 0.4 | F51: =+(1-D51)*$C51 -> 884.4 | G51: 0.55 | I51: =+(1-G51)*$C51 -> 663.3 | J51: 0.4 | L51: =+(1-J51)*$C51 -> 884.4 | M51: 0.4 | O51: =+(1-M51)*$C51 -> 884.4 | P51: 0.4 | R51: =+(1-P51)*$C51 -> 884.4 | S51: 0.35 | U51: =+(1-S51)*$C51 -> 958.1 | V51: 0.4 | X51: =+(1-V51)*$C51 -> 884.4
... A79: EAK0294B22A | B79: =VLOOKUP(A79,'DB Accessori'!A:G,7,0) -> Set of 4 probes for lab scope | C79: 37 | D79: 0.4 | F79: =+(1-D79)*$C79 -> 22.2 | G79: 0.55 | I79: =+(1-G79)*$C79 -> 16.65 | J79: 0.4 | L79: =+(1-J79)*$C79 -> 22.2 | M79: 0.4 | O79: =+(1-M79)*$C79 -> 22.2 | P79: 0.4 | R79: =+(1-P79)*$C79 -> 22.2 | S79: 0.35 | U79: =+(1-S79)*$C79 -> 24.05 | V79: 0.4 | X79: =+(1-V79)*$C79 -> 22.2
A80: A/C
A81: DECKY2NR00000000 | B81: =VLOOKUP(A81,'DB Equipment'!A:H,8,0) -> KIT R134A for BREEZE IV | C81: 271 | D81: 0.6 | F81: =+(1-D81)*$C81 -> 108.4 | G81: 0.6 | I81: =+(1-G81)*$C81 -> 108.4 | J81: 0.6 | L81: =+(1-J81)*$C81 -> 108.4 | M81: 0.6 | O81: =+(1-M81)*$C81 -> 108.4 | P81: 0.6 | R81: =+(1-P81)*$C81 -> 108.4 | S81: 0.6 | U81: =+(1-S81)*$C81 -> 108.4 | V81: 0.65 | X81: =+(1-V81)*$C81 -> 94.85
A82: DECKY2NH00000000 | B82: =VLOOKUP(A82,'DB Equipment'!A:H,8,0) -> KIT HFO for BREEZE IV | C82: 834 | D82: 0.65 | F82: =+(1-D82)*$C82 -> 291.9 | G82: 0.74 | I82: =+(1-G82)*$C82 -> 216.84 | J82: 0.6 | L82: =+(1-J82)*$C82 -> 333.6 | M82: 0.6 | O82: =+(1-M82)*$C82 -> 333.6 | P82: 0.6 | R82: =+(1-P82)*$C82 -> 333.6 | S82: 0.71 | U82: =+(1-S82)*$C82 -> 241.86 | V82: 0.85 | X82: =+(1-V82)*$C82 -> 125.1
A83: DECKY2FR00000000 | B83: =VLOOKUP(A83,'DB Equipment'!A:H,8,0) -> KIT R134A for QTECH IV | C83: 271 | D83: 0.65 | F83: =+(1-D83)*$C83 -> 94.85 | G83: 0.7 | I83: =+(1-G83)*$C83 -> 81.3 | J83: 0.6 | L83: =+(1-J83)*$C83 -> 108.4 | M83: 0.6 | O83: =+(1-M83)*$C83 -> 108.4 | P83: 0.6 | R83: =+(1-P83)*$C83 -> 108.4 | S83: 0.65 | U83: =+(1-S83)*$C83 -> 94.85 | V83: 0.65 | X83: =+(1-V83)*$C83 -> 94.85
A84: DECKY2FH00000000 | B84: =VLOOKUP(A84,'DB Equipment'!A:H,8,0) -> KIT HFO for QTECH IV | C84: 834 | D84: 0.65 | F84: =+(1-D84)*$C84 -> 291.9 | G84: 0.51 | I84: =+(1-G84)*$C84 -> 408.66 | J84: 0.6 | L84: =+(1-J84)*$C84 -> 333.6 | M84: 0.6 | O84: =+(1-M84)*$C84 -> 333.6 | P84: 0.6 | R84: =+(1-P84)*$C84 -> 333.6 | S84: 0.71 | U84: =+(1-S84)*$C84 -> 241.86 | V84: 0.85 | X84: =+(1-V84)*$C84 -> 125.1
A85: DECKKIT.HYBRID | B85: =VLOOKUP(A85,'DB Accessori'!A:G,7,0) -> Kit Hybrid Upgrade option HFO1234yf and R134a | C85: 437 | D85: 0.4 | F85: =+(1-D85)*$C85 -> 262.2 | G85: 0.45 | I85: =+(1-G85)*$C85 -> 240.35 | J85: 0.4 | L85: =+(1-J85)*$C85 -> 262.2 | M85: 0.4 | O85: =+(1-M85)*$C85 -> 262.2 | P85: 0.4 | R85: =+(1-P85)*$C85 -> 262.2 | S85: 0.4 | U85: =+(1-S85)*$C85 -> 262.2 | V85: 0.57 | X85: =+(1-V85)*$C85 -> 187.91
A86: DECKXS180.000000 | B86: =VLOOKUP(A86,'DB Accessori'!A:G,7,0) -> Gas identifier HFO for single and dual gas units | C86: 2906 | D86: 0.45 | F86: =+(1-D86)*$C86 -> 1598.3 | G86: 0.45 | I86: =+(1-G86)*$C86 -> 1598.3 | J86: 0.4 | L86: =+(1-J86)*$C86 -> 1743.6 | M86: 0.4 | O86: =+(1-M86)*$C86 -> 1743.6 | P86: 0.4 | R86: =+(1-P86)*$C86 -> 1743.6 | S86: 0.4 | U86: =+(1-S86)*$C86 -> 1743.6 | V86: 0.51 | X86: =+(1-V86)*$C86 -> 1423.94
A87: DECKKIT.GAS.R134 | B87: =VLOOKUP(A87,'DB Accessori'!A:G,7,0) -> Adapter kit R134a for gas analiser KIT.GAS | C87: 151 | D87: 0.4 | F87: =+(1-D87)*$C87 -> 90.6 | G87: 0.45 | I87: =+(1-G87)*$C87 -> 83.05 | J87: 0.4 | L87: =+(1-J87)*$C87 -> 90.6 | M87: 0.4 | O87: =+(1-M87)*$C87 -> 90.6 | P87: 0.4 | R87: =+(1-P87)*$C87 -> 90.6 | S87: 0.4 | U87: =+(1-S87)*$C87 -> 90.6 | V87: 0.51 | X87: =+(1-V87)*$C87 -> 73.99
A88: DECKKIT.WIFI-N | B88: =VLOOKUP(A88,'DB Accessori'!A:G,7,0) -> Connectivity kit EVO | C88: 552 | D88: 0.4 | F88: =+(1-D88)*$C88 -> 331.2 | G88: 0.45 | I88: =+(1-G88)*$C88 -> 303.6 | J88: 0.4 | L88: =+(1-J88)*$C88 -> 331.2 | M88: 0.4 | O88: =+(1-M88)*$C88 -> 331.2 | P88: 0.4 | R88: =+(1-P88)*$C88 -> 331.2 | S88: 0.4 | U88: =+(1-S88)*$C88 -> 331.2 | V88: 0.6 | X88: =+(1-V88)*$C88 -> 220.8
A89: DECKTUB1148 | B89: =VLOOKUP(A89,'DB Accessori'!A:G,7,0) -> R134A Service hose 6 m, red, for QTECH II / III units and Breeze, male/female | C89: 68 | D89: 0.4 | F89: =+(1-D89)*$C89 -> 40.8 | G89: 0.45 | I89: =+(1-G89)*$C89 -> 37.4 | J89: 0.4 | L89: =+(1-J89)*$C89 -> 40.8 | M89: 0.4 | O89: =+(1-M89)*$C89 -> 40.8 | P89: 0.4 | R89: =+(1-P89)*$C89 -> 40.8 | S89: 0.4 | U89: =+(1-S89)*$C89 -> 40.8 | V89: 0.17 | X89: =+(1-V89)*$C89 -> 56.44
A90: DECKTUB1149 | B90: =VLOOKUP(A90,'DB Accessori'!A:G,7,0) -> R134A Service hose 6 m, blue, for QTECH II / III units and Breeze, male/female | C90: 68 | D90: 0.4 | F90: =+(1-D90)*$C90 -> 40.8 | G90: 0.45 | I90: =+(1-G90)*$C90 -> 37.4 | J90: 0.4 | L90: =+(1-J90)*$C90 -> 40.8 | M90: 0.4 | O90: =+(1-M90)*$C90 -> 40.8 | P90: 0.4 | R90: =+(1-P90)*$C90 -> 40.8 | S90: 0.4 | U90: =+(1-S90)*$C90 -> 40.8 | V90: 0.17 | X90: =+(1-V90)*$C90 -> 56.44
A91: DECKGRTUB0001 | B91: =VLOOKUP(A91,'DB Accessori'!A:G,7,0) -> KoolKare nitogen/forming gas hose kit; for connection to a nitrogen or forming gas fitting, equipment end with hose and quick coupling. Spare parts, accessories as standard option with a Koolkare nitrogen/forming gas option | C91: 84 | D91: 0.4 | F91: =+(1-D91)*$C91 -> 50.4 | G91: 0.45 | I91: =+(1-G91)*$C91 -> 46.2 | J91: 0.4 | L91: =+(1-J91)*$C91 -> 50.4 | M91: 0.4 | O91: =+(1-M91)*$C91 -> 50.4 | P91: 0.4 | R91: =+(1-P91)*$C91 -> 50.4 | S91: 0.4 | U91: =+(1-S91)*$C91 -> 50.4 | V91: 0.4 | X91: =+(1-V91)*$C91 -> 50.4
A92: DECKAEK322 | B92: =VLOOKUP(A92,'DB Accessori'!A:G,7,0) -> Bottle of Saniflux liquid (1000 ml) | C92: 75.5 | D92: 0.4 | F92: =+(1-D92)*$C92 -> 45.3 | G92: 0.45 | I92: =+(1-G92)*$C92 -> 41.525 | J92: 0.4 | L92: =+(1-J92)*$C92 -> 45.3 | M92: 0.4 | O92: =+(1-M92)*$C92 -> 45.3 | P92: 0.4 | R92: =+(1-P92)*$C92 -> 45.3 | S92: 0.4 | U92: =+(1-S92)*$C92 -> 45.3 | V92: 0.4 | X92: =+(1-V92)*$C92 -> 45.3
A93: DECKAEK275 | B93: =VLOOKUP(A93,'DB Accessori'!A:G,7,0) -> Oil bottle PAG100, R134, HFO1234yf, mechanical and electrical compressor, 6 x 250 ml | C93: 16.5 | D93: 0.4 | F93: =+(1-D93)*$C93 -> 9.9 | G93: 0.45 | I93: =+(1-G93)*$C93 -> 9.075 | J93: 0.4 | L93: =+(1-J93)*$C93 -> 9.9 | M93: 0.4 | O93: =+(1-M93)*$C93 -> 9.9 | P93: 0.4 | R93: =+(1-P93)*$C93 -> 9.9 | S93: 0.4 | U93: =+(1-S93)*$C93 -> 9.9 | V93: 0.4 | X93: =+(1-V93)*$C93 -> 9.9
A94: DECKAEK275-N | B94: =VLOOKUP(A94,'DB Accessori'!A:G,7,0) -> Sealed oil cartridge PAG100 - 250ml for R134a, HFO1234yf mechanical and electric compressor | C94: 31 | D94: 0.4 | F94: =+(1-D94)*$C94 -> 18.6 | G94: 0.45 | I94: =+(1-G94)*$C94 -> 17.05 | J94: 0.4 | L94: =+(1-J94)*$C94 -> 18.6 | M94: 0.4 | O94: =+(1-M94)*$C94 -> 18.6 | P94: 0.4 | R94: =+(1-P94)*$C94 -> 18.6 | S94: 0.4 | U94: =+(1-S94)*$C94 -> 18.6 | V94: 0.4 | X94: =+(1-V94)*$C94 -> 18.6
A95: DECKAEK276 | B95: =VLOOKUP(A95,'DB Accessori'!A:G,7,0) -> Oil bottle PAG46, R134, HFO1234yf, mechanical and electrical compressor, 6 x 250 ml | C95: 16.5 | D95: 0.4 | F95: =+(1-D95)*$C95 -> 9.9 | G95: 0.45 | I95: =+(1-G95)*$C95 -> 9.075 | J95: 0.4 | L95: =+(1-J95)*$C95 -> 9.9 | M95: 0.4 | O95: =+(1-M95)*$C95 -> 9.9 | P95: 0.4 | R95: =+(1-P95)*$C95 -> 9.9 | S95: 0.4 | U95: =+(1-S95)*$C95 -> 9.9 | V95: 0.4 | X95: =+(1-V95)*$C95 -> 9.9
A96: DECKAEK276-N | B96: =VLOOKUP(A96,'DB Accessori'!A:G,7,0) -> Sealed oil cartridge PAG46 - 250ml for R134a, HFO1234yf mechanical and electric compressor | C96: 31 | D96: 0.4 | F96: =+(1-D96)*$C96 -> 18.6 | G96: 0.45 | I96: =+(1-G96)*$C96 -> 17.05 | J96: 0.4 | L96: =+(1-J96)*$C96 -> 18.6 | M96: 0.4 | O96: =+(1-M96)*$C96 -> 18.6 | P96: 0.4 | R96: =+(1-P96)*$C96 -> 18.6 | S96: 0.4 | U96: =+(1-S96)*$C96 -> 18.6 | V96: 0.4 | X96: =+(1-V96)*$C96 -> 18.6
... A132: DECKKIT.STM | B132: =VLOOKUP(A132,'DB Accessori'!A:G,7,0) -> Thermal Printer Upgrade option | C132: 116 | D132: 0.4 | F132: =+(1-D132)*$C132 -> 69.6 | G132: 0.45 | I132: =+(1-G132)*$C132 -> 63.8 | J132: 0.4 | L132: =+(1-J132)*$C132 -> 69.6 | M132: 0.4 | O132: =+(1-M132)*$C132 -> 69.6 | P132: 0.4 | R132: =+(1-P132)*$C132 -> 69.6 | S132: 0.4 | U132: =+(1-S132)*$C132 -> 69.6 | V132: 0.4 | X132: =+(1-V132)*$C132 -> 69.6
A133: ATF
A134: DECKKIT.ATF | B134: =VLOOKUP(A134,'DB Accessori'!A:G,7,0) -> ATF BASE KIT ADAPTERS | C134: 865 | D134: 0.4 | F134: =+(1-D134)*$C134 -> 519 | G134: 0.4 | I134: =+(1-G134)*$C134 -> 519 | J134: 0.4 | L134: =+(1-J134)*$C134 -> 519 | M134: 0.4 | O134: =+(1-M134)*$C134 -> 519 | P134: 0.4 | R134: =+(1-P134)*$C134 -> 519 | S134: 0.4 | U134: =+(1-S134)*$C134 -> 519 | V134: 0.4 | X134: =+(1-V134)*$C134 -> 519
A135: DECKLEVELKIT-ATF | B135: =VLOOKUP(A135,'DB Accessori'!A:G,7,0) -> OIL LEVEL CONNECTORS | C135: 155 | D135: 0.4 | F135: =+(1-D135)*$C135 -> 93 | G135: 0.4 | I135: =+(1-G135)*$C135 -> 93 | J135: 0.4 | L135: =+(1-J135)*$C135 -> 93 | M135: 0.4 | O135: =+(1-M135)*$C135 -> 93 | P135: 0.4 | R135: =+(1-P135)*$C135 -> 93 | S135: 0.4 | U135: =+(1-S135)*$C135 -> 93 | V135: 0.4 | X135: =+(1-V135)*$C135 -> 93
A136: DECKDB.ATF | B136: =VLOOKUP(A136,'DB Accessori'!A:G,7,0) -> LOCAL DATABASE UPDATE | C136: 360 | D136: 0.55 | F136: =+(1-D136)*$C136 -> 162 | G136: 0.55 | I136: =+(1-G136)*$C136 -> 162 | J136: 0.55 | L136: =+(1-J136)*$C136 -> 162 | M136: 0.55 | O136: =+(1-M136)*$C136 -> 162 | P136: 0.55 | R136: =+(1-P136)*$C136 -> 162 | S136: 0.55 | U136: =+(1-S136)*$C136 -> 162 | V136: 0.55 | X136: =+(1-V136)*$C136 -> 162
A137: DECKDB.ATF-LICENSE | B137: =VLOOKUP(A137,'DB Accessori'!A:G,7,0) -> LOCAL DATABASE UPDATE + WEB LICENSE | C137: 390 | D137: 0.55 | F137: =+(1-D137)*$C137 -> 175.5 | G137: 0.55 | I137: =+(1-G137)*$C137 -> 175.5 | J137: 0.55 | L137: =+(1-J137)*$C137 -> 175.5 | M137: 0.55 | O137: =+(1-M137)*$C137 -> 175.5 | P137: 0.55 | R137: =+(1-P137)*$C137 -> 175.5 | S137: 0.55 | U137: =+(1-S137)*$C137 -> 175.5 | V137: 0.55 | X137: =+(1-V137)*$C137 -> 175.5
A138: DECKCNT0031 | B138: =VLOOKUP(A138,'DB Accessori'!A:G,7,0) -> NEW CANISTER 20 liters | C138: 40 | D138: 0.4 | F138: =+(1-D138)*$C138 -> 24 | G138: 0.4 | I138: =+(1-G138)*$C138 -> 24 | J138: 0.4 | L138: =+(1-J138)*$C138 -> 24 | M138: 0.4 | O138: =+(1-M138)*$C138 -> 24 | P138: 0.4 | R138: =+(1-P138)*$C138 -> 24 | S138: 0.4 | U138: =+(1-S138)*$C138 -> 24 | V138: 0.4 | X138: =+(1-V138)*$C138 -> 24
A139: DECKFLT.ATF.1000 | B139: =VLOOKUP(A139,'DB Accessori'!A:G,7,0) -> 2 x FILTER CARTRIDGE | C139: 72 | D139: 0.4 | F139: =+(1-D139)*$C139 -> 43.2 | G139: 0.4 | I139: =+(1-G139)*$C139 -> 43.2 | J139: 0.4 | L139: =+(1-J139)*$C139 -> 43.2 | M139: 0.4 | O139: =+(1-M139)*$C139 -> 43.2 | P139: 0.4 | R139: =+(1-P139)*$C139 -> 43.2 | S139: 0.4 | U139: =+(1-S139)*$C139 -> 43.2 | V139: 0.4 | X139: =+(1-V139)*$C139 -> 43.2
A140: DECKRAC8201 | B140: =VLOOKUP(A140,'DB Accessori'!A:G,7,0) -> A1 | C140: 38 | D140: 0.4 | F140: =+(1-D140)*$C140 -> 22.8 | G140: 0.4 | I140: =+(1-G140)*$C140 -> 22.8 | J140: 0.4 | L140: =+(1-J140)*$C140 -> 22.8 | M140: 0.4 | O140: =+(1-M140)*$C140 -> 22.8 | P140: 0.4 | R140: =+(1-P140)*$C140 -> 22.8 | S140: 0.4 | U140: =+(1-S140)*$C140 -> 22.8 | V140: 0.4 | X140: =+(1-V140)*$C140 -> 22.8
A141: DECKRAC8202 | B141: =VLOOKUP(A141,'DB Accessori'!A:G,7,0) -> A2 | C141: 25 | D141: 0.4 | F141: =+(1-D141)*$C141 -> 15 | G141: 0.4 | I141: =+(1-G141)*$C141 -> 15 | J141: 0.4 | L141: =+(1-J141)*$C141 -> 15 | M141: 0.4 | O141: =+(1-M141)*$C141 -> 15 | P141: 0.4 | R141: =+(1-P141)*$C141 -> 15 | S141: 0.4 | U141: =+(1-S141)*$C141 -> 15 | V141: 0.4 | X141: =+(1-V141)*$C141 -> 15
A142: DECKRAC8203 | B142: =VLOOKUP(A142,'DB Accessori'!A:G,7,0) -> A3 | C142: 100 | D142: 0.4 | F142: =+(1-D142)*$C142 -> 60 | G142: 0.4 | I142: =+(1-G142)*$C142 -> 60 | J142: 0.4 | L142: =+(1-J142)*$C142 -> 60 | M142: 0.4 | O142: =+(1-M142)*$C142 -> 60 | P142: 0.4 | R142: =+(1-P142)*$C142 -> 60 | S142: 0.4 | U142: =+(1-S142)*$C142 -> 60 | V142: 0.4 | X142: =+(1-V142)*$C142 -> 60
A143: DECKRAC8204 | B143: =VLOOKUP(A143,'DB Accessori'!A:G,7,0) -> A4 | C143: 100 | D143: 0.4 | F143: =+(1-D143)*$C143 -> 60 | G143: 0.4 | I143: =+(1-G143)*$C143 -> 60 | J143: 0.4 | L143: =+(1-J143)*$C143 -> 60 | M143: 0.4 | O143: =+(1-M143)*$C143 -> 60 | P143: 0.4 | R143: =+(1-P143)*$C143 -> 60 | S143: 0.4 | U143: =+(1-S143)*$C143 -> 60 | V143: 0.4 | X143: =+(1-V143)*$C143 -> 60
A144: DECKRAC8205 | B144: =VLOOKUP(A144,'DB Accessori'!A:G,7,0) -> A5 | C144: 38 | D144: 0.4 | F144: =+(1-D144)*$C144 -> 22.8 | G144: 0.4 | I144: =+(1-G144)*$C144 -> 22.8 | J144: 0.4 | L144: =+(1-J144)*$C144 -> 22.8 | M144: 0.4 | O144: =+(1-M144)*$C144 -> 22.8 | P144: 0.4 | R144: =+(1-P144)*$C144 -> 22.8 | S144: 0.4 | U144: =+(1-S144)*$C144 -> 22.8 | V144: 0.4 | X144: =+(1-V144)*$C144 -> 22.8
A145: DECKRAC8206 | B145: =VLOOKUP(A145,'DB Accessori'!A:G,7,0) -> A6 | C145: 38 | D145: 0.4 | F145: =+(1-D145)*$C145 -> 22.8 | G145: 0.4 | I145: =+(1-G145)*$C145 -> 22.8 | J145: 0.4 | L145: =+(1-J145)*$C145 -> 22.8 | M145: 0.4 | O145: =+(1-M145)*$C145 -> 22.8 | P145: 0.4 | R145: =+(1-P145)*$C145 -> 22.8 | S145: 0.4 | U145: =+(1-S145)*$C145 -> 22.8 | V145: 0.4 | X145: =+(1-V145)*$C145 -> 22.8
... A247: DECKRAC8287 | B247: =VLOOKUP(A247,'DB Accessori'!A:G,7,0) -> A87 | C247: 120 | D247: 0.4 | F247: =+(1-D247)*$C247 -> 72 | G247: 0.4 | I247: =+(1-G247)*$C247 -> 72 | J247: 0.4 | L247: =+(1-J247)*$C247 -> 72 | M247: 0.4 | O247: =+(1-M247)*$C247 -> 72 | P247: 0.4 | R247: =+(1-P247)*$C247 -> 72 | S247: 0.4 | U247: =+(1-S247)*$C247 -> 72 | V247: 0.4 | X247: =+(1-V247)*$C247 -> 72

Sheet Equipment
E1: PRICE LIST 2026 (EURO) | J1: ENGLISH | K1: Validity 2026.01.01 | L1: CEE & CIS
C2: =IFERROR(VLOOKUP($J$1,Language!$A$11:$F$15,2,0),"Select a Language Above") -> Effective date: | E2: =IFERROR(VLOOKUP($J$1,Language!$C:$J,2,FALSE),"Select a Language Above") -> CUSTOMER CODE
E3: =IFERROR(VLOOKUP($J$1,Language!$C:$J,3,FALSE),"Select a Language Above") -> CUSTOMER NAME
E4: =IFERROR(VLOOKUP($J$1,Language!$C:$J,4,FALSE),"Select a Language Above") -> COUNTRY
E5: =IFERROR(VLOOKUP($J$1,Language!$C:$J,5,FALSE),"Select a Language Above") -> PAYMENT TERM
C6: =IFERROR(VLOOKUP($J$1,Language!$A$11:$F$15,4,0),"Select a Language Above") -> Sales Manager: | E6: =IFERROR(VLOOKUP($J$1,Language!$C:$J,6,FALSE),"Select a Language Above") -> REFERENCED PRICE LIST | F6: PL 2025.04
E7: =IFERROR(VLOOKUP($J$1,Language!$C:$J,7,FALSE),"Select a Language Above") -> CURRENCY | F7: Euro
C8: =IFERROR(VLOOKUP($J$1,Language!$A$11:$F$15,6,0),"Select a Language Above") -> Base Price | E8: =IFERROR(VLOOKUP($J$1,Language!$C:$J,8,FALSE),"Select a Language Above") -> CREDIT LIMIT
B10: =IFERROR(VLOOKUP($J$1,Language!$A$19:$N$23,2,0),"Select a Language Above") -> PRODUCT IMAGE | C10: =IFERROR(VLOOKUP($J$1,Language!$A$19:$N$23,7,0),"Select a Language Above") -> PRODUCT TYPE | E10: =IFERROR(VLOOKUP($J$1,Language!$A$19:$N$23,3,0),"Select a Language Above") -> P/N | F10: =IFERROR(VLOOKUP($J$1,Language!$A$19:$N$23,4,0),"Select a Language Above") -> MODEL | G10: LANGUAGE | H10: =IFERROR(VLOOKUP($J$1,Language!$A$19:$N$23,5,0),"Select a Language Above") -> VOLTAGE | I10: SEAWORTHY PACKAGE | J10: =IFERROR(VLOOKUP($J$1,Language!$A$19:$N$23,6,0),"Select a Language Above") -> DESCRIPTION | K10: List Price | L10: =IFERROR(VLOOKUP($J$1,Language!$A$19:$N$23,11,0),"Select a Language Above") -> Discount | M10: =IFERROR(VLOOKUP($J$1,Language!$A$19:$Q$23,17,0),"Select a Language Above") -> Discount 2 | N10: Net Price
B11: #VALUE! | C11: =IF($J$1="ITALIANO",VLOOKUP(E11,'DB Equipment'!$A:$K,7,0),IF($J$1="ESPAÑOL",VLOOKUP(E11,'DB Equipment'!$A:$K,6,0),IF($J$1="DEUTSCH",VLOOKUP(E11,'DB Equipment'!$A:$K,4,0),IF($J$1="FRANÇAIS",VLOOKUP(E11,'DB Equipment'!$A:$K,5,0),IF($J$1="ENGLISH",VLOOKUP(E11,'DB Equipment'!$A:$K,3,0),""))))) -> PDL | D11: =VLOOKUP(E11,'DB Equipment'!A:P,2,0) -> PDL 4200 | E11: EESCDE137A | F11: =VLOOKUP(E11,'DB Equipment'!A:K,8,0) -> PDL 4200 German | G11: =IF(VLOOKUP(E11,'DB Equipment'!A:K,9,0)=0,"",VLOOKUP(E11,'DB Equipment'!A:K,9,0)) -> German | H11: =IF(VLOOKUP(E11,'DB Equipment'!A:K,10,0)=0,"",VLOOKUP(E11,'DB Equipment'!A:K,10,0)) | I11: =IF(VLOOKUP(E11,'DB Equipment'!A:K,11,0)=0,"",VLOOKUP(E11,'DB Equipment'!A:K,11,0)) | J11: =IF(IF($J$1="ITALIANO",VLOOKUP($E11,'DB Equipment'!$A:$P,16,0),IF($J$1="ESPAÑOL",VLOOKUP($E11,'DB Equipment'!$A:$P,15,0),IF($J$1="DEUTSCH",VLOOKUP($E11,'DB Equipment'!$A:$P,13,0),IF($J$1="FRANÇAIS",VLOOKUP($E11,'DB Equipment'!$A:$P,14,0),IF($J$1="ENGLISH",VLOOKUP($E11,'DB Equipment'!$A:$P,12,0),"")))))=0,"",IF($J$1="ITALIANO",VLOOKUP($E11,'DB Equipment'!$A:$P,16,0),IF($J$1="ESPAÑOL",VLOOKUP($E11,'DB Equipment'!$A:$P,15,0),IF($J$1="DEUTSCH",VLOOKUP($E11,'DB Equipment'!$A:$P,13,0),IF($J$1="FRANÇAIS",VLOOKUP($E11,'DB Equipment'!$A:$P,14,0),IF($J$1="ENGLISH",VLOOKUP($E11,'DB Equipment'!$A:$P,12,0),"")))))) -> Including latest software release + free-of-charge updates (2 minimum) for one year, German version | K11: =IF(L$1="Germany",VLOOKUP(E11,Prices!A:AA,16,0),VLOOKUP(E11,Prices!A:AA,3,0)) -> 3785 | L11: =VLOOKUP(E11,Prices!A:AA,HLOOKUP(L$1&"D",Prices!A:AA,2,0),0) -> 0.3 | M11: =IF(VLOOKUP(E11,Prices!A:AA,HLOOKUP(L$1&"2",Prices!A:AA,2,0),0)="","",VLOOKUP(E11,Prices!A:AA,HLOOKUP(L$1&"2",Prices!A:AA,2,0),0)) | N11: =IFERROR(IF(M11="",$K11*(1-L11),$K11*(1-L11)*(1-M11)),"n.a.") -> 2649.5
C12: =IF($J$1="ITALIANO",VLOOKUP(E12,'DB Equipment'!$A:$K,7,0),IF($J$1="ESPAÑOL",VLOOKUP(E12,'DB Equipment'!$A:$K,6,0),IF($J$1="DEUTSCH",VLOOKUP(E12,'DB Equipment'!$A:$K,4,0),IF($J$1="FRANÇAIS",VLOOKUP(E12,'DB Equipment'!$A:$K,5,0),IF($J$1="ENGLISH",VLOOKUP(E12,'DB Equipment'!$A:$K,3,0),""))))) -> PDL | D12: =VLOOKUP(E12,'DB Equipment'!A:P,2,0) -> PDL 4200 | E12: EESCFR137A | F12: =VLOOKUP(E12,'DB Equipment'!A:K,8,0) -> PDL 4200 French | G12: =IF(VLOOKUP(E12,'DB Equipment'!A:K,9,0)=0,"",VLOOKUP(E12,'DB Equipment'!A:K,9,0)) -> French | H12: =IF(VLOOKUP(E12,'DB Equipment'!A:K,10,0)=0,"",VLOOKUP(E12,'DB Equipment'!A:K,10,0)) | I12: =IF(VLOOKUP(E12,'DB Equipment'!A:K,11,0)=0,"",VLOOKUP(E12,'DB Equipment'!A:K,11,0)) | J12: =IF(IF($J$1="ITALIANO",VLOOKUP($E12,'DB Equipment'!$A:$P,16,0),IF($J$1="ESPAÑOL",VLOOKUP($E12,'DB Equipment'!$A:$P,15,0),IF($J$1="DEUTSCH",VLOOKUP($E12,'DB Equipment'!$A:$P,13,0),IF($J$1="FRANÇAIS",VLOOKUP($E12,'DB Equipment'!$A:$P,14,0),IF($J$1="ENGLISH",VLOOKUP($E12,'DB Equipment'!$A:$P,12,0),"")))))=0,"",IF($J$1="ITALIANO",VLOOKUP($E12,'DB Equipment'!$A:$P,16,0),IF($J$1="ESPAÑOL",VLOOKUP($E12,'DB Equipment'!$A:$P,15,0),IF($J$1="DEUTSCH",VLOOKUP($E12,'DB Equipment'!$A:$P,13,0),IF($J$1="FRANÇAIS",VLOOKUP($E12,'DB Equipment'!$A:$P,14,0),IF($J$1="ENGLISH",VLOOKUP($E12,'DB Equipment'!$A:$P,12,0),"")))))) -> Including latest software release + free-of-charge updates (2 minimum) for one year, French version | K12: =IF(L$1="Germany",VLOOKUP(E12,Prices!A:AA,16,0),VLOOKUP(E12,Prices!A:AA,3,0)) -> 3785 | L12: =VLOOKUP(E12,Prices!A:AA,HLOOKUP(L$1&"D",Prices!A:AA,2,0),0) -> 0.3 | M12: =IF(VLOOKUP(E12,Prices!A:AA,HLOOKUP(L$1&"2",Prices!A:AA,2,0),0)="","",VLOOKUP(E12,Prices!A:AA,HLOOKUP(L$1&"2",Prices!A:AA,2,0),0)) | N12: =IFERROR(IF(M12="",$K12*(1-L12),$K12*(1-L12)*(1-M12)),"n.a.") -> 2649.5
C13: =IF($J$1="ITALIANO",VLOOKUP(E13,'DB Equipment'!$A:$K,7,0),IF($J$1="ESPAÑOL",VLOOKUP(E13,'DB Equipment'!$A:$K,6,0),IF($J$1="DEUTSCH",VLOOKUP(E13,'DB Equipment'!$A:$K,4,0),IF($J$1="FRANÇAIS",VLOOKUP(E13,'DB Equipment'!$A:$K,5,0),IF($J$1="ENGLISH",VLOOKUP(E13,'DB Equipment'!$A:$K,3,0),""))))) -> PDL | D13: =VLOOKUP(E13,'DB Equipment'!A:P,2,0) -> PDL 4200 | E13: EESCIT137A | F13: =VLOOKUP(E13,'DB Equipment'!A:K,8,0) -> PDL 4200 Italian | G13: =IF(VLOOKUP(E13,'DB Equipment'!A:K,9,0)=0,"",VLOOKUP(E13,'DB Equipment'!A:K,9,0)) -> Italian | H13: =IF(VLOOKUP(E13,'DB Equipment'!A:K,10,0)=0,"",VLOOKUP(E13,'DB Equipment'!A:K,10,0)) | I13: =IF(VLOOKUP(E13,'DB Equipment'!A:K,11,0)=0,"",VLOOKUP(E13,'DB Equipment'!A:K,11,0)) | J13: =IF(IF($J$1="ITALIANO",VLOOKUP($E13,'DB Equipment'!$A:$P,16,0),IF($J$1="ESPAÑOL",VLOOKUP($E13,'DB Equipment'!$A:$P,15,0),IF($J$1="DEUTSCH",VLOOKUP($E13,'DB Equipment'!$A:$P,13,0),IF($J$1="FRANÇAIS",VLOOKUP($E13,'DB Equipment'!$A:$P,14,0),IF($J$1="ENGLISH",VLOOKUP($E13,'DB Equipment'!$A:$P,12,0),"")))))=0,"",IF($J$1="ITALIANO",VLOOKUP($E13,'DB Equipment'!$A:$P,16,0),IF($J$1="ESPAÑOL",VLOOKUP($E13,'DB Equipment'!$A:$P,15,0),IF($J$1="DEUTSCH",VLOOKUP($E13,'DB Equipment'!$A:$P,13,0),IF($J$1="FRANÇAIS",VLOOKUP($E13,'DB Equipment'!$A:$P,14,0),IF($J$1="ENGLISH",VLOOKUP($E13,'DB Equipment'!$A:$P,12,0),"")))))) -> Including latest software release + free-of-charge updates (2 minimum) for one year, Italian version | K13: =IF(L$1="Germany",VLOOKUP(E13,Prices!A:AA,16,0),VLOOKUP(E13,Prices!A:AA,3,0)) -> 3785 | L13: =VLOOKUP(E13,Prices!A:AA,HLOOKUP(L$1&"D",Prices!A:AA,2,0),0) -> 0.3 | M13: =IF(VLOOKUP(E13,Prices!A:AA,HLOOKUP(L$1&"2",Prices!A:AA,2,0),0)="","",VLOOKUP(E13,Prices!A:AA,HLOOKUP(L$1&"2",Prices!A:AA,2,0),0)) | N13: =IFERROR(IF(M13="",$K13*(1-L13),$K13*(1-L13)*(1-M13)),"n.a.") -> 2649.5
C14: =IF($J$1="ITALIANO",VLOOKUP(E14,'DB Equipment'!$A:$K,7,0),IF($J$1="ESPAÑOL",VLOOKUP(E14,'DB Equipment'!$A:$K,6,0),IF($J$1="DEUTSCH",VLOOKUP(E14,'DB Equipment'!$A:$K,4,0),IF($J$1="FRANÇAIS",VLOOKUP(E14,'DB Equipment'!$A:$K,5,0),IF($J$1="ENGLISH",VLOOKUP(E14,'DB Equipment'!$A:$K,3,0),""))))) -> PDL | D14: =VLOOKUP(E14,'DB Equipment'!A:P,2,0) -> PDL 4200 | E14: EESCPL137A | F14: =VLOOKUP(E14,'DB Equipment'!A:K,8,0) -> PDL 4200 Polish | G14: =IF(VLOOKUP(E14,'DB Equipment'!A:K,9,0)=0,"",VLOOKUP(E14,'DB Equipment'!A:K,9,0)) -> Polish | H14: =IF(VLOOKUP(E14,'DB Equipment'!A:K,10,0)=0,"",VLOOKUP(E14,'DB Equipment'!A:K,10,0)) | I14: =IF(VLOOKUP(E14,'DB Equipment'!A:K,11,0)=0,"",VLOOKUP(E14,'DB Equipment'!A:K,11,0)) | J14: =IF(IF($J$1="ITALIANO",VLOOKUP($E14,'DB Equipment'!$A:$P,16,0),IF($J$1="ESPAÑOL",VLOOKUP($E14,'DB Equipment'!$A:$P,15,0),IF($J$1="DEUTSCH",VLOOKUP($E14,'DB Equipment'!$A:$P,13,0),IF($J$1="FRANÇAIS",VLOOKUP($E14,'DB Equipment'!$A:$P,14,0),IF($J$1="ENGLISH",VLOOKUP($E14,'DB Equipment'!$A:$P,12,0),"")))))=0,"",IF($J$1="ITALIANO",VLOOKUP($E14,'DB Equipment'!$A:$P,16,0),IF($J$1="ESPAÑOL",VLOOKUP($E14,'DB Equipment'!$A:$P,15,0),IF($J$1="DEUTSCH",VLOOKUP($E14,'DB Equipment'!$A:$P,13,0),IF($J$1="FRANÇAIS",VLOOKUP($E14,'DB Equipment'!$A:$P,14,0),IF($J$1="ENGLISH",VLOOKUP($E14,'DB Equipment'!$A:$P,12,0),"")))))) -> Including latest software release + free-of-charge updates (2 minimum) for one year, Polish version | K14: =IF(L$1="Germany",VLOOKUP(E14,Prices!A:AA,16,0),VLOOKUP(E14,Prices!A:AA,3,0)) -> 3785 | L14: =VLOOKUP(E14,Prices!A:AA,HLOOKUP(L$1&"D",Prices!A:AA,2,0),0) -> 0.3 | M14: =IF(VLOOKUP(E14,Prices!A:AA,HLOOKUP(L$1&"2",Prices!A:AA,2,0),0)="","",VLOOKUP(E14,Prices!A:AA,HLOOKUP(L$1&"2",Prices!A:AA,2,0),0)) | N14: =IFERROR(IF(M14="",$K14*(1-L14),$K14*(1-L14)*(1-M14)),"n.a.") -> 2649.5
C15: =IF($J$1="ITALIANO",VLOOKUP(E15,'DB Equipment'!$A:$K,7,0),IF($J$1="ESPAÑOL",VLOOKUP(E15,'DB Equipment'!$A:$K,6,0),IF($J$1="DEUTSCH",VLOOKUP(E15,'DB Equipment'!$A:$K,4,0),IF($J$1="FRANÇAIS",VLOOKUP(E15,'DB Equipment'!$A:$K,5,0),IF($J$1="ENGLISH",VLOOKUP(E15,'DB Equipment'!$A:$K,3,0),""))))) -> PDL | D15: =VLOOKUP(E15,'DB Equipment'!A:P,2,0) -> PDL 4200 | E15: EESCPL137A x 5 | F15: =VLOOKUP(E15,'DB Equipment'!A:K,8,0) -> PDL 4200 Polish | G15: =IF(VLOOKUP(E15,'DB Equipment'!A:K,9,0)=0,"",VLOOKUP(E15,'DB Equipment'!A:K,9,0)) -> Polish | H15: =IF(VLOOKUP(E15,'DB Equipment'!A:K,10,0)=0,"",VLOOKUP(E15,'DB Equipment'!A:K,10,0)) | I15: =IF(VLOOKUP(E15,'DB Equipment'!A:K,11,0)=0,"",VLOOKUP(E15,'DB Equipment'!A:K,11,0)) | J15: =IF(IF($J$1="ITALIANO",VLOOKUP($E15,'DB Equipment'!$A:$P,16,0),IF($J$1="ESPAÑOL",VLOOKUP($E15,'DB Equipment'!$A:$P,15,0),IF($J$1="DEUTSCH",VLOOKUP($E15,'DB Equipment'!$A:$P,13,0),IF($J$1="FRANÇAIS",VLOOKUP($E15,'DB Equipment'!$A:$P,14,0),IF($J$1="ENGLISH",VLOOKUP($E15,'DB Equipment'!$A:$P,12,0),"")))))=0,"",IF($J$1="ITALIANO",VLOOKUP($E15,'DB Equipment'!$A:$P,16,0),IF($J$1="ESPAÑOL",VLOOKUP($E15,'DB Equipment'!$A:$P,15,0),IF($J$1="DEUTSCH",VLOOKUP($E15,'DB Equipment'!$A:$P,13,0),IF($J$1="FRANÇAIS",VLOOKUP($E15,'DB Equipment'!$A:$P,14,0),IF($J$1="ENGLISH",VLOOKUP($E15,'DB Equipment'!$A:$P,12,0),"")))))) -> 5 unit order | K15: =IF(L$1="Germany",VLOOKUP(E15,Prices!A:AA,16,0),VLOOKUP(E15,Prices!A:AA,3,0)) -> 3785 | L15: =IF(VLOOKUP(E15,Prices!A:AA,HLOOKUP(L$1&"D",Prices!A:AA,2,0),0)=0,"",VLOOKUP(E15,Prices!A:AA,HLOOKUP(L$1&"D",Prices!A:AA,2,0),0)) | M15: =IF(VLOOKUP(E15,Prices!A:AA,HLOOKUP(L$1&"2",Prices!A:AA,2,0),0)="","",VLOOKUP(E15,Prices!A:AA,HLOOKUP(L$1&"2",Prices!A:AA,2,0),0)) | N15: =IFERROR(IF(M15="",$K15*(1-L15),$K15*(1-L15)*(1-M15)),"n.a.") -> n.a.
C16: =IF($J$1="ITALIANO",VLOOKUP(E16,'DB Equipment'!$A:$K,7,0),IF($J$1="ESPAÑOL",VLOOKUP(E16,'DB Equipment'!$A:$K,6,0),IF($J$1="DEUTSCH",VLOOKUP(E16,'DB Equipment'!$A:$K,4,0),IF($J$1="FRANÇAIS",VLOOKUP(E16,'DB Equipment'!$A:$K,5,0),IF($J$1="ENGLISH",VLOOKUP(E16,'DB Equipment'!$A:$K,3,0),""))))) -> PDL | D16: =VLOOKUP(E16,'DB Equipment'!A:P,2,0) -> PDL 4200 | E16: EESCPL137A x 10 | F16: =VLOOKUP(E16,'DB Equipment'!A:K,8,0) -> PDL 4200 Polish | G16: =IF(VLOOKUP(E16,'DB Equipment'!A:K,9,0)=0,"",VLOOKUP(E16,'DB Equipment'!A:K,9,0)) -> Polish | H16: =IF(VLOOKUP(E16,'DB Equipment'!A:K,10,0)=0,"",VLOOKUP(E16,'DB Equipment'!A:K,10,0)) | I16: =IF(VLOOKUP(E16,'DB Equipment'!A:K,11,0)=0,"",VLOOKUP(E16,'DB Equipment'!A:K,11,0)) | J16: =IF(IF($J$1="ITALIANO",VLOOKUP($E16,'DB Equipment'!$A:$P,16,0),IF($J$1="ESPAÑOL",VLOOKUP($E16,'DB Equipment'!$A:$P,15,0),IF($J$1="DEUTSCH",VLOOKUP($E16,'DB Equipment'!$A:$P,13,0),IF($J$1="FRANÇAIS",VLOOKUP($E16,'DB Equipment'!$A:$P,14,0),IF($J$1="ENGLISH",VLOOKUP($E16,'DB Equipment'!$A:$P,12,0),"")))))=0,"",IF($J$1="ITALIANO",VLOOKUP($E16,'DB Equipment'!$A:$P,16,0),IF($J$1="ESPAÑOL",VLOOKUP($E16,'DB Equipment'!$A:$P,15,0),IF($J$1="DEUTSCH",VLOOKUP($E16,'DB Equipment'!$A:$P,13,0),IF($J$1="FRANÇAIS",VLOOKUP($E16,'DB Equipment'!$A:$P,14,0),IF($J$1="ENGLISH",VLOOKUP($E16,'DB Equipment'!$A:$P,12,0),"")))))) -> 10 unit order | K16: =IF(L$1="Germany",VLOOKUP(E16,Prices!A:AA,16,0),VLOOKUP(E16,Prices!A:AA,3,0)) -> 3785 | L16: =IF(VLOOKUP(E16,Prices!A:AA,HLOOKUP(L$1&"D",Prices!A:AA,2,0),0)=0,"",VLOOKUP(E16,Prices!A:AA,HLOOKUP(L$1&"D",Prices!A:AA,2,0),0)) | M16: =IF(VLOOKUP(E16,Prices!A:AA,HLOOKUP(L$1&"2",Prices!A:AA,2,0),0)="","",VLOOKUP(E16,Prices!A:AA,HLOOKUP(L$1&"2",Prices!A:AA,2,0),0)) | N16: =IFERROR(IF(M16="",$K16*(1-L16),$K16*(1-L16)*(1-M16)),"n.a.") -> n.a.
C17: =IF($J$1="ITALIANO",VLOOKUP(E17,'DB Equipment'!$A:$K,7,0),IF($J$1="ESPAÑOL",VLOOKUP(E17,'DB Equipment'!$A:$K,6,0),IF($J$1="DEUTSCH",VLOOKUP(E17,'DB Equipment'!$A:$K,4,0),IF($J$1="FRANÇAIS",VLOOKUP(E17,'DB Equipment'!$A:$K,5,0),IF($J$1="ENGLISH",VLOOKUP(E17,'DB Equipment'!$A:$K,3,0),""))))) -> PDL | D17: =VLOOKUP(E17,'DB Equipment'!A:P,2,0) -> PDL 4200 | E17: EESCEG137A | F17: =VLOOKUP(E17,'DB Equipment'!A:K,8,0) -> PDL 4200 English | G17: =IF(VLOOKUP(E17,'DB Equipment'!A:K,9,0)=0,"",VLOOKUP(E17,'DB Equipment'!A:K,9,0)) -> English | H17: =IF(VLOOKUP(E17,'DB Equipment'!A:K,10,0)=0,"",VLOOKUP(E17,'DB Equipment'!A:K,10,0)) | I17: =IF(VLOOKUP(E17,'DB Equipment'!A:K,11,0)=0,"",VLOOKUP(E17,'DB Equipment'!A:K,11,0)) | J17: =IF(IF($J$1="ITALIANO",VLOOKUP($E17,'DB Equipment'!$A:$P,16,0),IF($J$1="ESPAÑOL",VLOOKUP($E17,'DB Equipment'!$A:$P,15,0),IF($J$1="DEUTSCH",VLOOKUP($E17,'DB Equipment'!$A:$P,13,0),IF($J$1="FRANÇAIS",VLOOKUP($E17,'DB Equipment'!$A:$P,14,0),IF($J$1="ENGLISH",VLOOKUP($E17,'DB Equipment'!$A:$P,12,0),"")))))=0,"",IF($J$1="ITALIANO",VLOOKUP($E17,'DB Equipment'!$A:$P,16,0),IF($J$1="ESPAÑOL",VLOOKUP($E17,'DB Equipment'!$A:$P,15,0),IF($J$1="DEUTSCH",VLOOKUP($E17,'DB Equipment'!$A:$P,13,0),IF($J$1="FRANÇAIS",VLOOKUP($E17,'DB Equipment'!$A:$P,14,0),IF($J$1="ENGLISH",VLOOKUP($E17,'DB Equipment'!$A:$P,12,0),"")))))) -> Including latest software release + free-of-charge updates (2 minimum) for one year, English version | K17: =IF(L$1="Germany",VLOOKUP(E17,Prices!A:AA,16,0),VLOOKUP(E17,Prices!A:AA,3,0)) -> 3785 | L17: =VLOOKUP(E17,Prices!A:AA,HLOOKUP(L$1&"D",Prices!A:AA,2,0),0) -> 0.3 | M17: =IF(VLOOKUP(E17,Prices!A:AA,HLOOKUP(L$1&"2",Prices!A:AA,2,0),0)="","",VLOOKUP(E17,Prices!A:AA,HLOOKUP(L$1&"2",Prices!A:AA,2,0),0)) | N17: =IFERROR(IF(M17="",$K17*(1-L17),$K17*(1-L17)*(1-M17)),"n.a.") -> 2649.5
B18: #VALUE! | C18: =IF($J$1="ITALIANO",VLOOKUP(E18,'DB Equipment'!$A:$K,7,0),IF($J$1="ESPAÑOL",VLOOKUP(E18,'DB Equipment'!$A:$K,6,0),IF($J$1="DEUTSCH",VLOOKUP(E18,'DB Equipment'!$A:$K,4,0),IF($J$1="FRANÇAIS",VLOOKUP(E18,'DB Equipment'!$A:$K,5,0),IF($J$1="ENGLISH",VLOOKUP(E18,'DB Equipment'!$A:$K,3,0),""))))) -> PDL | D18: =VLOOKUP(E18,'DB Equipment'!A:P,2,0) -> PDL 7100 | E18: EESCDE135A | F18: =VLOOKUP(E18,'DB Equipment'!A:K,8,0) -> PDL 7100 German | G18: =IF(VLOOKUP(E18,'DB Equipment'!A:K,9,0)=0,"",VLOOKUP(E18,'DB Equipment'!A:K,9,0)) -> German | H18: =IF(VLOOKUP(E18,'DB Equipment'!A:K,10,0)=0,"",VLOOKUP(E18,'DB Equipment'!A:K,10,0)) | I18: =IF(VLOOKUP(E18,'DB Equipment'!A:K,11,0)=0,"",VLOOKUP(E18,'DB Equipment'!A:K,11,0)) | J18: =IF(IF($J$1="ITALIANO",VLOOKUP($E18,'DB Equipment'!$A:$P,16,0),IF($J$1="ESPAÑOL",VLOOKUP($E18,'DB Equipment'!$A:$P,15,0),IF($J$1="DEUTSCH",VLOOKUP($E18,'DB Equipment'!$A:$P,13,0),IF($J$1="FRANÇAIS",VLOOKUP($E18,'DB Equipment'!$A:$P,14,0),IF($J$1="ENGLISH",VLOOKUP($E18,'DB Equipment'!$A:$P,12,0),"")))))=0,"",IF($J$1="ITALIANO",VLOOKUP($E18,'DB Equipment'!$A:$P,16,0),IF($J$1="ESPAÑOL",VLOOKUP($E18,'DB Equipment'!$A:$P,15,0),IF($J$1="DEUTSCH",VLOOKUP($E18,'DB Equipment'!$A:$P,13,0),IF($J$1="FRANÇAIS",VLOOKUP($E18,'DB Equipment'!$A:$P,14,0),IF($J$1="ENGLISH",VLOOKUP($E18,'DB Equipment'!$A:$P,12,0),"")))))) -> Including latest software release + free-of-charge updates (2 minimum) for one year, German version | K18: =IF(L$1="Germany",VLOOKUP(E18,Prices!A:AA,16,0),VLOOKUP(E18,Prices!A:AA,3,0)) -> 4210 | L18: =VLOOKUP(E18,Prices!A:AA,HLOOKUP(L$1&"D",Prices!A:AA,2,0),0) -> 0.3 | M18: =IF(VLOOKUP(E18,Prices!A:AA,HLOOKUP(L$1&"2",Prices!A:AA,2,0),0)="","",VLOOKUP(E18,Prices!A:AA,HLOOKUP(L$1&"2",Prices!A:AA,2,0),0)) | N18: =IFERROR(IF(M18="",$K18*(1-L18),$K18*(1-L18)*(1-M18)),"n.a.") -> 2947
C19: =IF($J$1="ITALIANO",VLOOKUP(E19,'DB Equipment'!$A:$K,7,0),IF($J$1="ESPAÑOL",VLOOKUP(E19,'DB Equipment'!$A:$K,6,0),IF($J$1="DEUTSCH",VLOOKUP(E19,'DB Equipment'!$A:$K,4,0),IF($J$1="FRANÇAIS",VLOOKUP(E19,'DB Equipment'!$A:$K,5,0),IF($J$1="ENGLISH",VLOOKUP(E19,'DB Equipment'!$A:$K,3,0),""))))) -> PDL | D19: =VLOOKUP(E19,'DB Equipment'!A:P,2,0) -> PDL 7100 | E19: EESCFR135A | F19: =VLOOKUP(E19,'DB Equipment'!A:K,8,0) -> PDL 7100 French | G19: =IF(VLOOKUP(E19,'DB Equipment'!A:K,9,0)=0,"",VLOOKUP(E19,'DB Equipment'!A:K,9,0)) -> French | H19: =IF(VLOOKUP(E19,'DB Equipment'!A:K,10,0)=0,"",VLOOKUP(E19,'DB Equipment'!A:K,10,0)) | I19: =IF(VLOOKUP(E19,'DB Equipment'!A:K,11,0)=0,"",VLOOKUP(E19,'DB Equipment'!A:K,11,0)) | J19: =IF(IF($J$1="ITALIANO",VLOOKUP($E19,'DB Equipment'!$A:$P,16,0),IF($J$1="ESPAÑOL",VLOOKUP($E19,'DB Equipment'!$A:$P,15,0),IF($J$1="DEUTSCH",VLOOKUP($E19,'DB Equipment'!$A:$P,13,0),IF($J$1="FRANÇAIS",VLOOKUP($E19,'DB Equipment'!$A:$P,14,0),IF($J$1="ENGLISH",VLOOKUP($E19,'DB Equipment'!$A:$P,12,0),"")))))=0,"",IF($J$1="ITALIANO",VLOOKUP($E19,'DB Equipment'!$A:$P,16,0),IF($J$1="ESPAÑOL",VLOOKUP($E19,'DB Equipment'!$A:$P,15,0),IF($J$1="DEUTSCH",VLOOKUP($E19,'DB Equipment'!$A:$P,13,0),IF($J$1="FRANÇAIS",VLOOKUP($E19,'DB Equipment'!$A:$P,14,0),IF($J$1="ENGLISH",VLOOKUP($E19,'DB Equipment'!$A:$P,12,0),"")))))) -> Including latest software release + free-of-charge updates (2 minimum) for one year, French version | K19: =IF(L$1="Germany",VLOOKUP(E19,Prices!A:AA,16,0),VLOOKUP(E19,Prices!A:AA,3,0)) -> 4210 | L19: =VLOOKUP(E19,Prices!A:AA,HLOOKUP(L$1&"D",Prices!A:AA,2,0),0) -> 0.3 | M19: =IF(VLOOKUP(E19,Prices!A:AA,HLOOKUP(L$1&"2",Prices!A:AA,2,0),0)="","",VLOOKUP(E19,Prices!A:AA,HLOOKUP(L$1&"2",Prices!A:AA,2,0),0)) | N19: =IFERROR(IF(M19="",$K19*(1-L19),$K19*(1-L19)*(1-M19)),"n.a.") -> 2947
C20: =IF($J$1="ITALIANO",VLOOKUP(E20,'DB Equipment'!$A:$K,7,0),IF($J$1="ESPAÑOL",VLOOKUP(E20,'DB Equipment'!$A:$K,6,0),IF($J$1="DEUTSCH",VLOOKUP(E20,'DB Equipment'!$A:$K,4,0),IF($J$1="FRANÇAIS",VLOOKUP(E20,'DB Equipment'!$A:$K,5,0),IF($J$1="ENGLISH",VLOOKUP(E20,'DB Equipment'!$A:$K,3,0),""))))) -> PDL | D20: =VLOOKUP(E20,'DB Equipment'!A:P,2,0) -> PDL 7100 | E20: EESCIT135A | F20: =VLOOKUP(E20,'DB Equipment'!A:K,8,0) -> PDL 7100 Italian | G20: =IF(VLOOKUP(E20,'DB Equipment'!A:K,9,0)=0,"",VLOOKUP(E20,'DB Equipment'!A:K,9,0)) -> Italian | H20: =IF(VLOOKUP(E20,'DB Equipment'!A:K,10,0)=0,"",VLOOKUP(E20,'DB Equipment'!A:K,10,0)) | I20: =IF(VLOOKUP(E20,'DB Equipment'!A:K,11,0)=0,"",VLOOKUP(E20,'DB Equipment'!A:K,11,0)) | J20: =IF(IF($J$1="ITALIANO",VLOOKUP($E20,'DB Equipment'!$A:$P,16,0),IF($J$1="ESPAÑOL",VLOOKUP($E20,'DB Equipment'!$A:$P,15,0),IF($J$1="DEUTSCH",VLOOKUP($E20,'DB Equipment'!$A:$P,13,0),IF($J$1="FRANÇAIS",VLOOKUP($E20,'DB Equipment'!$A:$P,14,0),IF($J$1="ENGLISH",VLOOKUP($E20,'DB Equipment'!$A:$P,12,0),"")))))=0,"",IF($J$1="ITALIANO",VLOOKUP($E20,'DB Equipment'!$A:$P,16,0),IF($J$1="ESPAÑOL",VLOOKUP($E20,'DB Equipment'!$A:$P,15,0),IF($J$1="DEUTSCH",VLOOKUP($E20,'DB Equipment'!$A:$P,13,0),IF($J$1="FRANÇAIS",VLOOKUP($E20,'DB Equipment'!$A:$P,14,0),IF($J$1="ENGLISH",VLOOKUP($E20,'DB Equipment'!$A:$P,12,0),"")))))) -> Including latest software release + free-of-charge updates (2 minimum) for one year, Italian version | K20: =IF(L$1="Germany",VLOOKUP(E20,Prices!A:AA,16,0),VLOOKUP(E20,Prices!A:AA,3,0)) -> 4210 | L20: =VLOOKUP(E20,Prices!A:AA,HLOOKUP(L$1&"D",Prices!A:AA,2,0),0) -> 0.3 | M20: =IF(VLOOKUP(E20,Prices!A:AA,HLOOKUP(L$1&"2",Prices!A:AA,2,0),0)="","",VLOOKUP(E20,Prices!A:AA,HLOOKUP(L$1&"2",Prices!A:AA,2,0),0)) | N20: =IFERROR(IF(M20="",$K20*(1-L20),$K20*(1-L20)*(1-M20)),"n.a.") -> 2947
C21: =IF($J$1="ITALIANO",VLOOKUP(E21,'DB Equipment'!$A:$K,7,0),IF($J$1="ESPAÑOL",VLOOKUP(E21,'DB Equipment'!$A:$K,6,0),IF($J$1="DEUTSCH",VLOOKUP(E21,'DB Equipment'!$A:$K,4,0),IF($J$1="FRANÇAIS",VLOOKUP(E21,'DB Equipment'!$A:$K,5,0),IF($J$1="ENGLISH",VLOOKUP(E21,'DB Equipment'!$A:$K,3,0),""))))) -> PDL | D21: =VLOOKUP(E21,'DB Equipment'!A:P,2,0) -> PDL 7100 | E21: EESCPL135A | F21: =VLOOKUP(E21,'DB Equipment'!A:K,8,0) -> PDL 7100 Polish | G21: =IF(VLOOKUP(E21,'DB Equipment'!A:K,9,0)=0,"",VLOOKUP(E21,'DB Equipment'!A:K,9,0)) -> Polish | H21: =IF(VLOOKUP(E21,'DB Equipment'!A:K,10,0)=0,"",VLOOKUP(E21,'DB Equipment'!A:K,10,0)) | I21: =IF(VLOOKUP(E21,'DB Equipment'!A:K,11,0)=0,"",VLOOKUP(E21,'DB Equipment'!A:K,11,0)) | J21: =IF(IF($J$1="ITALIANO",VLOOKUP($E21,'DB Equipment'!$A:$P,16,0),IF($J$1="ESPAÑOL",VLOOKUP($E21,'DB Equipment'!$A:$P,15,0),IF($J$1="DEUTSCH",VLOOKUP($E21,'DB Equipment'!$A:$P,13,0),IF($J$1="FRANÇAIS",VLOOKUP($E21,'DB Equipment'!$A:$P,14,0),IF($J$1="ENGLISH",VLOOKUP($E21,'DB Equipment'!$A:$P,12,0),"")))))=0,"",IF($J$1="ITALIANO",VLOOKUP($E21,'DB Equipment'!$A:$P,16,0),IF($J$1="ESPAÑOL",VLOOKUP($E21,'DB Equipment'!$A:$P,15,0),IF($J$1="DEUTSCH",VLOOKUP($E21,'DB Equipment'!$A:$P,13,0),IF($J$1="FRANÇAIS",VLOOKUP($E21,'DB Equipment'!$A:$P,14,0),IF($J$1="ENGLISH",VLOOKUP($E21,'DB Equipment'!$A:$P,12,0),"")))))) -> Including latest software release + free-of-charge updates (2 minimum) for one year, Polish version | K21: =IF(L$1="Germany",VLOOKUP(E21,Prices!A:AA,16,0),VLOOKUP(E21,Prices!A:AA,3,0)) -> 4210 | L21: =VLOOKUP(E21,Prices!A:AA,HLOOKUP(L$1&"D",Prices!A:AA,2,0),0) -> 0.3 | M21: =IF(VLOOKUP(E21,Prices!A:AA,HLOOKUP(L$1&"2",Prices!A:AA,2,0),0)="","",VLOOKUP(E21,Prices!A:AA,HLOOKUP(L$1&"2",Prices!A:AA,2,0),0)) | N21: =IFERROR(IF(M21="",$K21*(1-L21),$K21*(1-L21)*(1-M21)),"n.a.") -> 2947
C22: =IF($J$1="ITALIANO",VLOOKUP(E22,'DB Equipment'!$A:$K,7,0),IF($J$1="ESPAÑOL",VLOOKUP(E22,'DB Equipment'!$A:$K,6,0),IF($J$1="DEUTSCH",VLOOKUP(E22,'DB Equipment'!$A:$K,4,0),IF($J$1="FRANÇAIS",VLOOKUP(E22,'DB Equipment'!$A:$K,5,0),IF($J$1="ENGLISH",VLOOKUP(E22,'DB Equipment'!$A:$K,3,0),""))))) -> PDL | D22: =VLOOKUP(E22,'DB Equipment'!A:P,2,0) -> PDL 7100 | E22: EESCPL135A x 5 | F22: =VLOOKUP(E22,'DB Equipment'!A:K,8,0) -> PDL 7100 Polish | G22: =IF(VLOOKUP(E22,'DB Equipment'!A:K,9,0)=0,"",VLOOKUP(E22,'DB Equipment'!A:K,9,0)) -> Polish | H22: =IF(VLOOKUP(E22,'DB Equipment'!A:K,10,0)=0,"",VLOOKUP(E22,'DB Equipment'!A:K,10,0)) | I22: =IF(VLOOKUP(E22,'DB Equipment'!A:K,11,0)=0,"",VLOOKUP(E22,'DB Equipment'!A:K,11,0)) | J22: =IF(IF($J$1="ITALIANO",VLOOKUP($E22,'DB Equipment'!$A:$P,16,0),IF($J$1="ESPAÑOL",VLOOKUP($E22,'DB Equipment'!$A:$P,15,0),IF($J$1="DEUTSCH",VLOOKUP($E22,'DB Equipment'!$A:$P,13,0),IF($J$1="FRANÇAIS",VLOOKUP($E22,'DB Equipment'!$A:$P,14,0),IF($J$1="ENGLISH",VLOOKUP($E22,'DB Equipment'!$A:$P,12,0),"")))))=0,"",IF($J$1="ITALIANO",VLOOKUP($E22,'DB Equipment'!$A:$P,16,0),IF($J$1="ESPAÑOL",VLOOKUP($E22,'DB Equipment'!$A:$P,15,0),IF($J$1="DEUTSCH",VLOOKUP($E22,'DB Equipment'!$A:$P,13,0),IF($J$1="FRANÇAIS",VLOOKUP($E22,'DB Equipment'!$A:$P,14,0),IF($J$1="ENGLISH",VLOOKUP($E22,'DB Equipment'!$A:$P,12,0),"")))))) -> 5 unit order | K22: =IF(L$1="Germany",VLOOKUP(E22,Prices!A:AA,16,0),VLOOKUP(E22,Prices!A:AA,3,0)) -> 4210 | L22: =IF(VLOOKUP(E22,Prices!A:AA,HLOOKUP(L$1&"D",Prices!A:AA,2,0),0)=0,"",VLOOKUP(E22,Prices!A:AA,HLOOKUP(L$1&"D",Prices!A:AA,2,0),0)) | M22: =IF(VLOOKUP(E22,Prices!A:AA,HLOOKUP(L$1&"2",Prices!A:AA,2,0),0)="","",VLOOKUP(E22,Prices!A:AA,HLOOKUP(L$1&"2",Prices!A:AA,2,0),0)) | N22: =IFERROR(IF(M22="",$K22*(1-L22),$K22*(1-L22)*(1-M22)),"n.a.") -> n.a.
C23: =IF($J$1="ITALIANO",VLOOKUP(E23,'DB Equipment'!$A:$K,7,0),IF($J$1="ESPAÑOL",VLOOKUP(E23,'DB Equipment'!$A:$K,6,0),IF($J$1="DEUTSCH",VLOOKUP(E23,'DB Equipment'!$A:$K,4,0),IF($J$1="FRANÇAIS",VLOOKUP(E23,'DB Equipment'!$A:$K,5,0),IF($J$1="ENGLISH",VLOOKUP(E23,'DB Equipment'!$A:$K,3,0),""))))) -> PDL | D23: =VLOOKUP(E23,'DB Equipment'!A:P,2,0) -> PDL 7100 | E23: EESCPL135A x 10 | F23: =VLOOKUP(E23,'DB Equipment'!A:K,8,0) -> PDL 7100 Polish | G23: =IF(VLOOKUP(E23,'DB Equipment'!A:K,9,0)=0,"",VLOOKUP(E23,'DB Equipment'!A:K,9,0)) -> Polish | H23: =IF(VLOOKUP(E23,'DB Equipment'!A:K,10,0)=0,"",VLOOKUP(E23,'DB Equipment'!A:K,10,0)) | I23: =IF(VLOOKUP(E23,'DB Equipment'!A:K,11,0)=0,"",VLOOKUP(E23,'DB Equipment'!A:K,11,0)) | J23: =IF(IF($J$1="ITALIANO",VLOOKUP($E23,'DB Equipment'!$A:$P,16,0),IF($J$1="ESPAÑOL",VLOOKUP($E23,'DB Equipment'!$A:$P,15,0),IF($J$1="DEUTSCH",VLOOKUP($E23,'DB Equipment'!$A:$P,13,0),IF($J$1="FRANÇAIS",VLOOKUP($E23,'DB Equipment'!$A:$P,14,0),IF($J$1="ENGLISH",VLOOKUP($E23,'DB Equipment'!$A:$P,12,0),"")))))=0,"",IF($J$1="ITALIANO",VLOOKUP($E23,'DB Equipment'!$A:$P,16,0),IF($J$1="ESPAÑOL",VLOOKUP($E23,'DB Equipment'!$A:$P,15,0),IF($J$1="DEUTSCH",VLOOKUP($E23,'DB Equipment'!$A:$P,13,0),IF($J$1="FRANÇAIS",VLOOKUP($E23,'DB Equipment'!$A:$P,14,0),IF($J$1="ENGLISH",VLOOKUP($E23,'DB Equipment'!$A:$P,12,0),"")))))) -> 10 unit order | K23: =IF(L$1="Germany",VLOOKUP(E23,Prices!A:AA,16,0),VLOOKUP(E23,Prices!A:AA,3,0)) -> 4210 | L23: =IF(VLOOKUP(E23,Prices!A:AA,HLOOKUP(L$1&"D",Prices!A:AA,2,0),0)=0,"",VLOOKUP(E23,Prices!A:AA,HLOOKUP(L$1&"D",Prices!A:AA,2,0),0)) | M23: =IF(VLOOKUP(E23,Prices!A:AA,HLOOKUP(L$1&"2",Prices!A:AA,2,0),0)="","",VLOOKUP(E23,Prices!A:AA,HLOOKUP(L$1&"2",Prices!A:AA,2,0),0)) | N23: =IFERROR(IF(M23="",$K23*(1-L23),$K23*(1-L23)*(1-M23)),"n.a.") -> n.a.
C24: =IF($J$1="ITALIANO",VLOOKUP(E24,'DB Equipment'!$A:$K,7,0),IF($J$1="ESPAÑOL",VLOOKUP(E24,'DB Equipment'!$A:$K,6,0),IF($J$1="DEUTSCH",VLOOKUP(E24,'DB Equipment'!$A:$K,4,0),IF($J$1="FRANÇAIS",VLOOKUP(E24,'DB Equipment'!$A:$K,5,0),IF($J$1="ENGLISH",VLOOKUP(E24,'DB Equipment'!$A:$K,3,0),""))))) -> PDL | D24: =VLOOKUP(E24,'DB Equipment'!A:P,2,0) -> PDL 7100 | E24: EESCEG135A | F24: =VLOOKUP(E24,'DB Equipment'!A:K,8,0) -> PDL 7100 English | G24: =IF(VLOOKUP(E24,'DB Equipment'!A:K,9,0)=0,"",VLOOKUP(E24,'DB Equipment'!A:K,9,0)) -> English | H24: =IF(VLOOKUP(E24,'DB Equipment'!A:K,10,0)=0,"",VLOOKUP(E24,'DB Equipment'!A:K,10,0)) | I24: =IF(VLOOKUP(E24,'DB Equipment'!A:K,11,0)=0,"",VLOOKUP(E24,'DB Equipment'!A:K,11,0)) | J24: =IF(IF($J$1="ITALIANO",VLOOKUP($E24,'DB Equipment'!$A:$P,16,0),IF($J$1="ESPAÑOL",VLOOKUP($E24,'DB Equipment'!$A:$P,15,0),IF($J$1="DEUTSCH",VLOOKUP($E24,'DB Equipment'!$A:$P,13,0),IF($J$1="FRANÇAIS",VLOOKUP($E24,'DB Equipment'!$A:$P,14,0),IF($J$1="ENGLISH",VLOOKUP($E24,'DB Equipment'!$A:$P,12,0),"")))))=0,"",IF($J$1="ITALIANO",VLOOKUP($E24,'DB Equipment'!$A:$P,16,0),IF($J$1="ESPAÑOL",VLOOKUP($E24,'DB Equipment'!$A:$P,15,0),IF($J$1="DEUTSCH",VLOOKUP($E24,'DB Equipment'!$A:$P,13,0),IF($J$1="FRANÇAIS",VLOOKUP($E24,'DB Equipment'!$A:$P,14,0),IF($J$1="ENGLISH",VLOOKUP($E24,'DB Equipment'!$A:$P,12,0),"")))))) -> Including latest software release + free-of-charge updates (2 minimum) for one year, English version | K24: =IF(L$1="Germany",VLOOKUP(E24,Prices!A:AA,16,0),VLOOKUP(E24,Prices!A:AA,3,0)) -> 4210 | L24: =VLOOKUP(E24,Prices!A:AA,HLOOKUP(L$1&"D",Prices!A:AA,2,0),0) -> 0.3 | M24: =IF(VLOOKUP(E24,Prices!A:AA,HLOOKUP(L$1&"2",Prices!A:AA,2,0),0)="","",VLOOKUP(E24,Prices!A:AA,HLOOKUP(L$1&"2",Prices!A:AA,2,0),0)) | N24: =IFERROR(IF(M24="",$K24*(1-L24),$K24*(1-L24)*(1-M24)),"n.a.") -> 2947
B25: #VALUE! | C25: =IF($J$1="ITALIANO",VLOOKUP(E25,'DB Equipment'!$A:$K,7,0),IF($J$1="ESPAÑOL",VLOOKUP(E25,'DB Equipment'!$A:$K,6,0),IF($J$1="DEUTSCH",VLOOKUP(E25,'DB Equipment'!$A:$K,4,0),IF($J$1="FRANÇAIS",VLOOKUP(E25,'DB Equipment'!$A:$K,5,0),IF($J$1="ENGLISH",VLOOKUP(E25,'DB Equipment'!$A:$K,3,0),""))))) -> PDL | D25: =VLOOKUP(E25,'DB Equipment'!A:P,2,0) -> PDL 8200 | E25: EEMSDE149A | F25: =VLOOKUP(E25,'DB Equipment'!A:K,8,0) -> PDL 8200 German | G25: =IF(VLOOKUP(E25,'DB Equipment'!A:K,9,0)=0,"",VLOOKUP(E25,'DB Equipment'!A:K,9,0)) -> German | H25: =IF(VLOOKUP(E25,'DB Equipment'!A:K,10,0)=0,"",VLOOKUP(E25,'DB Equipment'!A:K,10,0)) | I25: =IF(VLOOKUP(E25,'DB Equipment'!A:K,11,0)=0,"",VLOOKUP(E25,'DB Equipment'!A:K,11,0)) | J25: =IF(IF($J$1="ITALIANO",VLOOKUP($E25,'DB Equipment'!$A:$P,16,0),IF($J$1="ESPAÑOL",VLOOKUP($E25,'DB Equipment'!$A:$P,15,0),IF($J$1="DEUTSCH",VLOOKUP($E25,'DB Equipment'!$A:$P,13,0),IF($J$1="FRANÇAIS",VLOOKUP($E25,'DB Equipment'!$A:$P,14,0),IF($J$1="ENGLISH",VLOOKUP($E25,'DB Equipment'!$A:$P,12,0),"")))))=0,"",IF($J$1="ITALIANO",VLOOKUP($E25,'DB Equipment'!$A:$P,16,0),IF($J$1="ESPAÑOL",VLOOKUP($E25,'DB Equipment'!$A:$P,15,0),IF($J$1="DEUTSCH",VLOOKUP($E25,'DB Equipment'!$A:$P,13,0),IF($J$1="FRANÇAIS",VLOOKUP($E25,'DB Equipment'!$A:$P,14,0),IF($J$1="ENGLISH",VLOOKUP($E25,'DB Equipment'!$A:$P,12,0),"")))))) -> Including latest software release + free-of-charge updates (2 minimum) for one year, German version | K25: =IF(L$1="Germany",VLOOKUP(E25,Prices!A:AA,16,0),VLOOKUP(E25,Prices!A:AA,3,0)) -> 6815 | L25: =VLOOKUP(E25,Prices!A:AA,HLOOKUP(L$1&"D",Prices!A:AA,2,0),0) -> 0.3 | M25: =IF(VLOOKUP(E25,Prices!A:AA,HLOOKUP(L$1&"2",Prices!A:AA,2,0),0)="","",VLOOKUP(E25,Prices!A:AA,HLOOKUP(L$1&"2",Prices!A:AA,2,0),0)) | N25: =IFERROR(IF(M25="",$K25*(1-L25),$K25*(1-L25)*(1-M25)),"n.a.") -> 4770.5
C26: =IF($J$1="ITALIANO",VLOOKUP(E26,'DB Equipment'!$A:$K,7,0),IF($J$1="ESPAÑOL",VLOOKUP(E26,'DB Equipment'!$A:$K,6,0),IF($J$1="DEUTSCH",VLOOKUP(E26,'DB Equipment'!$A:$K,4,0),IF($J$1="FRANÇAIS",VLOOKUP(E26,'DB Equipment'!$A:$K,5,0),IF($J$1="ENGLISH",VLOOKUP(E26,'DB Equipment'!$A:$K,3,0),""))))) -> PDL | D26: =VLOOKUP(E26,'DB Equipment'!A:P,2,0) -> PDL 8200 | E26: EEMSFR149A | F26: =VLOOKUP(E26,'DB Equipment'!A:K,8,0) -> PDL 8200 French | G26: =IF(VLOOKUP(E26,'DB Equipment'!A:K,9,0)=0,"",VLOOKUP(E26,'DB Equipment'!A:K,9,0)) -> French | H26: =IF(VLOOKUP(E26,'DB Equipment'!A:K,10,0)=0,"",VLOOKUP(E26,'DB Equipment'!A:K,10,0)) | I26: =IF(VLOOKUP(E26,'DB Equipment'!A:K,11,0)=0,"",VLOOKUP(E26,'DB Equipment'!A:K,11,0)) | J26: =IF(IF($J$1="ITALIANO",VLOOKUP($E26,'DB Equipment'!$A:$P,16,0),IF($J$1="ESPAÑOL",VLOOKUP($E26,'DB Equipment'!$A:$P,15,0),IF($J$1="DEUTSCH",VLOOKUP($E26,'DB Equipment'!$A:$P,13,0),IF($J$1="FRANÇAIS",VLOOKUP($E26,'DB Equipment'!$A:$P,14,0),IF($J$1="ENGLISH",VLOOKUP($E26,'DB Equipment'!$A:$P,12,0),"")))))=0,"",IF($J$1="ITALIANO",VLOOKUP($E26,'DB Equipment'!$A:$P,16,0),IF($J$1="ESPAÑOL",VLOOKUP($E26,'DB Equipment'!$A:$P,15,0),IF($J$1="DEUTSCH",VLOOKUP($E26,'DB Equipment'!$A:$P,13,0),IF($J$1="FRANÇAIS",VLOOKUP($E26,'DB Equipment'!$A:$P,14,0),IF($J$1="ENGLISH",VLOOKUP($E26,'DB Equipment'!$A:$P,12,0),"")))))) -> Including latest software release + free-of-charge updates (2 minimum) for one year, French version | K26: =IF(L$1="Germany",VLOOKUP(E26,Prices!A:AA,16,0),VLOOKUP(E26,Prices!A:AA,3,0)) -> 6815 | L26: =VLOOKUP(E26,Prices!A:AA,HLOOKUP(L$1&"D",Prices!A:AA,2,0),0) -> 0.3 | M26: =IF(VLOOKUP(E26,Prices!A:AA,HLOOKUP(L$1&"2",Prices!A:AA,2,0),0)="","",VLOOKUP(E26,Prices!A:AA,HLOOKUP(L$1&"2",Prices!A:AA,2,0),0)) | N26: =IFERROR(IF(M26="",$K26*(1-L26),$K26*(1-L26)*(1-M26)),"n.a.") -> 4770.5
C27: =IF($J$1="ITALIANO",VLOOKUP(E27,'DB Equipment'!$A:$K,7,0),IF($J$1="ESPAÑOL",VLOOKUP(E27,'DB Equipment'!$A:$K,6,0),IF($J$1="DEUTSCH",VLOOKUP(E27,'DB Equipment'!$A:$K,4,0),IF($J$1="FRANÇAIS",VLOOKUP(E27,'DB Equipment'!$A:$K,5,0),IF($J$1="ENGLISH",VLOOKUP(E27,'DB Equipment'!$A:$K,3,0),""))))) -> PDL | D27: =VLOOKUP(E27,'DB Equipment'!A:P,2,0) -> PDL 8200 | E27: EEMSIT149A | F27: =VLOOKUP(E27,'DB Equipment'!A:K,8,0) -> PDL 8200 Italian | G27: =IF(VLOOKUP(E27,'DB Equipment'!A:K,9,0)=0,"",VLOOKUP(E27,'DB Equipment'!A:K,9,0)) -> Italian | H27: =IF(VLOOKUP(E27,'DB Equipment'!A:K,10,0)=0,"",VLOOKUP(E27,'DB Equipment'!A:K,10,0)) | I27: =IF(VLOOKUP(E27,'DB Equipment'!A:K,11,0)=0,"",VLOOKUP(E27,'DB Equipment'!A:K,11,0)) | J27: =IF(IF($J$1="ITALIANO",VLOOKUP($E27,'DB Equipment'!$A:$P,16,0),IF($J$1="ESPAÑOL",VLOOKUP($E27,'DB Equipment'!$A:$P,15,0),IF($J$1="DEUTSCH",VLOOKUP($E27,'DB Equipment'!$A:$P,13,0),IF($J$1="FRANÇAIS",VLOOKUP($E27,'DB Equipment'!$A:$P,14,0),IF($J$1="ENGLISH",VLOOKUP($E27,'DB Equipment'!$A:$P,12,0),"")))))=0,"",IF($J$1="ITALIANO",VLOOKUP($E27,'DB Equipment'!$A:$P,16,0),IF($J$1="ESPAÑOL",VLOOKUP($E27,'DB Equipment'!$A:$P,15,0),IF($J$1="DEUTSCH",VLOOKUP($E27,'DB Equipment'!$A:$P,13,0),IF($J$1="FRANÇAIS",VLOOKUP($E27,'DB Equipment'!$A:$P,14,0),IF($J$1="ENGLISH",VLOOKUP($E27,'DB Equipment'!$A:$P,12,0),"")))))) -> Including latest software release + free-of-charge updates (2 minimum) for one year, Italian version | K27: =IF(L$1="Germany",VLOOKUP(E27,Prices!A:AA,16,0),VLOOKUP(E27,Prices!A:AA,3,0)) -> 6815 | L27: =VLOOKUP(E27,Prices!A:AA,HLOOKUP(L$1&"D",Prices!A:AA,2,0),0) -> 0.3 | M27: =IF(VLOOKUP(E27,Prices!A:AA,HLOOKUP(L$1&"2",Prices!A:AA,2,0),0)="","",VLOOKUP(E27,Prices!A:AA,HLOOKUP(L$1&"2",Prices!A:AA,2,0),0)) | N27: =IFERROR(IF(M27="",$K27*(1-L27),$K27*(1-L27)*(1-M27)),"n.a.") -> 4770.5
C28: =IF($J$1="ITALIANO",VLOOKUP(E28,'DB Equipment'!$A:$K,7,0),IF($J$1="ESPAÑOL",VLOOKUP(E28,'DB Equipment'!$A:$K,6,0),IF($J$1="DEUTSCH",VLOOKUP(E28,'DB Equipment'!$A:$K,4,0),IF($J$1="FRANÇAIS",VLOOKUP(E28,'DB Equipment'!$A:$K,5,0),IF($J$1="ENGLISH",VLOOKUP(E28,'DB Equipment'!$A:$K,3,0),""))))) -> PDL | D28: =VLOOKUP(E28,'DB Equipment'!A:P,2,0) -> PDL 8200 | E28: EEMSPL149A | F28: =VLOOKUP(E28,'DB Equipment'!A:K,8,0) -> PDL 8200 Polish | G28: =IF(VLOOKUP(E28,'DB Equipment'!A:K,9,0)=0,"",VLOOKUP(E28,'DB Equipment'!A:K,9,0)) -> Polish | H28: =IF(VLOOKUP(E28,'DB Equipment'!A:K,10,0)=0,"",VLOOKUP(E28,'DB Equipment'!A:K,10,0)) | I28: =IF(VLOOKUP(E28,'DB Equipment'!A:K,11,0)=0,"",VLOOKUP(E28,'DB Equipment'!A:K,11,0)) | J28: =IF(IF($J$1="ITALIANO",VLOOKUP($E28,'DB Equipment'!$A:$P,16,0),IF($J$1="ESPAÑOL",VLOOKUP($E28,'DB Equipment'!$A:$P,15,0),IF($J$1="DEUTSCH",VLOOKUP($E28,'DB Equipment'!$A:$P,13,0),IF($J$1="FRANÇAIS",VLOOKUP($E28,'DB Equipment'!$A:$P,14,0),IF($J$1="ENGLISH",VLOOKUP($E28,'DB Equipment'!$A:$P,12,0),"")))))=0,"",IF($J$1="ITALIANO",VLOOKUP($E28,'DB Equipment'!$A:$P,16,0),IF($J$1="ESPAÑOL",VLOOKUP($E28,'DB Equipment'!$A:$P,15,0),IF($J$1="DEUTSCH",VLOOKUP($E28,'DB Equipment'!$A:$P,13,0),IF($J$1="FRANÇAIS",VLOOKUP($E28,'DB Equipment'!$A:$P,14,0),IF($J$1="ENGLISH",VLOOKUP($E28,'DB Equipment'!$A:$P,12,0),"")))))) -> Including latest software release + free-of-charge updates (2 minimum) for one year, Polish version | K28: =IF(L$1="Germany",VLOOKUP(E28,Prices!A:AA,16,0),VLOOKUP(E28,Prices!A:AA,3,0)) -> 6815 | L28: =VLOOKUP(E28,Prices!A:AA,HLOOKUP(L$1&"D",Prices!A:AA,2,0),0) -> 0.3 | M28: =IF(VLOOKUP(E28,Prices!A:AA,HLOOKUP(L$1&"2",Prices!A:AA,2,0),0)="","",VLOOKUP(E28,Prices!A:AA,HLOOKUP(L$1&"2",Prices!A:AA,2,0),0)) | N28: =IFERROR(IF(M28="",$K28*(1-L28),$K28*(1-L28)*(1-M28)),"n.a.") -> 4770.5
C29: =IF($J$1="ITALIANO",VLOOKUP(E29,'DB Equipment'!$A:$K,7,0),IF($J$1="ESPAÑOL",VLOOKUP(E29,'DB Equipment'!$A:$K,6,0),IF($J$1="DEUTSCH",VLOOKUP(E29,'DB Equipment'!$A:$K,4,0),IF($J$1="FRANÇAIS",VLOOKUP(E29,'DB Equipment'!$A:$K,5,0),IF($J$1="ENGLISH",VLOOKUP(E29,'DB Equipment'!$A:$K,3,0),""))))) -> PDL | D29: =VLOOKUP(E29,'DB Equipment'!A:P,2,0) -> PDL 8200 | E29: EEMSPL149A x 5 | F29: =VLOOKUP(E29,'DB Equipment'!A:K,8,0) -> PDL 8200 Polish | G29: =IF(VLOOKUP(E29,'DB Equipment'!A:K,9,0)=0,"",VLOOKUP(E29,'DB Equipment'!A:K,9,0)) -> Polish | H29: =IF(VLOOKUP(E29,'DB Equipment'!A:K,10,0)=0,"",VLOOKUP(E29,'DB Equipment'!A:K,10,0)) | I29: =IF(VLOOKUP(E29,'DB Equipment'!A:K,11,0)=0,"",VLOOKUP(E29,'DB Equipment'!A:K,11,0)) | J29: =IF(IF($J$1="ITALIANO",VLOOKUP($E29,'DB Equipment'!$A:$P,16,0),IF($J$1="ESPAÑOL",VLOOKUP($E29,'DB Equipment'!$A:$P,15,0),IF($J$1="DEUTSCH",VLOOKUP($E29,'DB Equipment'!$A:$P,13,0),IF($J$1="FRANÇAIS",VLOOKUP($E29,'DB Equipment'!$A:$P,14,0),IF($J$1="ENGLISH",VLOOKUP($E29,'DB Equipment'!$A:$P,12,0),"")))))=0,"",IF($J$1="ITALIANO",VLOOKUP($E29,'DB Equipment'!$A:$P,16,0),IF($J$1="ESPAÑOL",VLOOKUP($E29,'DB Equipment'!$A:$P,15,0),IF($J$1="DEUTSCH",VLOOKUP($E29,'DB Equipment'!$A:$P,13,0),IF($J$1="FRANÇAIS",VLOOKUP($E29,'DB Equipment'!$A:$P,14,0),IF($J$1="ENGLISH",VLOOKUP($E29,'DB Equipment'!$A:$P,12,0),"")))))) -> 5 unit order | K29: =IF(L$1="Germany",VLOOKUP(E29,Prices!A:AA,16,0),VLOOKUP(E29,Prices!A:AA,3,0)) -> 6815 | L29: =IF(VLOOKUP(E29,Prices!A:AA,HLOOKUP(L$1&"D",Prices!A:AA,2,0),0)=0,"",VLOOKUP(E29,Prices!A:AA,HLOOKUP(L$1&"D",Prices!A:AA,2,0),0)) | M29: =IF(VLOOKUP(E29,Prices!A:AA,HLOOKUP(L$1&"2",Prices!A:AA,2,0),0)="","",VLOOKUP(E29,Prices!A:AA,HLOOKUP(L$1&"2",Prices!A:AA,2,0),0)) | N29: =IFERROR(IF(M29="",$K29*(1-L29),$K29*(1-L29)*(1-M29)),"n.a.") -> n.a.
C30: =IF($J$1="ITALIANO",VLOOKUP(E30,'DB Equipment'!$A:$K,7,0),IF($J$1="ESPAÑOL",VLOOKUP(E30,'DB Equipment'!$A:$K,6,0),IF($J$1="DEUTSCH",VLOOKUP(E30,'DB Equipment'!$A:$K,4,0),IF($J$1="FRANÇAIS",VLOOKUP(E30,'DB Equipment'!$A:$K,5,0),IF($J$1="ENGLISH",VLOOKUP(E30,'DB Equipment'!$A:$K,3,0),""))))) -> PDL | D30: =VLOOKUP(E30,'DB Equipment'!A:P,2,0) -> PDL 8200 | E30: EEMSPL149A x 10 | F30: =VLOOKUP(E30,'DB Equipment'!A:K,8,0) -> PDL 8200 Polish | G30: =IF(VLOOKUP(E30,'DB Equipment'!A:K,9,0)=0,"",VLOOKUP(E30,'DB Equipment'!A:K,9,0)) -> Polish | H30: =IF(VLOOKUP(E30,'DB Equipment'!A:K,10,0)=0,"",VLOOKUP(E30,'DB Equipment'!A:K,10,0)) | I30: =IF(VLOOKUP(E30,'DB Equipment'!A:K,11,0)=0,"",VLOOKUP(E30,'DB Equipment'!A:K,11,0)) | J30: =IF(IF($J$1="ITALIANO",VLOOKUP($E30,'DB Equipment'!$A:$P,16,0),IF($J$1="ESPAÑOL",VLOOKUP($E30,'DB Equipment'!$A:$P,15,0),IF($J$1="DEUTSCH",VLOOKUP($E30,'DB Equipment'!$A:$P,13,0),IF($J$1="FRANÇAIS",VLOOKUP($E30,'DB Equipment'!$A:$P,14,0),IF($J$1="ENGLISH",VLOOKUP($E30,'DB Equipment'!$A:$P,12,0),"")))))=0,"",IF($J$1="ITALIANO",VLOOKUP($E30,'DB Equipment'!$A:$P,16,0),IF($J$1="ESPAÑOL",VLOOKUP($E30,'DB Equipment'!$A:$P,15,0),IF($J$1="DEUTSCH",VLOOKUP($E30,'DB Equipment'!$A:$P,13,0),IF($J$1="FRANÇAIS",VLOOKUP($E30,'DB Equipment'!$A:$P,14,0),IF($J$1="ENGLISH",VLOOKUP($E30,'DB Equipment'!$A:$P,12,0),"")))))) -> 10 unit order | K30: =IF(L$1="Germany",VLOOKUP(E30,Prices!A:AA,16,0),VLOOKUP(E30,Prices!A:AA,3,0)) -> 6815 | L30: =IF(VLOOKUP(E30,Prices!A:AA,HLOOKUP(L$1&"D",Prices!A:AA,2,0),0)=0,"",VLOOKUP(E30,Prices!A:AA,HLOOKUP(L$1&"D",Prices!A:AA,2,0),0)) | M30: =IF(VLOOKUP(E30,Prices!A:AA,HLOOKUP(L$1&"2",Prices!A:AA,2,0),0)="","",VLOOKUP(E30,Prices!A:AA,HLOOKUP(L$1&"2",Prices!A:AA,2,0),0)) | N30: =IFERROR(IF(M30="",$K30*(1-L30),$K30*(1-L30)*(1-M30)),"n.a.") -> n.a.
C31: =IF($J$1="ITALIANO",VLOOKUP(E31,'DB Equipment'!$A:$K,7,0),IF($J$1="ESPAÑOL",VLOOKUP(E31,'DB Equipment'!$A:$K,6,0),IF($J$1="DEUTSCH",VLOOKUP(E31,'DB Equipment'!$A:$K,4,0),IF($J$1="FRANÇAIS",VLOOKUP(E31,'DB Equipment'!$A:$K,5,0),IF($J$1="ENGLISH",VLOOKUP(E31,'DB Equipment'!$A:$K,3,0),""))))) -> PDL | D31: =VLOOKUP(E31,'DB Equipment'!A:P,2,0) -> PDL 8200 | E31: EEMSEG149A | F31: =VLOOKUP(E31,'DB Equipment'!A:K,8,0) -> PDL 8200 English | G31: =IF(VLOOKUP(E31,'DB Equipment'!A:K,9,0)=0,"",VLOOKUP(E31,'DB Equipment'!A:K,9,0)) -> English | H31: =IF(VLOOKUP(E31,'DB Equipment'!A:K,10,0)=0,"",VLOOKUP(E31,'DB Equipment'!A:K,10,0)) | I31: =IF(VLOOKUP(E31,'DB Equipment'!A:K,11,0)=0,"",VLOOKUP(E31,'DB Equipment'!A:K,11,0)) | J31: =IF(IF($J$1="ITALIANO",VLOOKUP($E31,'DB Equipment'!$A:$P,16,0),IF($J$1="ESPAÑOL",VLOOKUP($E31,'DB Equipment'!$A:$P,15,0),IF($J$1="DEUTSCH",VLOOKUP($E31,'DB Equipment'!$A:$P,13,0),IF($J$1="FRANÇAIS",VLOOKUP($E31,'DB Equipment'!$A:$P,14,0),IF($J$1="ENGLISH",VLOOKUP($E31,'DB Equipment'!$A:$P,12,0),"")))))=0,"",IF($J$1="ITALIANO",VLOOKUP($E31,'DB Equipment'!$A:$P,16,0),IF($J$1="ESPAÑOL",VLOOKUP($E31,'DB Equipment'!$A:$P,15,0),IF($J$1="DEUTSCH",VLOOKUP($E31,'DB Equipment'!$A:$P,13,0),IF($J$1="FRANÇAIS",VLOOKUP($E31,'DB Equipment'!$A:$P,14,0),IF($J$1="ENGLISH",VLOOKUP($E31,'DB Equipment'!$A:$P,12,0),"")))))) -> Including latest software release + free-of-charge updates (2 minimum) for one year, English version | K31: =IF(L$1="Germany",VLOOKUP(E31,Prices!A:AA,16,0),VLOOKUP(E31,Prices!A:AA,3,0)) -> 6815 | L31: =VLOOKUP(E31,Prices!A:AA,HLOOKUP(L$1&"D",Prices!A:AA,2,0),0) -> 0.3 | M31: =IF(VLOOKUP(E31,Prices!A:AA,HLOOKUP(L$1&"2",Prices!A:AA,2,0),0)="","",VLOOKUP(E31,Prices!A:AA,HLOOKUP(L$1&"2",Prices!A:AA,2,0),0)) | N31: =IFERROR(IF(M31="",$K31*(1-L31),$K31*(1-L31)*(1-M31)),"n.a.") -> 4770.5
B32: #VALUE! | C32: =IF($J$1="ITALIANO",VLOOKUP(E32,'DB Equipment'!$A:$K,7,0),IF($J$1="ESPAÑOL",VLOOKUP(E32,'DB Equipment'!$A:$K,6,0),IF($J$1="DEUTSCH",VLOOKUP(E32,'DB Equipment'!$A:$K,4,0),IF($J$1="FRANÇAIS",VLOOKUP(E32,'DB Equipment'!$A:$K,5,0),IF($J$1="ENGLISH",VLOOKUP(E32,'DB Equipment'!$A:$K,3,0),""))))) -> TPMX | D32: =VLOOKUP(E32,'DB Equipment'!A:P,2,0) -> TPMX tool | E32: EEPVEU118A | F32: =VLOOKUP(E32,'DB Equipment'!A:K,8,0) -> TPMX tool | G32: =IF(VLOOKUP(E32,'DB Equipment'!A:K,9,0)=0,"",VLOOKUP(E32,'DB Equipment'!A:K,9,0)) | H32: =IF(VLOOKUP(E32,'DB Equipment'!A:K,10,0)=0,"",VLOOKUP(E32,'DB Equipment'!A:K,10,0)) | I32: =IF(VLOOKUP(E32,'DB Equipment'!A:K,11,0)=0,"",VLOOKUP(E32,'DB Equipment'!A:K,11,0)) | J32: =IF(IF($J$1="ITALIANO",VLOOKUP($E32,'DB Equipment'!$A:$P,16,0),IF($J$1="ESPAÑOL",VLOOKUP($E32,'DB Equipment'!$A:$P,15,0),IF($J$1="DEUTSCH",VLOOKUP($E32,'DB Equipment'!$A:$P,13,0),IF($J$1="FRANÇAIS",VLOOKUP($E32,'DB Equipment'!$A:$P,14,0),IF($J$1="ENGLISH",VLOOKUP($E32,'DB Equipment'!$A:$P,12,0),"")))))=0,"",IF($J$1="ITALIANO",VLOOKUP($E32,'DB Equipment'!$A:$P,16,0),IF($J$1="ESPAÑOL",VLOOKUP($E32,'DB Equipment'!$A:$P,15,0),IF($J$1="DEUTSCH",VLOOKUP($E32,'DB Equipment'!$A:$P,13,0),IF($J$1="FRANÇAIS",VLOOKUP($E32,'DB Equipment'!$A:$P,14,0),IF($J$1="ENGLISH",VLOOKUP($E32,'DB Equipment'!$A:$P,12,0),"")))))) -> Languages: English, Italian, Dutch, German, French, Polish, Spanish | K32: =IF(L$1="Germany",VLOOKUP(E32,Prices!A:AA,16,0),VLOOKUP(E32,Prices!A:AA,3,0)) -> 1200 | L32: =VLOOKUP(E32,Prices!A:AA,HLOOKUP(L$1&"D",Prices!A:AA,2,0),0) -> 0.3 | M32: =IF(VLOOKUP(E32,Prices!A:AA,HLOOKUP(L$1&"2",Prices!A:AA,2,0),0)="","",VLOOKUP(E32,Prices!A:AA,HLOOKUP(L$1&"2",Prices!A:AA,2,0),0)) | N32: =IFERROR(IF(M32="",$K32*(1-L32),$K32*(1-L32)*(1-M32)),"n.a.") -> 840
B33: #VALUE! | C33: =IF($J$1="ITALIANO",VLOOKUP(E33,'DB Equipment'!$A:$K,7,0),IF($J$1="ESPAÑOL",VLOOKUP(E33,'DB Equipment'!$A:$K,6,0),IF($J$1="DEUTSCH",VLOOKUP(E33,'DB Equipment'!$A:$K,4,0),IF($J$1="FRANÇAIS",VLOOKUP(E33,'DB Equipment'!$A:$K,5,0),IF($J$1="ENGLISH",VLOOKUP(E33,'DB Equipment'!$A:$K,3,0),""))))) -> A/C | D33: =VLOOKUP(E33,'DB Equipment'!A:P,2,0) -> Breeze IV | E33: DECKY2N20020S000 | F33: =VLOOKUP(E33,'DB Equipment'!A:K,8,0) -> BREEZE IV with printer | G33: =IF(VLOOKUP(E33,'DB Equipment'!A:K,9,0)=0,"",VLOOKUP(E33,'DB Equipment'!A:K,9,0)) | H33: =IF(VLOOKUP(E33,'DB Equipment'!A:K,10,0)=0,"",VLOOKUP(E33,'DB Equipment'!A:K,10,0)) -> 220-240V 50/60 Hz | I33: =IF(VLOOKUP(E33,'DB Equipment'!A:K,11,0)=0,"",VLOOKUP(E33,'DB Equipment'!A:K,11,0)) | J33: =IF(IF($J$1="ITALIANO",VLOOKUP($E33,'DB Equipment'!$A:$P,16,0),IF($J$1="ESPAÑOL",VLOOKUP($E33,'DB Equipment'!$A:$P,15,0),IF($J$1="DEUTSCH",VLOOKUP($E33,'DB Equipment'!$A:$P,13,0),IF($J$1="FRANÇAIS",VLOOKUP($E33,'DB Equipment'!$A:$P,14,0),IF($J$1="ENGLISH",VLOOKUP($E33,'DB Equipment'!$A:$P,12,0),"")))))=0,"",IF($J$1="ITALIANO",VLOOKUP($E33,'DB Equipment'!$A:$P,16,0),IF($J$1="ESPAÑOL",VLOOKUP($E33,'DB Equipment'!$A:$P,15,0),IF($J$1="DEUTSCH",VLOOKUP($E33,'DB Equipment'!$A:$P,13,0),IF($J$1="FRANÇAIS",VLOOKUP($E33,'DB Equipment'!$A:$P,14,0),IF($J$1="ENGLISH",VLOOKUP($E33,'DB Equipment'!$A:$P,12,0),"")))))) -> Fully automatic A/C service station for recovery, recycling and recharging of different types of refrigerants. The innovative and exclusive solution allows to set the R134a or the HFO1234yf gas directly during activation in the workshop. 4,3” touch screen display. Thermal printer included. With its modular features, the machine can be configured to meet the most specific needs. The upgrade with the Gas Analyser detects the different components of the refrigerant, and the result provides information about their percentages. C.A.R. method (Compressor Assisted Recharge) With the advanced technology based on an innovative solenoid valve system, BREEZE IV consumes 20% less energy than the previous models. Futuristic design. Less than 30” to open the revolving control panel. BREEZE IV grants excellent maneuverability as a result of the considerable axial distance between the two wheels. User-friendly | K33: =IF(L$1="Germany",VLOOKUP(E33,Prices!A:AA,16,0),VLOOKUP(E33,Prices!A:AA,3,0)) -> 4575 | L33: =VLOOKUP(E33,Prices!A:AA,HLOOKUP(L$1&"D",Prices!A:AA,2,0),0) -> 0.6 | M33: =IF(VLOOKUP(E33,Prices!A:AA,HLOOKUP(L$1&"2",Prices!A:AA,2,0),0)="","",VLOOKUP(E33,Prices!A:AA,HLOOKUP(L$1&"2",Prices!A:AA,2,0),0)) | N33: =IFERROR(IF(M33="",$K33*(1-L33),$K33*(1-L33)*(1-M33)),"n.a.") -> 1830
C34: =IF($J$1="ITALIANO",VLOOKUP(E34,'DB Equipment'!$A:$K,7,0),IF($J$1="ESPAÑOL",VLOOKUP(E34,'DB Equipment'!$A:$K,6,0),IF($J$1="DEUTSCH",VLOOKUP(E34,'DB Equipment'!$A:$K,4,0),IF($J$1="FRANÇAIS",VLOOKUP(E34,'DB Equipment'!$A:$K,5,0),IF($J$1="ENGLISH",VLOOKUP(E34,'DB Equipment'!$A:$K,3,0),""))))) -> A/C | D34: =VLOOKUP(E34,'DB Equipment'!A:P,2,0) -> Breeze IV | E34: DECKY2NR00000000 | F34: =VLOOKUP(E34,'DB Equipment'!A:K,8,0) -> KIT R134A for BREEZE IV | G34: =IF(VLOOKUP(E34,'DB Equipment'!A:K,9,0)=0,"",VLOOKUP(E34,'DB Equipment'!A:K,9,0)) | H34: =IF(VLOOKUP(E34,'DB Equipment'!A:K,10,0)=0,"",VLOOKUP(E34,'DB Equipment'!A:K,10,0)) | I34: =IF(VLOOKUP(E34,'DB Equipment'!A:K,11,0)=0,"",VLOOKUP(E34,'DB Equipment'!A:K,11,0)) | J34: =IF(IF($J$1="ITALIANO",VLOOKUP($E34,'DB Equipment'!$A:$P,16,0),IF($J$1="ESPAÑOL",VLOOKUP($E34,'DB Equipment'!$A:$P,15,0),IF($J$1="DEUTSCH",VLOOKUP($E34,'DB Equipment'!$A:$P,13,0),IF($J$1="FRANÇAIS",VLOOKUP($E34,'DB Equipment'!$A:$P,14,0),IF($J$1="ENGLISH",VLOOKUP($E34,'DB Equipment'!$A:$P,12,0),"")))))=0,"",IF($J$1="ITALIANO",VLOOKUP($E34,'DB Equipment'!$A:$P,16,0),IF($J$1="ESPAÑOL",VLOOKUP($E34,'DB Equipment'!$A:$P,15,0),IF($J$1="DEUTSCH",VLOOKUP($E34,'DB Equipment'!$A:$P,13,0),IF($J$1="FRANÇAIS",VLOOKUP($E34,'DB Equipment'!$A:$P,14,0),IF($J$1="ENGLISH",VLOOKUP($E34,'DB Equipment'!$A:$P,12,0),"")))))) -> Refrigerant Kit NEXT R134a | K34: =IF(L$1="Germany",VLOOKUP(E34,Prices!A:AA,16,0),VLOOKUP(E34,Prices!A:AA,3,0)) -> 271 | L34: =VLOOKUP(E34,Prices!A:AA,HLOOKUP(L$1&"D",Prices!A:AA,2,0),0) -> 0.6 | M34: =IF(VLOOKUP(E34,Prices!A:AA,HLOOKUP(L$1&"2",Prices!A:AA,2,0),0)="","",VLOOKUP(E34,Prices!A:AA,HLOOKUP(L$1&"2",Prices!A:AA,2,0),0)) | N34: =IFERROR(IF(M34="",$K34*(1-L34),$K34*(1-L34)*(1-M34)),"n.a.") -> 108.4
C35: =IF($J$1="ITALIANO",VLOOKUP(E35,'DB Equipment'!$A:$K,7,0),IF($J$1="ESPAÑOL",VLOOKUP(E35,'DB Equipment'!$A:$K,6,0),IF($J$1="DEUTSCH",VLOOKUP(E35,'DB Equipment'!$A:$K,4,0),IF($J$1="FRANÇAIS",VLOOKUP(E35,'DB Equipment'!$A:$K,5,0),IF($J$1="ENGLISH",VLOOKUP(E35,'DB Equipment'!$A:$K,3,0),""))))) -> A/C | D35: =VLOOKUP(E35,'DB Equipment'!A:P,2,0) -> Breeze IV | E35: DECKY2NH00000000 | F35: =VLOOKUP(E35,'DB Equipment'!A:K,8,0) -> KIT HFO for BREEZE IV | G35: =IF(VLOOKUP(E35,'DB Equipment'!A:K,9,0)=0,"",VLOOKUP(E35,'DB Equipment'!A:K,9,0)) | H35: =IF(VLOOKUP(E35,'DB Equipment'!A:K,10,0)=0,"",VLOOKUP(E35,'DB Equipment'!A:K,10,0)) | I35: =IF(VLOOKUP(E35,'DB Equipment'!A:K,11,0)=0,"",VLOOKUP(E35,'DB Equipment'!A:K,11,0)) | J35: =IF(IF($J$1="ITALIANO",VLOOKUP($E35,'DB Equipment'!$A:$P,16,0),IF($J$1="ESPAÑOL",VLOOKUP($E35,'DB Equipment'!$A:$P,15,0),IF($J$1="DEUTSCH",VLOOKUP($E35,'DB Equipment'!$A:$P,13,0),IF($J$1="FRANÇAIS",VLOOKUP($E35,'DB Equipment'!$A:$P,14,0),IF($J$1="ENGLISH",VLOOKUP($E35,'DB Equipment'!$A:$P,12,0),"")))))=0,"",IF($J$1="ITALIANO",VLOOKUP($E35,'DB Equipment'!$A:$P,16,0),IF($J$1="ESPAÑOL",VLOOKUP($E35,'DB Equipment'!$A:$P,15,0),IF($J$1="DEUTSCH",VLOOKUP($E35,'DB Equipment'!$A:$P,13,0),IF($J$1="FRANÇAIS",VLOOKUP($E35,'DB Equipment'!$A:$P,14,0),IF($J$1="ENGLISH",VLOOKUP($E35,'DB Equipment'!$A:$P,12,0),"")))))) -> Refrigerant Kit NEXT HFO1234yf | K35: =IF(L$1="Germany",VLOOKUP(E35,Prices!A:AA,16,0),VLOOKUP(E35,Prices!A:AA,3,0)) -> 834 | L35: =VLOOKUP(E35,Prices!A:AA,HLOOKUP(L$1&"D",Prices!A:AA,2,0),0) -> 0.65 | M35: =IF(VLOOKUP(E35,Prices!A:AA,HLOOKUP(L$1&"2",Prices!A:AA,2,0),0)="","",VLOOKUP(E35,Prices!A:AA,HLOOKUP(L$1&"2",Prices!A:AA,2,0),0)) | N35: =IFERROR(IF(M35="",$K35*(1-L35),$K35*(1-L35)*(1-M35)),"n.a.") -> 291.9
B36: #VALUE! | C36: =IF($J$1="ITALIANO",VLOOKUP(E36,'DB Equipment'!$A:$K,7,0),IF($J$1="ESPAÑOL",VLOOKUP(E36,'DB Equipment'!$A:$K,6,0),IF($J$1="DEUTSCH",VLOOKUP(E36,'DB Equipment'!$A:$K,4,0),IF($J$1="FRANÇAIS",VLOOKUP(E36,'DB Equipment'!$A:$K,5,0),IF($J$1="ENGLISH",VLOOKUP(E36,'DB Equipment'!$A:$K,3,0),""))))) -> A/C | D36: =VLOOKUP(E36,'DB Equipment'!A:P,2,0) -> Blizzard Qtech IV | E36: DECKY2F20020S000 | F36: =VLOOKUP(E36,'DB Equipment'!A:K,8,0) -> BLIZZARD QTECH IV | G36: =IF(VLOOKUP(E36,'DB Equipment'!A:K,9,0)=0,"",VLOOKUP(E36,'DB Equipment'!A:K,9,0)) | H36: =IF(VLOOKUP(E36,'DB Equipment'!A:K,10,0)=0,"",VLOOKUP(E36,'DB Equipment'!A:K,10,0)) -> 220-240V 50/60 Hz | I36: =IF(VLOOKUP(E36,'DB Equipment'!A:K,11,0)=0,"",VLOOKUP(E36,'DB Equipment'!A:K,11,0)) | J36: =IF(IF($J$1="ITALIANO",VLOOKUP($E36,'DB Equipment'!$A:$P,16,0),IF($J$1="ESPAÑOL",VLOOKUP($E36,'DB Equipment'!$A:$P,15,0),IF($J$1="DEUTSCH",VLOOKUP($E36,'DB Equipment'!$A:$P,13,0),IF($J$1="FRANÇAIS",VLOOKUP($E36,'DB Equipment'!$A:$P,14,0),IF($J$1="ENGLISH",VLOOKUP($E36,'DB Equipment'!$A:$P,12,0),"")))))=0,"",IF($J$1="ITALIANO",VLOOKUP($E36,'DB Equipment'!$A:$P,16,0),IF($J$1="ESPAÑOL",VLOOKUP($E36,'DB Equipment'!$A:$P,15,0),IF($J$1="DEUTSCH",VLOOKUP($E36,'DB Equipment'!$A:$P,13,0),IF($J$1="FRANÇAIS",VLOOKUP($E36,'DB Equipment'!$A:$P,14,0),IF($J$1="ENGLISH",VLOOKUP($E36,'DB Equipment'!$A:$P,12,0),"")))))) -> Fully automatic A/C service station for recovery, recycling and recharging of different types of refrigerants. Menu navigation is intuitive, professional, designed for an easy and rapid work with the machine. 7’’ color touchscreen. WI-FI connectivity. Hybrid and Nitrogen leak detection. The unit can handle the hermetic oil and dye cartridges, as well as the hermetic and refillable containers. The result is easy serviceability: less than 30” to open the revolving control panel and less than 2 minutes to remove both plastic covers and access all the internal components. QTECH IV grants excellent maneuverability as a result of the considerable axial distance between the two wheels. User-friendly features: pressure gauges and touch screen are perfectly inclined for excellent ergonomics. | K36: =IF(L$1="Germany",VLOOKUP(E36,Prices!A:AA,16,0),VLOOKUP(E36,Prices!A:AA,3,0)) -> 7050 | L36: =VLOOKUP(E36,Prices!A:AA,HLOOKUP(L$1&"D",Prices!A:AA,2,0),0) -> 0.65 | M36: =IF(VLOOKUP(E36,Prices!A:AA,HLOOKUP(L$1&"2",Prices!A:AA,2,0),0)="","",VLOOKUP(E36,Prices!A:AA,HLOOKUP(L$1&"2",Prices!A:AA,2,0),0)) | N36: =IFERROR(IF(M36="",$K36*(1-L36),$K36*(1-L36)*(1-M36)),"n.a.") -> 2467.5
C37: =IF($J$1="ITALIANO",VLOOKUP(E37,'DB Equipment'!$A:$K,7,0),IF($J$1="ESPAÑOL",VLOOKUP(E37,'DB Equipment'!$A:$K,6,0),IF($J$1="DEUTSCH",VLOOKUP(E37,'DB Equipment'!$A:$K,4,0),IF($J$1="FRANÇAIS",VLOOKUP(E37,'DB Equipment'!$A:$K,5,0),IF($J$1="ENGLISH",VLOOKUP(E37,'DB Equipment'!$A:$K,3,0),""))))) -> A/C | D37: =VLOOKUP(E37,'DB Equipment'!A:P,2,0) -> Blizzard Qtech IV | E37: DECKY2FR00000000 | F37: =VLOOKUP(E37,'DB Equipment'!A:K,8,0) -> KIT R134A for QTECH IV | G37: =IF(VLOOKUP(E37,'DB Equipment'!A:K,9,0)=0,"",VLOOKUP(E37,'DB Equipment'!A:K,9,0)) | H37: =IF(VLOOKUP(E37,'DB Equipment'!A:K,10,0)=0,"",VLOOKUP(E37,'DB Equipment'!A:K,10,0)) | I37: =IF(VLOOKUP(E37,'DB Equipment'!A:K,11,0)=0,"",VLOOKUP(E37,'DB Equipment'!A:K,11,0)) | J37: =IF(IF($J$1="ITALIANO",VLOOKUP($E37,'DB Equipment'!$A:$P,16,0),IF($J$1="ESPAÑOL",VLOOKUP($E37,'DB Equipment'!$A:$P,15,0),IF($J$1="DEUTSCH",VLOOKUP($E37,'DB Equipment'!$A:$P,13,0),IF($J$1="FRANÇAIS",VLOOKUP($E37,'DB Equipment'!$A:$P,14,0),IF($J$1="ENGLISH",VLOOKUP($E37,'DB Equipment'!$A:$P,12,0),"")))))=0,"",IF($J$1="ITALIANO",VLOOKUP($E37,'DB Equipment'!$A:$P,16,0),IF($J$1="ESPAÑOL",VLOOKUP($E37,'DB Equipment'!$A:$P,15,0),IF($J$1="DEUTSCH",VLOOKUP($E37,'DB Equipment'!$A:$P,13,0),IF($J$1="FRANÇAIS",VLOOKUP($E37,'DB Equipment'!$A:$P,14,0),IF($J$1="ENGLISH",VLOOKUP($E37,'DB Equipment'!$A:$P,12,0),"")))))) -> Refrigerant Kit FLAG R134a | K37: =IF(L$1="Germany",VLOOKUP(E37,Prices!A:AA,16,0),VLOOKUP(E37,Prices!A:AA,3,0)) -> 271 | L37: =VLOOKUP(E37,Prices!A:AA,HLOOKUP(L$1&"D",Prices!A:AA,2,0),0) -> 0.65 | M37: =IF(VLOOKUP(E37,Prices!A:AA,HLOOKUP(L$1&"2",Prices!A:AA,2,0),0)="","",VLOOKUP(E37,Prices!A:AA,HLOOKUP(L$1&"2",Prices!A:AA,2,0),0)) | N37: =IFERROR(IF(M37="",$K37*(1-L37),$K37*(1-L37)*(1-M37)),"n.a.") -> 94.85
C38: =IF($J$1="ITALIANO",VLOOKUP(E38,'DB Equipment'!$A:$K,7,0),IF($J$1="ESPAÑOL",VLOOKUP(E38,'DB Equipment'!$A:$K,6,0),IF($J$1="DEUTSCH",VLOOKUP(E38,'DB Equipment'!$A:$K,4,0),IF($J$1="FRANÇAIS",VLOOKUP(E38,'DB Equipment'!$A:$K,5,0),IF($J$1="ENGLISH",VLOOKUP(E38,'DB Equipment'!$A:$K,3,0),""))))) -> A/C | D38: =VLOOKUP(E38,'DB Equipment'!A:P,2,0) -> Blizzard Qtech IV | E38: DECKY2FH00000000 | F38: =VLOOKUP(E38,'DB Equipment'!A:K,8,0) -> KIT HFO for QTECH IV | G38: =IF(VLOOKUP(E38,'DB Equipment'!A:K,9,0)=0,"",VLOOKUP(E38,'DB Equipment'!A:K,9,0)) | H38: =IF(VLOOKUP(E38,'DB Equipment'!A:K,10,0)=0,"",VLOOKUP(E38,'DB Equipment'!A:K,10,0)) | I38: =IF(VLOOKUP(E38,'DB Equipment'!A:K,11,0)=0,"",VLOOKUP(E38,'DB Equipment'!A:K,11,0)) | J38: =IF(IF($J$1="ITALIANO",VLOOKUP($E38,'DB Equipment'!$A:$P,16,0),IF($J$1="ESPAÑOL",VLOOKUP($E38,'DB Equipment'!$A:$P,15,0),IF($J$1="DEUTSCH",VLOOKUP($E38,'DB Equipment'!$A:$P,13,0),IF($J$1="FRANÇAIS",VLOOKUP($E38,'DB Equipment'!$A:$P,14,0),IF($J$1="ENGLISH",VLOOKUP($E38,'DB Equipment'!$A:$P,12,0),"")))))=0,"",IF($J$1="ITALIANO",VLOOKUP($E38,'DB Equipment'!$A:$P,16,0),IF($J$1="ESPAÑOL",VLOOKUP($E38,'DB Equipment'!$A:$P,15,0),IF($J$1="DEUTSCH",VLOOKUP($E38,'DB Equipment'!$A:$P,13,0),IF($J$1="FRANÇAIS",VLOOKUP($E38,'DB Equipment'!$A:$P,14,0),IF($J$1="ENGLISH",VLOOKUP($E38,'DB Equipment'!$A:$P,12,0),"")))))) -> Refrigerant Kit FLAG HFO1234yf | K38: =IF(L$1="Germany",VLOOKUP(E38,Prices!A:AA,16,0),VLOOKUP(E38,Prices!A:AA,3,0)) -> 834 | L38: =VLOOKUP(E38,Prices!A:AA,HLOOKUP(L$1&"D",Prices!A:AA,2,0),0) -> 0.65 | M38: =IF(VLOOKUP(E38,Prices!A:AA,HLOOKUP(L$1&"2",Prices!A:AA,2,0),0)="","",VLOOKUP(E38,Prices!A:AA,HLOOKUP(L$1&"2",Prices!A:AA,2,0),0)) | N38: =IFERROR(IF(M38="",$K38*(1-L38),$K38*(1-L38)*(1-M38)),"n.a.") -> 291.9
B39: #VALUE! | C39: =IF($J$1="ITALIANO",VLOOKUP(E39,'DB Equipment'!$A:$K,7,0),IF($J$1="ESPAÑOL",VLOOKUP(E39,'DB Equipment'!$A:$K,6,0),IF($J$1="DEUTSCH",VLOOKUP(E39,'DB Equipment'!$A:$K,4,0),IF($J$1="FRANÇAIS",VLOOKUP(E39,'DB Equipment'!$A:$K,5,0),IF($J$1="ENGLISH",VLOOKUP(E39,'DB Equipment'!$A:$K,3,0),""))))) -> A/C | D39: =VLOOKUP(E39,'DB Equipment'!A:P,2,0) -> Koolkare Dual Gas 12 | E39: DECKK6T5A090S00B | F39: =VLOOKUP(E39,'DB Equipment'!A:K,8,0) -> KOOLKARE DUAL GAS 12 | G39: =IF(VLOOKUP(E39,'DB Equipment'!A:K,9,0)=0,"",VLOOKUP(E39,'DB Equipment'!A:K,9,0)) | H39: =IF(VLOOKUP(E39,'DB Equipment'!A:K,10,0)=0,"",VLOOKUP(E39,'DB Equipment'!A:K,10,0)) -> 220-240V 50/60 Hz | I39: =IF(VLOOKUP(E39,'DB Equipment'!A:K,11,0)=0,"",VLOOKUP(E39,'DB Equipment'!A:K,11,0)) | J39: =IF(IF($J$1="ITALIANO",VLOOKUP($E39,'DB Equipment'!$A:$P,16,0),IF($J$1="ESPAÑOL",VLOOKUP($E39,'DB Equipment'!$A:$P,15,0),IF($J$1="DEUTSCH",VLOOKUP($E39,'DB Equipment'!$A:$P,13,0),IF($J$1="FRANÇAIS",VLOOKUP($E39,'DB Equipment'!$A:$P,14,0),IF($J$1="ENGLISH",VLOOKUP($E39,'DB Equipment'!$A:$P,12,0),"")))))=0,"",IF($J$1="ITALIANO",VLOOKUP($E39,'DB Equipment'!$A:$P,16,0),IF($J$1="ESPAÑOL",VLOOKUP($E39,'DB Equipment'!$A:$P,15,0),IF($J$1="DEUTSCH",VLOOKUP($E39,'DB Equipment'!$A:$P,13,0),IF($J$1="FRANÇAIS",VLOOKUP($E39,'DB Equipment'!$A:$P,14,0),IF($J$1="ENGLISH",VLOOKUP($E39,'DB Equipment'!$A:$P,12,0),"")))))) -> Fully automatic air conditioning recycling unit for R134a and HFO12234yf. Separate tanks, compressors, gauges, hoses, couplers, oil and dye bottles for the two gases. Easy-to-read 7" display. Fully automatic or manual recycling procedure. Hermetic oil and dye bottle systems. Advanced database, 2x12 kg tank, prepared for flushing function (software). + Nitrogen or forming gas leak check enabled software. + Oil function for hybrid vehicles + Refrigerant identifier ready | K39: =IF(L$1="Germany",VLOOKUP(E39,Prices!A:AA,16,0),VLOOKUP(E39,Prices!A:AA,3,0)) -> 10030 | L39: =VLOOKUP(E39,Prices!A:AA,HLOOKUP(L$1&"D",Prices!A:AA,2,0),0) -> 0.6 | M39: =IF(VLOOKUP(E39,Prices!A:AA,HLOOKUP(L$1&"2",Prices!A:AA,2,0),0)="","",VLOOKUP(E39,Prices!A:AA,HLOOKUP(L$1&"2",Prices!A:AA,2,0),0)) | N39: =IFERROR(IF(M39="",$K39*(1-L39),$K39*(1-L39)*(1-M39)),"n.a.") -> 4012
B40: #VALUE! | C40: =IF($J$1="ITALIANO",VLOOKUP(E40,'DB Equipment'!$A:$K,7,0),IF($J$1="ESPAÑOL",VLOOKUP(E40,'DB Equipment'!$A:$K,6,0),IF($J$1="DEUTSCH",VLOOKUP(E40,'DB Equipment'!$A:$K,4,0),IF($J$1="FRANÇAIS",VLOOKUP(E40,'DB Equipment'!$A:$K,5,0),IF($J$1="ENGLISH",VLOOKUP(E40,'DB Equipment'!$A:$K,3,0),""))))) -> A/C | D40: =VLOOKUP(E40,'DB Equipment'!A:P,2,0) -> KoolKare HD-S | E40: DECKXK456A170S51 | F40: =VLOOKUP(E40,'DB Equipment'!A:K,8,0) -> KoolKare HD-S | G40: =IF(VLOOKUP(E40,'DB Equipment'!A:K,9,0)=0,"",VLOOKUP(E40,'DB Equipment'!A:K,9,0)) | H40: =IF(VLOOKUP(E40,'DB Equipment'!A:K,10,0)=0,"",VLOOKUP(E40,'DB Equipment'!A:K,10,0)) -> 220-240V 50/60 Hz | I40: =IF(VLOOKUP(E40,'DB Equipment'!A:K,11,0)=0,"",VLOOKUP(E40,'DB Equipment'!A:K,11,0)) | J40: =IF(IF($J$1="ITALIANO",VLOOKUP($E40,'DB Equipment'!$A:$P,16,0),IF($J$1="ESPAÑOL",VLOOKUP($E40,'DB Equipment'!$A:$P,15,0),IF($J$1="DEUTSCH",VLOOKUP($E40,'DB Equipment'!$A:$P,13,0),IF($J$1="FRANÇAIS",VLOOKUP($E40,'DB Equipment'!$A:$P,14,0),IF($J$1="ENGLISH",VLOOKUP($E40,'DB Equipment'!$A:$P,12,0),"")))))=0,"",IF($J$1="ITALIANO",VLOOKUP($E40,'DB Equipment'!$A:$P,16,0),IF($J$1="ESPAÑOL",VLOOKUP($E40,'DB Equipment'!$A:$P,15,0),IF($J$1="DEUTSCH",VLOOKUP($E40,'DB Equipment'!$A:$P,13,0),IF($J$1="FRANÇAIS",VLOOKUP($E40,'DB Equipment'!$A:$P,14,0),IF($J$1="ENGLISH",VLOOKUP($E40,'DB Equipment'!$A:$P,12,0),"")))))) -> Ideally suited for large AIRCO systems. Robust design with easy mobility around the workshop, easy-to-use controls and displays, fully automatic or manual recycling procedure, large 40 kg tank, gear pump for quick charging of bigger systems, database, automatic dye injection. | K40: =IF(L$1="Germany",VLOOKUP(E40,Prices!A:AA,16,0),VLOOKUP(E40,Prices!A:AA,3,0)) -> 8335 | L40: =VLOOKUP(E40,Prices!A:AA,HLOOKUP(L$1&"D",Prices!A:AA,2,0),0) -> 0.6 | M40: =IF(VLOOKUP(E40,Prices!A:AA,HLOOKUP(L$1&"2",Prices!A:AA,2,0),0)="","",VLOOKUP(E40,Prices!A:AA,HLOOKUP(L$1&"2",Prices!A:AA,2,0),0)) | N40: =IFERROR(IF(M40="",$K40*(1-L40),$K40*(1-L40)*(1-M40)),"n.a.") -> 3334
B41: #VALUE! | C41: =IF($J$1="ITALIANO",VLOOKUP(E41,'DB Equipment'!$A:$K,7,0),IF($J$1="ESPAÑOL",VLOOKUP(E41,'DB Equipment'!$A:$K,6,0),IF($J$1="DEUTSCH",VLOOKUP(E41,'DB Equipment'!$A:$K,4,0),IF($J$1="FRANÇAIS",VLOOKUP(E41,'DB Equipment'!$A:$K,5,0),IF($J$1="ENGLISH",VLOOKUP(E41,'DB Equipment'!$A:$K,3,0),""))))) -> A/C | D41: =VLOOKUP(E41,'DB Equipment'!A:P,2,0) -> ECO2KARE | E41: DECKY1R74420S000 | F41: =VLOOKUP(E41,'DB Equipment'!A:K,8,0) -> ECO2KARE | G41: =IF(VLOOKUP(E41,'DB Equipment'!A:K,9,0)=0,"",VLOOKUP(E41,'DB Equipment'!A:K,9,0)) | H41: =IF(VLOOKUP(E41,'DB Equipment'!A:K,10,0)=0,"",VLOOKUP(E41,'DB Equipment'!A:K,10,0)) -> 220-240V 50/60 Hz | I41: =IF(VLOOKUP(E41,'DB Equipment'!A:K,11,0)=0,"",VLOOKUP(E41,'DB Equipment'!A:K,11,0)) | J41: =IF(IF($J$1="ITALIANO",VLOOKUP($E41,'DB Equipment'!$A:$P,16,0),IF($J$1="ESPAÑOL",VLOOKUP($E41,'DB Equipment'!$A:$P,15,0),IF($J$1="DEUTSCH",VLOOKUP($E41,'DB Equipment'!$A:$P,13,0),IF($J$1="FRANÇAIS",VLOOKUP($E41,'DB Equipment'!$A:$P,14,0),IF($J$1="ENGLISH",VLOOKUP($E41,'DB Equipment'!$A:$P,12,0),"")))))=0,"",IF($J$1="ITALIANO",VLOOKUP($E41,'DB Equipment'!$A:$P,16,0),IF($J$1="ESPAÑOL",VLOOKUP($E41,'DB Equipment'!$A:$P,15,0),IF($J$1="DEUTSCH",VLOOKUP($E41,'DB Equipment'!$A:$P,13,0),IF($J$1="FRANÇAIS",VLOOKUP($E41,'DB Equipment'!$A:$P,14,0),IF($J$1="ENGLISH",VLOOKUP($E41,'DB Equipment'!$A:$P,12,0),"")))))) -> Fully automatic air conditioning service unit for emptying, servicing and filling R744 air conditioning systems | K41: =IF(L$1="Germany",VLOOKUP(E41,Prices!A:AA,16,0),VLOOKUP(E41,Prices!A:AA,3,0)) -> 8495 | L41: =VLOOKUP(E41,Prices!A:AA,HLOOKUP(L$1&"D",Prices!A:AA,2,0),0) -> 0.5051 | M41: =IF(VLOOKUP(E41,Prices!A:AA,HLOOKUP(L$1&"2",Prices!A:AA,2,0),0)="","",VLOOKUP(E41,Prices!A:AA,HLOOKUP(L$1&"2",Prices!A:AA,2,0),0)) | N41: =IFERROR(IF(M41="",$K41*(1-L41),$K41*(1-L41)*(1-M41)),"n.a.") -> 4204.1755
B42: #VALUE! | C42: =IF($J$1="ITALIANO",VLOOKUP(E42,'DB Equipment'!$A:$K,7,0),IF($J$1="ESPAÑOL",VLOOKUP(E42,'DB Equipment'!$A:$K,6,0),IF($J$1="DEUTSCH",VLOOKUP(E42,'DB Equipment'!$A:$K,4,0),IF($J$1="FRANÇAIS",VLOOKUP(E42,'DB Equipment'!$A:$K,5,0),IF($J$1="ENGLISH",VLOOKUP(E42,'DB Equipment'!$A:$K,3,0),""))))) -> ATF | D42: =VLOOKUP(E42,'DB Equipment'!A:P,2,0) -> ATF Gearkare | E42: DECKY1ATF020S000 | F42: =VLOOKUP(E42,'DB Equipment'!A:K,8,0) -> ATF Gearkare | G42: =IF(VLOOKUP(E42,'DB Equipment'!A:K,9,0)=0,"",VLOOKUP(E42,'DB Equipment'!A:K,9,0)) | H42: =IF(VLOOKUP(E42,'DB Equipment'!A:K,10,0)=0,"",VLOOKUP(E42,'DB Equipment'!A:K,10,0)) -> 220-240V 50/60 Hz | I42: =IF(VLOOKUP(E42,'DB Equipment'!A:K,11,0)=0,"",VLOOKUP(E42,'DB Equipment'!A:K,11,0)) | J42: =IF(IF($J$1="ITALIANO",VLOOKUP($E42,'DB Equipment'!$A:$P,16,0),IF($J$1="ESPAÑOL",VLOOKUP($E42,'DB Equipment'!$A:$P,15,0),IF($J$1="DEUTSCH",VLOOKUP($E42,'DB Equipment'!$A:$P,13,0),IF($J$1="FRANÇAIS",VLOOKUP($E42,'DB Equipment'!$A:$P,14,0),IF($J$1="ENGLISH",VLOOKUP($E42,'DB Equipment'!$A:$P,12,0),"")))))=0,"",IF($J$1="ITALIANO",VLOOKUP($E42,'DB Equipment'!$A:$P,16,0),IF($J$1="ESPAÑOL",VLOOKUP($E42,'DB Equipment'!$A:$P,15,0),IF($J$1="DEUTSCH",VLOOKUP($E42,'DB Equipment'!$A:$P,13,0),IF($J$1="FRANÇAIS",VLOOKUP($E42,'DB Equipment'!$A:$P,14,0),IF($J$1="ENGLISH",VLOOKUP($E42,'DB Equipment'!$A:$P,12,0),"")))))) -> ATF Gearkare | K42: =IF(L$1="Germany",VLOOKUP(E42,Prices!A:AA,16,0),VLOOKUP(E42,Prices!A:AA,3,0)) -> 6070 | L42: =VLOOKUP(E42,Prices!A:AA,HLOOKUP(L$1&"D",Prices!A:AA,2,0),0) -> 0.55 | M42: =IF(VLOOKUP(E42,Prices!A:AA,HLOOKUP(L$1&"2",Prices!A:AA,2,0),0)="","",VLOOKUP(E42,Prices!A:AA,HLOOKUP(L$1&"2",Prices!A:AA,2,0),0)) | N42: =IFERROR(IF(M42="",$K42*(1-L42),$K42*(1-L42)*(1-M42)),"n.a.") -> 2731.5
C43: =IF($J$1="ITALIANO",VLOOKUP(E43,'DB Equipment'!$A:$K,7,0),IF($J$1="ESPAÑOL",VLOOKUP(E43,'DB Equipment'!$A:$K,6,0),IF($J$1="DEUTSCH",VLOOKUP(E43,'DB Equipment'!$A:$K,4,0),IF($J$1="FRANÇAIS",VLOOKUP(E43,'DB Equipment'!$A:$K,5,0),IF($J$1="ENGLISH",VLOOKUP(E43,'DB Equipment'!$A:$K,3,0),""))))) -> ATF | D43: =VLOOKUP(E43,'DB Equipment'!A:P,2,0) -> ATF Gearkare | E43: DECKY1ATF0000SIM | F43: =VLOOKUP(E43,'DB Equipment'!A:K,8,0) -> ATF Gearkare Simulator | G43: =IF(VLOOKUP(E43,'DB Equipment'!A:K,9,0)=0,"",VLOOKUP(E43,'DB Equipment'!A:K,9,0)) | H43: =IF(VLOOKUP(E43,'DB Equipment'!A:K,10,0)=0,"",VLOOKUP(E43,'DB Equipment'!A:K,10,0)) -> 220-240V 50/60 Hz | I43: =IF(VLOOKUP(E43,'DB Equipment'!A:K,11,0)=0,"",VLOOKUP(E43,'DB Equipment'!A:K,11,0)) | J43: =IF(IF($J$1="ITALIANO",VLOOKUP($E43,'DB Equipment'!$A:$P,16,0),IF($J$1="ESPAÑOL",VLOOKUP($E43,'DB Equipment'!$A:$P,15,0),IF($J$1="DEUTSCH",VLOOKUP($E43,'DB Equipment'!$A:$P,13,0),IF($J$1="FRANÇAIS",VLOOKUP($E43,'DB Equipment'!$A:$P,14,0),IF($J$1="ENGLISH",VLOOKUP($E43,'DB Equipment'!$A:$P,12,0),"")))))=0,"",IF($J$1="ITALIANO",VLOOKUP($E43,'DB Equipment'!$A:$P,16,0),IF($J$1="ESPAÑOL",VLOOKUP($E43,'DB Equipment'!$A:$P,15,0),IF($J$1="DEUTSCH",VLOOKUP($E43,'DB Equipment'!$A:$P,13,0),IF($J$1="FRANÇAIS",VLOOKUP($E43,'DB Equipment'!$A:$P,14,0),IF($J$1="ENGLISH",VLOOKUP($E43,'DB Equipment'!$A:$P,12,0),"")))))) -> ATF Gearkare Simulator | K43: =IF(L$1="Germany",VLOOKUP(E43,Prices!A:AA,16,0),VLOOKUP(E43,Prices!A:AA,3,0)) -> 1950 | L43: =VLOOKUP(E43,Prices!A:AA,HLOOKUP(L$1&"D",Prices!A:AA,2,0),0) -> 0.55 | M43: =IF(VLOOKUP(E43,Prices!A:AA,HLOOKUP(L$1&"2",Prices!A:AA,2,0),0)="","",VLOOKUP(E43,Prices!A:AA,HLOOKUP(L$1&"2",Prices!A:AA,2,0),0)) | N43: =IFERROR(IF(M43="",$K43*(1-L43),$K43*(1-L43)*(1-M43)),"n.a.") -> 877.5
E45: =IFERROR(VLOOKUP($J$1,Language!$A$38:$F$42,2,0),"Select a Language Above") -> NOTE: all above mentioned machines in RAL 5015b, 3000, 7040 keep the same net price as showed in this list. All other colors may be available with a LP surcharge of 280€
E47: =IFERROR(VLOOKUP($J$1,Language!$A$45:$F$49,2,0),"Select a Language Above") -> Standard discount on ACCESSORIES Price List: | H47: 0.4
E48: =IFERROR(VLOOKUP($J$1,Language!$A$51:$F$55,2,0),"Select a Language Above") -> Standard discount on SPARE PARTS Price List: | H48: 52%
E50: =IFERROR(VLOOKUP($J$1,Language!$A$58:$F$62,2,0),"Select a Language Above") -> Required by:
E51: =IFERROR(VLOOKUP($J$1,Language!$A$65:$F$69,2,0),"Select a Language Above") -> Date:
E52: =IFERROR(VLOOKUP($J$1,Language!$A$72:$F$76,2,0),"Select a Language Above") -> Signature:
E54: =IFERROR(VLOOKUP($J$1,Language!$A$79:$F$83,2,0),"Select a Language Above") -> Approved by:
E55: =IFERROR(VLOOKUP($J$1,Language!$A$65:$F$69,2,0),"Select a Language Above") -> Date:
E56: =IFERROR(VLOOKUP($J$1,Language!$A$72:$F$76,2,0),"Select a Language Above") -> Signature:

Sheet Accessories
D1: PRICE LIST 2026 (EURO) | G1: ENGLISH | H1: =IFERROR(VLOOKUP($G$1,Language!$A$11:$F$15,5,0),"Select a Language Above")&" 2026.01.01" -> Validity 2026.01.01 | I1: CEE & CIS
C2: =IFERROR(VLOOKUP($J$1,Language!$A$11:$F$15,2,0),"Select a Language Above") -> Select a Language Above | E2: =IFERROR(VLOOKUP($G$1,Language!$C:$J,2,FALSE),"Select a Language Above") -> CUSTOMER CODE
E3: =IFERROR(VLOOKUP($G$1,Language!$C:$J,3,FALSE),"Select a Language Above") -> CUSTOMER NAME
E4: =IFERROR(VLOOKUP($G$1,Language!$C:$J,4,FALSE),"Select a Language Above") -> COUNTRY
E5: =IFERROR(VLOOKUP($G$1,Language!$C:$J,5,FALSE),"Select a Language Above") -> PAYMENT TERM
C6: =IFERROR(VLOOKUP($J$1,Language!$A$11:$F$15,4,0),"Select a Language Above") -> Select a Language Above | E6: =IFERROR(VLOOKUP($G$1,Language!$C:$J,6,FALSE),"Select a Language Above") -> REFERENCED PRICE LIST | F6: PL 2025.04
E7: =IFERROR(VLOOKUP($G$1,Language!$C:$J,7,FALSE),"Select a Language Above") -> CURRENCY | F7: Euro
C8: =IFERROR(VLOOKUP($J$1,Language!$A$11:$F$15,6,0),"Select a Language Above") -> Select a Language Above | E8: =IFERROR(VLOOKUP($G$1,Language!$C:$J,8,FALSE),"Select a Language Above") -> CREDIT LIMIT
B10: =IFERROR(VLOOKUP($G$1,Language!$A$19:$N$23,2,0),"Select a Language Above") -> PRODUCT IMAGE | C10: =IFERROR(VLOOKUP($G$1,Language!$A$19:$P$23,14,0),"Select a Language Above") -> CATEGORY | D10: =IFERROR(VLOOKUP($G$1,Language!$A$19:$P$23,3,0),"Select a Language Above") -> P/N | E10: =IFERROR(VLOOKUP($G$1,Language!$A$19:$P$23,15,0),"Select a Language Above") -> ITEM | F10: =IFERROR(VLOOKUP($G$1,Language!$A$19:$P$23,6,0),"Select a Language Above") -> DESCRIPTION | G10: =IFERROR(VLOOKUP($G$1,Language!$A$19:$P$23,16,0),"Select a Language Above") -> COMPATIBILITY | H10: =IFERROR(VLOOKUP($G$1,Language!$A$19:$N$23,10,0),"Select a Language Above") -> List Price | I10: =IFERROR(VLOOKUP($G$1,Language!$A$19:$N$23,11,0),"Select a Language Above") -> Discount | J10: =IFERROR(VLOOKUP($G$1,Language!$A$19:$N$23,12,0),"Select a Language Above") -> Net Price
C11: =IF($G$1="ITALIANO",VLOOKUP(D11,'DB Accessori'!$A:$P,6,0),IF($G$1="ESPAÑOL",VLOOKUP(D11,'DB Accessori'!$A:$P,5,0),IF($G$1="DEUTSCH",VLOOKUP(D11,'DB Accessori'!$A:$P,3,0),IF($G$1="FRANÇAIS",VLOOKUP(D11,'DB Accessori'!$A:$P,4,0),IF($G$1="ENGLISH",VLOOKUP(D11,'DB Accessori'!$A:$P,2,0),""))))) -> PDL | D11: EAX0068L01A | E11: =IF($G$1="ITALIANO",VLOOKUP(D11,'DB Accessori'!$A:$P,11,0),IF($G$1="ESPAÑOL",VLOOKUP(D11,'DB Accessori'!$A:$P,10,0),IF($G$1="DEUTSCH",VLOOKUP(D11,'DB Accessori'!$A:$P,8,0),IF($G$1="FRANÇAIS",VLOOKUP(D11,'DB Accessori'!$A:$P,9,0),IF($G$1="ENGLISH",VLOOKUP(D11,'DB Accessori'!$A:$P,7,0),""))))) -> Adaptor cable DA-5 | F11: =IF($G$1="ITALIANO",VLOOKUP(D11,'DB Accessori'!$A:$P,16,0),IF($G$1="ESPAÑOL",VLOOKUP(D11,'DB Accessori'!$A:$P,15,0),IF($G$1="DEUTSCH",VLOOKUP(D11,'DB Accessori'!$A:$P,13,0),IF($G$1="FRANÇAIS",VLOOKUP(D11,'DB Accessori'!$A:$P,14,0),IF($G$1="ENGLISH",VLOOKUP(D11,'DB Accessori'!$A:$P,12,0),""))))) -> Adaptor cable DA-10 | G11: =IF(IF($G$1="ITALIANO",VLOOKUP(D11,'DB Accessori'!$A:$U,21,0),IF($G$1="ESPAÑOL",VLOOKUP(D11,'DB Accessori'!$A:$U,20,0),IF($G$1="DEUTSCH",VLOOKUP(D11,'DB Accessori'!$A:$U,18,0),IF($G$1="FRANÇAIS",VLOOKUP(D11,'DB Accessori'!$A:$U,19,0),IF($G$1="ENGLISH",VLOOKUP(D11,'DB Accessori'!$A:$U,17,0),"")))))=0,"",(IF($G$1="ITALIANO",VLOOKUP(D11,'DB Accessori'!$A:$U,21,0),IF($G$1="ESPAÑOL",VLOOKUP(D11,'DB Accessori'!$A:$U,20,0),IF($G$1="DEUTSCH",VLOOKUP(D11,'DB Accessori'!$A:$U,18,0),IF($G$1="FRANÇAIS",VLOOKUP(D11,'DB Accessori'!$A:$U,19,0),IF($G$1="ENGLISH",VLOOKUP(D11,'DB Accessori'!$A:$U,17,0),""))))))) -> PDL 3000, 3200, 4000, 4100, 5000, 5500, 5600, 7100, 8000, 8100 | H11: =IF(I$1="Germany",VLOOKUP(D11,Prices!A:AA,16,0),VLOOKUP(D11,Prices!A:AA,3,0)) -> 114 | I11: =VLOOKUP(D11,Prices!A:AA,HLOOKUP(I$1&"D",Prices!A:AA,2,0),0) -> 0.4 | J11: =+$H11*(1-I11) -> 68.4
C12: =IF($G$1="ITALIANO",VLOOKUP(D12,'DB Accessori'!$A:$P,6,0),IF($G$1="ESPAÑOL",VLOOKUP(D12,'DB Accessori'!$A:$P,5,0),IF($G$1="DEUTSCH",VLOOKUP(D12,'DB Accessori'!$A:$P,3,0),IF($G$1="FRANÇAIS",VLOOKUP(D12,'DB Accessori'!$A:$P,4,0),IF($G$1="ENGLISH",VLOOKUP(D12,'DB Accessori'!$A:$P,2,0),""))))) -> PDL | D12: EAX0068L00C | E12: =IF($G$1="ITALIANO",VLOOKUP(D12,'DB Accessori'!$A:$P,11,0),IF($G$1="ESPAÑOL",VLOOKUP(D12,'DB Accessori'!$A:$P,10,0),IF($G$1="DEUTSCH",VLOOKUP(D12,'DB Accessori'!$A:$P,8,0),IF($G$1="FRANÇAIS",VLOOKUP(D12,'DB Accessori'!$A:$P,9,0),IF($G$1="ENGLISH",VLOOKUP(D12,'DB Accessori'!$A:$P,7,0),""))))) -> OBDII data cable w/o light (16-pin cable) | F12: =IF($G$1="ITALIANO",VLOOKUP(D12,'DB Accessori'!$A:$P,16,0),IF($G$1="ESPAÑOL",VLOOKUP(D12,'DB Accessori'!$A:$P,15,0),IF($G$1="DEUTSCH",VLOOKUP(D12,'DB Accessori'!$A:$P,13,0),IF($G$1="FRANÇAIS",VLOOKUP(D12,'DB Accessori'!$A:$P,14,0),IF($G$1="ENGLISH",VLOOKUP(D12,'DB Accessori'!$A:$P,12,0),""))))) -> OBDII data cable w/o light (16-pin cable) | G12: =IF(IF($G$1="ITALIANO",VLOOKUP(D12,'DB Accessori'!$A:$U,21,0),IF($G$1="ESPAÑOL",VLOOKUP(D12,'DB Accessori'!$A:$U,20,0),IF($G$1="DEUTSCH",VLOOKUP(D12,'DB Accessori'!$A:$U,18,0),IF($G$1="FRANÇAIS",VLOOKUP(D12,'DB Accessori'!$A:$U,19,0),IF($G$1="ENGLISH",VLOOKUP(D12,'DB Accessori'!$A:$U,17,0),"")))))=0,"",(IF($G$1="ITALIANO",VLOOKUP(D12,'DB Accessori'!$A:$U,21,0),IF($G$1="ESPAÑOL",VLOOKUP(D12,'DB Accessori'!$A:$U,20,0),IF($G$1="DEUTSCH",VLOOKUP(D12,'DB Accessori'!$A:$U,18,0),IF($G$1="FRANÇAIS",VLOOKUP(D12,'DB Accessori'!$A:$U,19,0),IF($G$1="ENGLISH",VLOOKUP(D12,'DB Accessori'!$A:$U,17,0),""))))))) -> PDL 3000, 3200, 4000, 4100, 5000, 5500, 7100 | H12: =IF(I$1="Germany",VLOOKUP(D12,Prices!A:AA,16,0),VLOOKUP(D12,Prices!A:AA,3,0)) -> 72 | I12: =VLOOKUP(D12,Prices!A:AA,HLOOKUP(I$1&"D",Prices!A:AA,2,0),0) -> 0.4 | J12: =+$H12*(1-I12) -> 43.2
C13: =IF($G$1="ITALIANO",VLOOKUP(D13,'DB Accessori'!$A:$P,6,0),IF($G$1="ESPAÑOL",VLOOKUP(D13,'DB Accessori'!$A:$P,5,0),IF($G$1="DEUTSCH",VLOOKUP(D13,'DB Accessori'!$A:$P,3,0),IF($G$1="FRANÇAIS",VLOOKUP(D13,'DB Accessori'!$A:$P,4,0),IF($G$1="ENGLISH",VLOOKUP(D13,'DB Accessori'!$A:$P,2,0),""))))) -> PDL | D13: EAX0068L26A | E13: =IF($G$1="ITALIANO",VLOOKUP(D13,'DB Accessori'!$A:$P,11,0),IF($G$1="ESPAÑOL",VLOOKUP(D13,'DB Accessori'!$A:$P,10,0),IF($G$1="DEUTSCH",VLOOKUP(D13,'DB Accessori'!$A:$P,8,0),IF($G$1="FRANÇAIS",VLOOKUP(D13,'DB Accessori'!$A:$P,9,0),IF($G$1="ENGLISH",VLOOKUP(D13,'DB Accessori'!$A:$P,7,0),""))))) -> OBDII data cable w/ light (16-pin cable) | F13: =IF($G$1="ITALIANO",VLOOKUP(D13,'DB Accessori'!$A:$P,16,0),IF($G$1="ESPAÑOL",VLOOKUP(D13,'DB Accessori'!$A:$P,15,0),IF($G$1="DEUTSCH",VLOOKUP(D13,'DB Accessori'!$A:$P,13,0),IF($G$1="FRANÇAIS",VLOOKUP(D13,'DB Accessori'!$A:$P,14,0),IF($G$1="ENGLISH",VLOOKUP(D13,'DB Accessori'!$A:$P,12,0),""))))) -> OBDII data cable w/ light (16-pin cable) | G13: =IF(IF($G$1="ITALIANO",VLOOKUP(D13,'DB Accessori'!$A:$U,21,0),IF($G$1="ESPAÑOL",VLOOKUP(D13,'DB Accessori'!$A:$U,20,0),IF($G$1="DEUTSCH",VLOOKUP(D13,'DB Accessori'!$A:$U,18,0),IF($G$1="FRANÇAIS",VLOOKUP(D13,'DB Accessori'!$A:$U,19,0),IF($G$1="ENGLISH",VLOOKUP(D13,'DB Accessori'!$A:$U,17,0),"")))))=0,"",(IF($G$1="ITALIANO",VLOOKUP(D13,'DB Accessori'!$A:$U,21,0),IF($G$1="ESPAÑOL",VLOOKUP(D13,'DB Accessori'!$A:$U,20,0),IF($G$1="DEUTSCH",VLOOKUP(D13,'DB Accessori'!$A:$U,18,0),IF($G$1="FRANÇAIS",VLOOKUP(D13,'DB Accessori'!$A:$U,19,0),IF($G$1="ENGLISH",VLOOKUP(D13,'DB Accessori'!$A:$U,17,0),""))))))) -> PDL 4000, 4100, 5000, 5500, 5600, 7100, 8000, 8100 | H13: =IF(I$1="Germany",VLOOKUP(D13,Prices!A:AA,16,0),VLOOKUP(D13,Prices!A:AA,3,0)) -> 156 | I13: =VLOOKUP(D13,Prices!A:AA,HLOOKUP(I$1&"D",Prices!A:AA,2,0),0) -> 0.4 | J13: =+$H13*(1-I13) -> 93.6
C14: =IF($G$1="ITALIANO",VLOOKUP(D14,'DB Accessori'!$A:$P,6,0),IF($G$1="ESPAÑOL",VLOOKUP(D14,'DB Accessori'!$A:$P,5,0),IF($G$1="DEUTSCH",VLOOKUP(D14,'DB Accessori'!$A:$P,3,0),IF($G$1="FRANÇAIS",VLOOKUP(D14,'DB Accessori'!$A:$P,4,0),IF($G$1="ENGLISH",VLOOKUP(D14,'DB Accessori'!$A:$P,2,0),""))))) -> PDL | D14: EAX0072L17A | E14: =IF($G$1="ITALIANO",VLOOKUP(D14,'DB Accessori'!$A:$P,11,0),IF($G$1="ESPAÑOL",VLOOKUP(D14,'DB Accessori'!$A:$P,10,0),IF($G$1="DEUTSCH",VLOOKUP(D14,'DB Accessori'!$A:$P,8,0),IF($G$1="FRANÇAIS",VLOOKUP(D14,'DB Accessori'!$A:$P,9,0),IF($G$1="ENGLISH",VLOOKUP(D14,'DB Accessori'!$A:$P,7,0),""))))) -> DA-4EA Ethernet DOIP data cable | F14: =IF($G$1="ITALIANO",VLOOKUP(D14,'DB Accessori'!$A:$P,16,0),IF($G$1="ESPAÑOL",VLOOKUP(D14,'DB Accessori'!$A:$P,15,0),IF($G$1="DEUTSCH",VLOOKUP(D14,'DB Accessori'!$A:$P,13,0),IF($G$1="FRANÇAIS",VLOOKUP(D14,'DB Accessori'!$A:$P,14,0),IF($G$1="ENGLISH",VLOOKUP(D14,'DB Accessori'!$A:$P,12,0),""))))) -> DA-4EA Ethernet DOIP data cable | G14: =IF(IF($G$1="ITALIANO",VLOOKUP(D14,'DB Accessori'!$A:$U,21,0),IF($G$1="ESPAÑOL",VLOOKUP(D14,'DB Accessori'!$A:$U,20,0),IF($G$1="DEUTSCH",VLOOKUP(D14,'DB Accessori'!$A:$U,18,0),IF($G$1="FRANÇAIS",VLOOKUP(D14,'DB Accessori'!$A:$U,19,0),IF($G$1="ENGLISH",VLOOKUP(D14,'DB Accessori'!$A:$U,17,0),"")))))=0,"",(IF($G$1="ITALIANO",VLOOKUP(D14,'DB Accessori'!$A:$U,21,0),IF($G$1="ESPAÑOL",VLOOKUP(D14,'DB Accessori'!$A:$U,20,0),IF($G$1="DEUTSCH",VLOOKUP(D14,'DB Accessori'!$A:$U,18,0),IF($G$1="FRANÇAIS",VLOOKUP(D14,'DB Accessori'!$A:$U,19,0),IF($G$1="ENGLISH",VLOOKUP(D14,'DB Accessori'!$A:$U,17,0),""))))))) -> PDL 3200, 4100, 5500, 5600, 7100, 8000, 8100 | H14: =IF(I$1="Germany",VLOOKUP(D14,Prices!A:AA,16,0),VLOOKUP(D14,Prices!A:AA,3,0)) -> 240 | I14: =VLOOKUP(D14,Prices!A:AA,HLOOKUP(I$1&"D",Prices!A:AA,2,0),0) -> 0.4 | J14: =+$H14*(1-I14) -> 144
C15: =IF($G$1="ITALIANO",VLOOKUP(D15,'DB Accessori'!$A:$P,6,0),IF($G$1="ESPAÑOL",VLOOKUP(D15,'DB Accessori'!$A:$P,5,0),IF($G$1="DEUTSCH",VLOOKUP(D15,'DB Accessori'!$A:$P,3,0),IF($G$1="FRANÇAIS",VLOOKUP(D15,'DB Accessori'!$A:$P,4,0),IF($G$1="ENGLISH",VLOOKUP(D15,'DB Accessori'!$A:$P,2,0),""))))) -> PDL | D15: 2-03965A | E15: =IF($G$1="ITALIANO",VLOOKUP(D15,'DB Accessori'!$A:$P,11,0),IF($G$1="ESPAÑOL",VLOOKUP(D15,'DB Accessori'!$A:$P,10,0),IF($G$1="DEUTSCH",VLOOKUP(D15,'DB Accessori'!$A:$P,8,0),IF($G$1="FRANÇAIS",VLOOKUP(D15,'DB Accessori'!$A:$P,9,0),IF($G$1="ENGLISH",VLOOKUP(D15,'DB Accessori'!$A:$P,7,0),""))))) -> Soft Case | F15: =IF($G$1="ITALIANO",VLOOKUP(D15,'DB Accessori'!$A:$P,16,0),IF($G$1="ESPAÑOL",VLOOKUP(D15,'DB Accessori'!$A:$P,15,0),IF($G$1="DEUTSCH",VLOOKUP(D15,'DB Accessori'!$A:$P,13,0),IF($G$1="FRANÇAIS",VLOOKUP(D15,'DB Accessori'!$A:$P,14,0),IF($G$1="ENGLISH",VLOOKUP(D15,'DB Accessori'!$A:$P,12,0),""))))) -> Soft Case | G15: =IF(IF($G$1="ITALIANO",VLOOKUP(D15,'DB Accessori'!$A:$U,21,0),IF($G$1="ESPAÑOL",VLOOKUP(D15,'DB Accessori'!$A:$U,20,0),IF($G$1="DEUTSCH",VLOOKUP(D15,'DB Accessori'!$A:$U,18,0),IF($G$1="FRANÇAIS",VLOOKUP(D15,'DB Accessori'!$A:$U,19,0),IF($G$1="ENGLISH",VLOOKUP(D15,'DB Accessori'!$A:$U,17,0),"")))))=0,"",(IF($G$1="ITALIANO",VLOOKUP(D15,'DB Accessori'!$A:$U,21,0),IF($G$1="ESPAÑOL",VLOOKUP(D15,'DB Accessori'!$A:$U,20,0),IF($G$1="DEUTSCH",VLOOKUP(D15,'DB Accessori'!$A:$U,18,0),IF($G$1="FRANÇAIS",VLOOKUP(D15,'DB Accessori'!$A:$U,19,0),IF($G$1="ENGLISH",VLOOKUP(D15,'DB Accessori'!$A:$U,17,0),""))))))) -> PDL 3200, 4100, 5600, 7100, 8000, 8100 | H15: =IF(I$1="Germany",VLOOKUP(D15,Prices!A:AA,16,0),VLOOKUP(D15,Prices!A:AA,3,0)) -> 28 | I15: =VLOOKUP(D15,Prices!A:AA,HLOOKUP(I$1&"D",Prices!A:AA,2,0),0) -> 0.4 | J15: =+$H15*(1-I15) -> 16.8
C16: =IF($G$1="ITALIANO",VLOOKUP(D16,'DB Accessori'!$A:$P,6,0),IF($G$1="ESPAÑOL",VLOOKUP(D16,'DB Accessori'!$A:$P,5,0),IF($G$1="DEUTSCH",VLOOKUP(D16,'DB Accessori'!$A:$P,3,0),IF($G$1="FRANÇAIS",VLOOKUP(D16,'DB Accessori'!$A:$P,4,0),IF($G$1="ENGLISH",VLOOKUP(D16,'DB Accessori'!$A:$P,2,0),""))))) -> PDL | D16: EAC0111L76A3 | E16: =IF($G$1="ITALIANO",VLOOKUP(D16,'DB Accessori'!$A:$P,11,0),IF($G$1="ESPAÑOL",VLOOKUP(D16,'DB Accessori'!$A:$P,10,0),IF($G$1="DEUTSCH",VLOOKUP(D16,'DB Accessori'!$A:$P,8,0),IF($G$1="FRANÇAIS",VLOOKUP(D16,'DB Accessori'!$A:$P,9,0),IF($G$1="ENGLISH",VLOOKUP(D16,'DB Accessori'!$A:$P,7,0),""))))) -> Screen Protector 3 Pack | F16: =IF($G$1="ITALIANO",VLOOKUP(D16,'DB Accessori'!$A:$P,16,0),IF($G$1="ESPAÑOL",VLOOKUP(D16,'DB Accessori'!$A:$P,15,0),IF($G$1="DEUTSCH",VLOOKUP(D16,'DB Accessori'!$A:$P,13,0),IF($G$1="FRANÇAIS",VLOOKUP(D16,'DB Accessori'!$A:$P,14,0),IF($G$1="ENGLISH",VLOOKUP(D16,'DB Accessori'!$A:$P,12,0),""))))) -> Screen Protector 3 Pack | G16: =IF(IF($G$1="ITALIANO",VLOOKUP(D16,'DB Accessori'!$A:$U,21,0),IF($G$1="ESPAÑOL",VLOOKUP(D16,'DB Accessori'!$A:$U,20,0),IF($G$1="DEUTSCH",VLOOKUP(D16,'DB Accessori'!$A:$U,18,0),IF($G$1="FRANÇAIS",VLOOKUP(D16,'DB Accessori'!$A:$U,19,0),IF($G$1="ENGLISH",VLOOKUP(D16,'DB Accessori'!$A:$U,17,0),"")))))=0,"",(IF($G$1="ITALIANO",VLOOKUP(D16,'DB Accessori'!$A:$U,21,0),IF($G$1="ESPAÑOL",VLOOKUP(D16,'DB Accessori'!$A:$U,20,0),IF($G$1="DEUTSCH",VLOOKUP(D16,'DB Accessori'!$A:$U,18,0),IF($G$1="FRANÇAIS",VLOOKUP(D16,'DB Accessori'!$A:$U,19,0),IF($G$1="ENGLISH",VLOOKUP(D16,'DB Accessori'!$A:$U,17,0),""))))))) -> PDL 4000, 4100, 5600, 8000, 8100 | H16: =IF(I$1="Germany",VLOOKUP(D16,Prices!A:AA,16,0),VLOOKUP(D16,Prices!A:AA,3,0)) -> 36 | I16: =VLOOKUP(D16,Prices!A:AA,HLOOKUP(I$1&"D",Prices!A:AA,2,0),0) -> 0.4 | J16: =+$H16*(1-I16) -> 21.6
C17: =IF($G$1="ITALIANO",VLOOKUP(D17,'DB Accessori'!$A:$P,6,0),IF($G$1="ESPAÑOL",VLOOKUP(D17,'DB Accessori'!$A:$P,5,0),IF($G$1="DEUTSCH",VLOOKUP(D17,'DB Accessori'!$A:$P,3,0),IF($G$1="FRANÇAIS",VLOOKUP(D17,'DB Accessori'!$A:$P,4,0),IF($G$1="ENGLISH",VLOOKUP(D17,'DB Accessori'!$A:$P,2,0),""))))) -> PDL | D17: EESP115A-4.1 | E17: =IF($G$1="ITALIANO",VLOOKUP(D17,'DB Accessori'!$A:$P,11,0),IF($G$1="ESPAÑOL",VLOOKUP(D17,'DB Accessori'!$A:$P,10,0),IF($G$1="DEUTSCH",VLOOKUP(D17,'DB Accessori'!$A:$P,8,0),IF($G$1="FRANÇAIS",VLOOKUP(D17,'DB Accessori'!$A:$P,9,0),IF($G$1="ENGLISH",VLOOKUP(D17,'DB Accessori'!$A:$P,7,0),""))))) -> PDL 4100 Software update for 1 year (2 minimum per year) | F17: =IF($G$1="ITALIANO",VLOOKUP(D17,'DB Accessori'!$A:$P,16,0),IF($G$1="ESPAÑOL",VLOOKUP(D17,'DB Accessori'!$A:$P,15,0),IF($G$1="DEUTSCH",VLOOKUP(D17,'DB Accessori'!$A:$P,13,0),IF($G$1="FRANÇAIS",VLOOKUP(D17,'DB Accessori'!$A:$P,14,0),IF($G$1="ENGLISH",VLOOKUP(D17,'DB Accessori'!$A:$P,12,0),""))))) -> PDL 4100 Software update for 1 year (2 minimum per year) | G17: =IF(IF($G$1="ITALIANO",VLOOKUP(D17,'DB Accessori'!$A:$U,21,0),IF($G$1="ESPAÑOL",VLOOKUP(D17,'DB Accessori'!$A:$U,20,0),IF($G$1="DEUTSCH",VLOOKUP(D17,'DB Accessori'!$A:$U,18,0),IF($G$1="FRANÇAIS",VLOOKUP(D17,'DB Accessori'!$A:$U,19,0),IF($G$1="ENGLISH",VLOOKUP(D17,'DB Accessori'!$A:$U,17,0),"")))))=0,"",(IF($G$1="ITALIANO",VLOOKUP(D17,'DB Accessori'!$A:$U,21,0),IF($G$1="ESPAÑOL",VLOOKUP(D17,'DB Accessori'!$A:$U,20,0),IF($G$1="DEUTSCH",VLOOKUP(D17,'DB Accessori'!$A:$U,18,0),IF($G$1="FRANÇAIS",VLOOKUP(D17,'DB Accessori'!$A:$U,19,0),IF($G$1="ENGLISH",VLOOKUP(D17,'DB Accessori'!$A:$U,17,0),""))))))) -> PDL 4100 | H17: =IF(I$1="Germany",VLOOKUP(D17,Prices!A:AA,16,0),VLOOKUP(D17,Prices!A:AA,3,0)) -> 818 | I17: =VLOOKUP(D17,Prices!A:AA,HLOOKUP(I$1&"D",Prices!A:AA,2,0),0) -> 0.4 | J17: =+$H17*(1-I17) -> 490.8
C18: =IF($G$1="ITALIANO",VLOOKUP(D18,'DB Accessori'!$A:$P,6,0),IF($G$1="ESPAÑOL",VLOOKUP(D18,'DB Accessori'!$A:$P,5,0),IF($G$1="DEUTSCH",VLOOKUP(D18,'DB Accessori'!$A:$P,3,0),IF($G$1="FRANÇAIS",VLOOKUP(D18,'DB Accessori'!$A:$P,4,0),IF($G$1="ENGLISH",VLOOKUP(D18,'DB Accessori'!$A:$P,2,0),""))))) -> PDL | D18: EESP116A-4.1 | E18: =IF($G$1="ITALIANO",VLOOKUP(D18,'DB Accessori'!$A:$P,11,0),IF($G$1="ESPAÑOL",VLOOKUP(D18,'DB Accessori'!$A:$P,10,0),IF($G$1="DEUTSCH",VLOOKUP(D18,'DB Accessori'!$A:$P,8,0),IF($G$1="FRANÇAIS",VLOOKUP(D18,'DB Accessori'!$A:$P,9,0),IF($G$1="ENGLISH",VLOOKUP(D18,'DB Accessori'!$A:$P,7,0),""))))) -> PDL 4100 Software update for 1 year (2 minimum per year) after termination plus charge for re-activation | F18: =IF($G$1="ITALIANO",VLOOKUP(D18,'DB Accessori'!$A:$P,16,0),IF($G$1="ESPAÑOL",VLOOKUP(D18,'DB Accessori'!$A:$P,15,0),IF($G$1="DEUTSCH",VLOOKUP(D18,'DB Accessori'!$A:$P,13,0),IF($G$1="FRANÇAIS",VLOOKUP(D18,'DB Accessori'!$A:$P,14,0),IF($G$1="ENGLISH",VLOOKUP(D18,'DB Accessori'!$A:$P,12,0),""))))) -> PDL 4100 Software update for 1 year (2 minimum per year) after termination plus charge for re-activation | G18: =IF(IF($G$1="ITALIANO",VLOOKUP(D18,'DB Accessori'!$A:$U,21,0),IF($G$1="ESPAÑOL",VLOOKUP(D18,'DB Accessori'!$A:$U,20,0),IF($G$1="DEUTSCH",VLOOKUP(D18,'DB Accessori'!$A:$U,18,0),IF($G$1="FRANÇAIS",VLOOKUP(D18,'DB Accessori'!$A:$U,19,0),IF($G$1="ENGLISH",VLOOKUP(D18,'DB Accessori'!$A:$U,17,0),"")))))=0,"",(IF($G$1="ITALIANO",VLOOKUP(D18,'DB Accessori'!$A:$U,21,0),IF($G$1="ESPAÑOL",VLOOKUP(D18,'DB Accessori'!$A:$U,20,0),IF($G$1="DEUTSCH",VLOOKUP(D18,'DB Accessori'!$A:$U,18,0),IF($G$1="FRANÇAIS",VLOOKUP(D18,'DB Accessori'!$A:$U,19,0),IF($G$1="ENGLISH",VLOOKUP(D18,'DB Accessori'!$A:$U,17,0),""))))))) -> PDL 4100 | H18: =IF(I$1="Germany",VLOOKUP(D18,Prices!A:AA,16,0),VLOOKUP(D18,Prices!A:AA,3,0)) -> 1172 | I18: =VLOOKUP(D18,Prices!A:AA,HLOOKUP(I$1&"D",Prices!A:AA,2,0),0) -> 0.4 | J18: =+$H18*(1-I18) -> 703.2
C19: =IF($G$1="ITALIANO",VLOOKUP(D19,'DB Accessori'!$A:$P,6,0),IF($G$1="ESPAÑOL",VLOOKUP(D19,'DB Accessori'!$A:$P,5,0),IF($G$1="DEUTSCH",VLOOKUP(D19,'DB Accessori'!$A:$P,3,0),IF($G$1="FRANÇAIS",VLOOKUP(D19,'DB Accessori'!$A:$P,4,0),IF($G$1="ENGLISH",VLOOKUP(D19,'DB Accessori'!$A:$P,2,0),""))))) -> PDL | D19: EESP118A-4.1 | E19: =IF($G$1="ITALIANO",VLOOKUP(D19,'DB Accessori'!$A:$P,11,0),IF($G$1="ESPAÑOL",VLOOKUP(D19,'DB Accessori'!$A:$P,10,0),IF($G$1="DEUTSCH",VLOOKUP(D19,'DB Accessori'!$A:$P,8,0),IF($G$1="FRANÇAIS",VLOOKUP(D19,'DB Accessori'!$A:$P,9,0),IF($G$1="ENGLISH",VLOOKUP(D19,'DB Accessori'!$A:$P,7,0),""))))) -> PDL 4100 Software update for 2 years (2 minimum per year) | F19: =IF($G$1="ITALIANO",VLOOKUP(D19,'DB Accessori'!$A:$P,16,0),IF($G$1="ESPAÑOL",VLOOKUP(D19,'DB Accessori'!$A:$P,15,0),IF($G$1="DEUTSCH",VLOOKUP(D19,'DB Accessori'!$A:$P,13,0),IF($G$1="FRANÇAIS",VLOOKUP(D19,'DB Accessori'!$A:$P,14,0),IF($G$1="ENGLISH",VLOOKUP(D19,'DB Accessori'!$A:$P,12,0),""))))) -> PDL 4100 Software update for 2 years (2 minimum per year) | G19: =IF(IF($G$1="ITALIANO",VLOOKUP(D19,'DB Accessori'!$A:$U,21,0),IF($G$1="ESPAÑOL",VLOOKUP(D19,'DB Accessori'!$A:$U,20,0),IF($G$1="DEUTSCH",VLOOKUP(D19,'DB Accessori'!$A:$U,18,0),IF($G$1="FRANÇAIS",VLOOKUP(D19,'DB Accessori'!$A:$U,19,0),IF($G$1="ENGLISH",VLOOKUP(D19,'DB Accessori'!$A:$U,17,0),"")))))=0,"",(IF($G$1="ITALIANO",VLOOKUP(D19,'DB Accessori'!$A:$U,21,0),IF($G$1="ESPAÑOL",VLOOKUP(D19,'DB Accessori'!$A:$U,20,0),IF($G$1="DEUTSCH",VLOOKUP(D19,'DB Accessori'!$A:$U,18,0),IF($G$1="FRANÇAIS",VLOOKUP(D19,'DB Accessori'!$A:$U,19,0),IF($G$1="ENGLISH",VLOOKUP(D19,'DB Accessori'!$A:$U,17,0),""))))))) -> PDL 4100 | H19: =IF(I$1="Germany",VLOOKUP(D19,Prices!A:AA,16,0),VLOOKUP(D19,Prices!A:AA,3,0)) -> 1474 | I19: =VLOOKUP(D19,Prices!A:AA,HLOOKUP(I$1&"D",Prices!A:AA,2,0),0) -> 0.4 | J19: =+$H19*(1-I19) -> 884.4
C20: =IF($G$1="ITALIANO",VLOOKUP(D20,'DB Accessori'!$A:$P,6,0),IF($G$1="ESPAÑOL",VLOOKUP(D20,'DB Accessori'!$A:$P,5,0),IF($G$1="DEUTSCH",VLOOKUP(D20,'DB Accessori'!$A:$P,3,0),IF($G$1="FRANÇAIS",VLOOKUP(D20,'DB Accessori'!$A:$P,4,0),IF($G$1="ENGLISH",VLOOKUP(D20,'DB Accessori'!$A:$P,2,0),""))))) -> PDL | D20: EESP115A-4.2 | E20: =IF($G$1="ITALIANO",VLOOKUP(D20,'DB Accessori'!$A:$P,11,0),IF($G$1="ESPAÑOL",VLOOKUP(D20,'DB Accessori'!$A:$P,10,0),IF($G$1="DEUTSCH",VLOOKUP(D20,'DB Accessori'!$A:$P,8,0),IF($G$1="FRANÇAIS",VLOOKUP(D20,'DB Accessori'!$A:$P,9,0),IF($G$1="ENGLISH",VLOOKUP(D20,'DB Accessori'!$A:$P,7,0),""))))) -> PDL 4200 Software update for 1 year (2 minimum per year) | F20: =IF($G$1="ITALIANO",VLOOKUP(D20,'DB Accessori'!$A:$P,16,0),IF($G$1="ESPAÑOL",VLOOKUP(D20,'DB Accessori'!$A:$P,15,0),IF($G$1="DEUTSCH",VLOOKUP(D20,'DB Accessori'!$A:$P,13,0),IF($G$1="FRANÇAIS",VLOOKUP(D20,'DB Accessori'!$A:$P,14,0),IF($G$1="ENGLISH",VLOOKUP(D20,'DB Accessori'!$A:$P,12,0),""))))) -> PDL 4200 Software update for 1 year (2 minimum per year) | G20: =IF(IF($G$1="ITALIANO",VLOOKUP(D20,'DB Accessori'!$A:$U,21,0),IF($G$1="ESPAÑOL",VLOOKUP(D20,'DB Accessori'!$A:$U,20,0),IF($G$1="DEUTSCH",VLOOKUP(D20,'DB Accessori'!$A:$U,18,0),IF($G$1="FRANÇAIS",VLOOKUP(D20,'DB Accessori'!$A:$U,19,0),IF($G$1="ENGLISH",VLOOKUP(D20,'DB Accessori'!$A:$U,17,0),"")))))=0,"",(IF($G$1="ITALIANO",VLOOKUP(D20,'DB Accessori'!$A:$U,21,0),IF($G$1="ESPAÑOL",VLOOKUP(D20,'DB Accessori'!$A:$U,20,0),IF($G$1="DEUTSCH",VLOOKUP(D20,'DB Accessori'!$A:$U,18,0),IF($G$1="FRANÇAIS",VLOOKUP(D20,'DB Accessori'!$A:$U,19,0),IF($G$1="ENGLISH",VLOOKUP(D20,'DB Accessori'!$A:$U,17,0),""))))))) -> PDL 4200 | H20: =IF(I$1="Germany",VLOOKUP(D20,Prices!A:AA,16,0),VLOOKUP(D20,Prices!A:AA,3,0)) -> 818 | I20: =VLOOKUP(D20,Prices!A:AA,HLOOKUP(I$1&"D",Prices!A:AA,2,0),0) -> 0.4 | J20: =+$H20*(1-I20) -> 490.8
C21: =IF($G$1="ITALIANO",VLOOKUP(D21,'DB Accessori'!$A:$P,6,0),IF($G$1="ESPAÑOL",VLOOKUP(D21,'DB Accessori'!$A:$P,5,0),IF($G$1="DEUTSCH",VLOOKUP(D21,'DB Accessori'!$A:$P,3,0),IF($G$1="FRANÇAIS",VLOOKUP(D21,'DB Accessori'!$A:$P,4,0),IF($G$1="ENGLISH",VLOOKUP(D21,'DB Accessori'!$A:$P,2,0),""))))) -> PDL | D21: EESP116A-4.2 | E21: =IF($G$1="ITALIANO",VLOOKUP(D21,'DB Accessori'!$A:$P,11,0),IF($G$1="ESPAÑOL",VLOOKUP(D21,'DB Accessori'!$A:$P,10,0),IF($G$1="DEUTSCH",VLOOKUP(D21,'DB Accessori'!$A:$P,8,0),IF($G$1="FRANÇAIS",VLOOKUP(D21,'DB Accessori'!$A:$P,9,0),IF($G$1="ENGLISH",VLOOKUP(D21,'DB Accessori'!$A:$P,7,0),""))))) -> PDL 4200 Software update for 1 year (2 minimum per year) after termination plus charge for re-activation | F21: =IF($G$1="ITALIANO",VLOOKUP(D21,'DB Accessori'!$A:$P,16,0),IF($G$1="ESPAÑOL",VLOOKUP(D21,'DB Accessori'!$A:$P,15,0),IF($G$1="DEUTSCH",VLOOKUP(D21,'DB Accessori'!$A:$P,13,0),IF($G$1="FRANÇAIS",VLOOKUP(D21,'DB Accessori'!$A:$P,14,0),IF($G$1="ENGLISH",VLOOKUP(D21,'DB Accessori'!$A:$P,12,0),""))))) -> PDL 4200 Software update for 1 year (2 minimum per year) after termination plus charge for re-activation | G21: =IF(IF($G$1="ITALIANO",VLOOKUP(D21,'DB Accessori'!$A:$U,21,0),IF($G$1="ESPAÑOL",VLOOKUP(D21,'DB Accessori'!$A:$U,20,0),IF($G$1="DEUTSCH",VLOOKUP(D21,'DB Accessori'!$A:$U,18,0),IF($G$1="FRANÇAIS",VLOOKUP(D21,'DB Accessori'!$A:$U,19,0),IF($G$1="ENGLISH",VLOOKUP(D21,'DB Accessori'!$A:$U,17,0),"")))))=0,"",(IF($G$1="ITALIANO",VLOOKUP(D21,'DB Accessori'!$A:$U,21,0),IF($G$1="ESPAÑOL",VLOOKUP(D21,'DB Accessori'!$A:$U,20,0),IF($G$1="DEUTSCH",VLOOKUP(D21,'DB Accessori'!$A:$U,18,0),IF($G$1="FRANÇAIS",VLOOKUP(D21,'DB Accessori'!$A:$U,19,0),IF($G$1="ENGLISH",VLOOKUP(D21,'DB Accessori'!$A:$U,17,0),""))))))) -> PDL 4200 | H21: =IF(I$1="Germany",VLOOKUP(D21,Prices!A:AA,16,0),VLOOKUP(D21,Prices!A:AA,3,0)) -> 1172 | I21: =VLOOKUP(D21,Prices!A:AA,HLOOKUP(I$1&"D",Prices!A:AA,2,0),0) -> 0.4 | J21: =+$H21*(1-I21) -> 703.2
C22: =IF($G$1="ITALIANO",VLOOKUP(D22,'DB Accessori'!$A:$P,6,0),IF($G$1="ESPAÑOL",VLOOKUP(D22,'DB Accessori'!$A:$P,5,0),IF($G$1="DEUTSCH",VLOOKUP(D22,'DB Accessori'!$A:$P,3,0),IF($G$1="FRANÇAIS",VLOOKUP(D22,'DB Accessori'!$A:$P,4,0),IF($G$1="ENGLISH",VLOOKUP(D22,'DB Accessori'!$A:$P,2,0),""))))) -> PDL | D22: EESP118A-4.2 | E22: =IF($G$1="ITALIANO",VLOOKUP(D22,'DB Accessori'!$A:$P,11,0),IF($G$1="ESPAÑOL",VLOOKUP(D22,'DB Accessori'!$A:$P,10,0),IF($G$1="DEUTSCH",VLOOKUP(D22,'DB Accessori'!$A:$P,8,0),IF($G$1="FRANÇAIS",VLOOKUP(D22,'DB Accessori'!$A:$P,9,0),IF($G$1="ENGLISH",VLOOKUP(D22,'DB Accessori'!$A:$P,7,0),""))))) -> PDL 4200 Software update for 2 years (2 minimum per year) | F22: =IF($G$1="ITALIANO",VLOOKUP(D22,'DB Accessori'!$A:$P,16,0),IF($G$1="ESPAÑOL",VLOOKUP(D22,'DB Accessori'!$A:$P,15,0),IF($G$1="DEUTSCH",VLOOKUP(D22,'DB Accessori'!$A:$P,13,0),IF($G$1="FRANÇAIS",VLOOKUP(D22,'DB Accessori'!$A:$P,14,0),IF($G$1="ENGLISH",VLOOKUP(D22,'DB Accessori'!$A:$P,12,0),""))))) -> PDL 4200 Software update for 2 years (2 minimum per year) | G22: =IF(IF($G$1="ITALIANO",VLOOKUP(D22,'DB Accessori'!$A:$U,21,0),IF($G$1="ESPAÑOL",VLOOKUP(D22,'DB Accessori'!$A:$U,20,0),IF($G$1="DEUTSCH",VLOOKUP(D22,'DB Accessori'!$A:$U,18,0),IF($G$1="FRANÇAIS",VLOOKUP(D22,'DB Accessori'!$A:$U,19,0),IF($G$1="ENGLISH",VLOOKUP(D22,'DB Accessori'!$A:$U,17,0),"")))))=0,"",(IF($G$1="ITALIANO",VLOOKUP(D22,'DB Accessori'!$A:$U,21,0),IF($G$1="ESPAÑOL",VLOOKUP(D22,'DB Accessori'!$A:$U,20,0),IF($G$1="DEUTSCH",VLOOKUP(D22,'DB Accessori'!$A:$U,18,0),IF($G$1="FRANÇAIS",VLOOKUP(D22,'DB Accessori'!$A:$U,19,0),IF($G$1="ENGLISH",VLOOKUP(D22,'DB Accessori'!$A:$U,17,0),""))))))) -> PDL 4200 | H22: =IF(I$1="Germany",VLOOKUP(D22,Prices!A:AA,16,0),VLOOKUP(D22,Prices!A:AA,3,0)) -> 1474 | I22: =VLOOKUP(D22,Prices!A:AA,HLOOKUP(I$1&"D",Prices!A:AA,2,0),0) -> 0.4 | J22: =+$H22*(1-I22) -> 884.4
... C53: =IF($G$1="ITALIANO",VLOOKUP(D53,'DB Accessori'!$A:$P,6,0),IF($G$1="ESPAÑOL",VLOOKUP(D53,'DB Accessori'!$A:$P,5,0),IF($G$1="DEUTSCH",VLOOKUP(D53,'DB Accessori'!$A:$P,3,0),IF($G$1="FRANÇAIS",VLOOKUP(D53,'DB Accessori'!$A:$P,4,0),IF($G$1="ENGLISH",VLOOKUP(D53,'DB Accessori'!$A:$P,2,0),""))))) -> A/C | D53: DECKTUB1149 | E53: =IF($G$1="ITALIANO",VLOOKUP(D53,'DB Accessori'!$A:$P,11,0),IF($G$1="ESPAÑOL",VLOOKUP(D53,'DB Accessori'!$A:$P,10,0),IF($G$1="DEUTSCH",VLOOKUP(D53,'DB Accessori'!$A:$P,8,0),IF($G$1="FRANÇAIS",VLOOKUP(D53,'DB Accessori'!$A:$P,9,0),IF($G$1="ENGLISH",VLOOKUP(D53,'DB Accessori'!$A:$P,7,0),""))))) -> R134A Service hose 6 m, blue, for QTECH II / III units and Breeze, male/female | F53: =IF($G$1="ITALIANO",VLOOKUP(D53,'DB Accessori'!$A:$P,16,0),IF($G$1="ESPAÑOL",VLOOKUP(D53,'DB Accessori'!$A:$P,15,0),IF($G$1="DEUTSCH",VLOOKUP(D53,'DB Accessori'!$A:$P,13,0),IF($G$1="FRANÇAIS",VLOOKUP(D53,'DB Accessori'!$A:$P,14,0),IF($G$1="ENGLISH",VLOOKUP(D53,'DB Accessori'!$A:$P,12,0),""))))) -> R134A Service hose 6 m, blue, for QTECH II / III units and Breeze, male/female | G53: =IF(IF($G$1="ITALIANO",VLOOKUP(D53,'DB Accessori'!$A:$U,21,0),IF($G$1="ESPAÑOL",VLOOKUP(D53,'DB Accessori'!$A:$U,20,0),IF($G$1="DEUTSCH",VLOOKUP(D53,'DB Accessori'!$A:$U,18,0),IF($G$1="FRANÇAIS",VLOOKUP(D53,'DB Accessori'!$A:$U,19,0),IF($G$1="ENGLISH",VLOOKUP(D53,'DB Accessori'!$A:$U,17,0),"")))))=0,"",(IF($G$1="ITALIANO",VLOOKUP(D53,'DB Accessori'!$A:$U,21,0),IF($G$1="ESPAÑOL",VLOOKUP(D53,'DB Accessori'!$A:$U,20,0),IF($G$1="DEUTSCH",VLOOKUP(D53,'DB Accessori'!$A:$U,18,0),IF($G$1="FRANÇAIS",VLOOKUP(D53,'DB Accessori'!$A:$U,19,0),IF($G$1="ENGLISH",VLOOKUP(D53,'DB Accessori'!$A:$U,17,0),""))))))) -> All A/C machines | H53: =IF(I$1="Germany",VLOOKUP(D53,Prices!A:AA,16,0),VLOOKUP(D53,Prices!A:AA,3,0)) -> 68 | I53: =VLOOKUP(D53,Prices!A:AA,HLOOKUP(I$1&"D",Prices!A:AA,2,0),0) -> 0.4 | J53: =+$H53*(1-I53) -> 40.8
C54: =IF($G$1="ITALIANO",VLOOKUP(D54,'DB Accessori'!$A:$P,6,0),IF($G$1="ESPAÑOL",VLOOKUP(D54,'DB Accessori'!$A:$P,5,0),IF($G$1="DEUTSCH",VLOOKUP(D54,'DB Accessori'!$A:$P,3,0),IF($G$1="FRANÇAIS",VLOOKUP(D54,'DB Accessori'!$A:$P,4,0),IF($G$1="ENGLISH",VLOOKUP(D54,'DB Accessori'!$A:$P,2,0),""))))) -> A/C | D54: DECKGRTUB0001 | E54: =IF($G$1="ITALIANO",VLOOKUP(D54,'DB Accessori'!$A:$P,11,0),IF($G$1="ESPAÑOL",VLOOKUP(D54,'DB Accessori'!$A:$P,10,0),IF($G$1="DEUTSCH",VLOOKUP(D54,'DB Accessori'!$A:$P,8,0),IF($G$1="FRANÇAIS",VLOOKUP(D54,'DB Accessori'!$A:$P,9,0),IF($G$1="ENGLISH",VLOOKUP(D54,'DB Accessori'!$A:$P,7,0),""))))) -> KoolKare nitogen/forming gas hose kit; for connection to a nitrogen or forming gas fitting, equipment end with hose and quick coupling. Spare parts, accessories as standard option with a Koolkare nitrogen/forming gas option | F54: =IF($G$1="ITALIANO",VLOOKUP(D54,'DB Accessori'!$A:$P,16,0),IF($G$1="ESPAÑOL",VLOOKUP(D54,'DB Accessori'!$A:$P,15,0),IF($G$1="DEUTSCH",VLOOKUP(D54,'DB Accessori'!$A:$P,13,0),IF($G$1="FRANÇAIS",VLOOKUP(D54,'DB Accessori'!$A:$P,14,0),IF($G$1="ENGLISH",VLOOKUP(D54,'DB Accessori'!$A:$P,12,0),""))))) -> KoolKare nitogen/forming gas hose kit; for connection to a nitrogen or forming gas fitting, equipment end with hose and quick coupling. Spare parts, accessories as standard option with a Koolkare nitrogen/forming gas option | G54: =IF(IF($G$1="ITALIANO",VLOOKUP(D54,'DB Accessori'!$A:$U,21,0),IF($G$1="ESPAÑOL",VLOOKUP(D54,'DB Accessori'!$A:$U,20,0),IF($G$1="DEUTSCH",VLOOKUP(D54,'DB Accessori'!$A:$U,18,0),IF($G$1="FRANÇAIS",VLOOKUP(D54,'DB Accessori'!$A:$U,19,0),IF($G$1="ENGLISH",VLOOKUP(D54,'DB Accessori'!$A:$U,17,0),"")))))=0,"",(IF($G$1="ITALIANO",VLOOKUP(D54,'DB Accessori'!$A:$U,21,0),IF($G$1="ESPAÑOL",VLOOKUP(D54,'DB Accessori'!$A:$U,20,0),IF($G$1="DEUTSCH",VLOOKUP(D54,'DB Accessori'!$A:$U,18,0),IF($G$1="FRANÇAIS",VLOOKUP(D54,'DB Accessori'!$A:$U,19,0),IF($G$1="ENGLISH",VLOOKUP(D54,'DB Accessori'!$A:$U,17,0),""))))))) -> Qtech IV, Dual Gas, Qtech III | H54: 80.5 | I54: =VLOOKUP(D54,Prices!A:AA,HLOOKUP(I$1&"D",Prices!A:AA,2,0),0) -> 0.4 | J54: =+$H54*(1-I54) -> 48.3
C55: =IF($G$1="ITALIANO",VLOOKUP(D55,'DB Accessori'!$A:$P,6,0),IF($G$1="ESPAÑOL",VLOOKUP(D55,'DB Accessori'!$A:$P,5,0),IF($G$1="DEUTSCH",VLOOKUP(D55,'DB Accessori'!$A:$P,3,0),IF($G$1="FRANÇAIS",VLOOKUP(D55,'DB Accessori'!$A:$P,4,0),IF($G$1="ENGLISH",VLOOKUP(D55,'DB Accessori'!$A:$P,2,0),""))))) -> A/C | D55: DECKAEK322 | E55: =IF($G$1="ITALIANO",VLOOKUP(D55,'DB Accessori'!$A:$P,11,0),IF($G$1="ESPAÑOL",VLOOKUP(D55,'DB Accessori'!$A:$P,10,0),IF($G$1="DEUTSCH",VLOOKUP(D55,'DB Accessori'!$A:$P,8,0),IF($G$1="FRANÇAIS",VLOOKUP(D55,'DB Accessori'!$A:$P,9,0),IF($G$1="ENGLISH",VLOOKUP(D55,'DB Accessori'!$A:$P,7,0),""))))) -> Bottle of Saniflux liquid (1000 ml) | F55: =IF($G$1="ITALIANO",VLOOKUP(D55,'DB Accessori'!$A:$P,16,0),IF($G$1="ESPAÑOL",VLOOKUP(D55,'DB Accessori'!$A:$P,15,0),IF($G$1="DEUTSCH",VLOOKUP(D55,'DB Accessori'!$A:$P,13,0),IF($G$1="FRANÇAIS",VLOOKUP(D55,'DB Accessori'!$A:$P,14,0),IF($G$1="ENGLISH",VLOOKUP(D55,'DB Accessori'!$A:$P,12,0),""))))) -> Bottle of Saniflux liquid (1000 ml) | G55: =IF(IF($G$1="ITALIANO",VLOOKUP(D55,'DB Accessori'!$A:$U,21,0),IF($G$1="ESPAÑOL",VLOOKUP(D55,'DB Accessori'!$A:$U,20,0),IF($G$1="DEUTSCH",VLOOKUP(D55,'DB Accessori'!$A:$U,18,0),IF($G$1="FRANÇAIS",VLOOKUP(D55,'DB Accessori'!$A:$U,19,0),IF($G$1="ENGLISH",VLOOKUP(D55,'DB Accessori'!$A:$U,17,0),"")))))=0,"",(IF($G$1="ITALIANO",VLOOKUP(D55,'DB Accessori'!$A:$U,21,0),IF($G$1="ESPAÑOL",VLOOKUP(D55,'DB Accessori'!$A:$U,20,0),IF($G$1="DEUTSCH",VLOOKUP(D55,'DB Accessori'!$A:$U,18,0),IF($G$1="FRANÇAIS",VLOOKUP(D55,'DB Accessori'!$A:$U,19,0),IF($G$1="ENGLISH",VLOOKUP(D55,'DB Accessori'!$A:$U,17,0),""))))))) -> All A/C machines | H55: =IF(I$1="Germany",VLOOKUP(D55,Prices!A:AA,16,0),VLOOKUP(D55,Prices!A:AA,3,0)) -> 75.5 | I55: =VLOOKUP(D55,Prices!A:AA,HLOOKUP(I$1&"D",Prices!A:AA,2,0),0) -> 0.4 | J55: =+$H55*(1-I55) -> 45.3
C56: =IF($G$1="ITALIANO",VLOOKUP(D56,'DB Accessori'!$A:$P,6,0),IF($G$1="ESPAÑOL",VLOOKUP(D56,'DB Accessori'!$A:$P,5,0),IF($G$1="DEUTSCH",VLOOKUP(D56,'DB Accessori'!$A:$P,3,0),IF($G$1="FRANÇAIS",VLOOKUP(D56,'DB Accessori'!$A:$P,4,0),IF($G$1="ENGLISH",VLOOKUP(D56,'DB Accessori'!$A:$P,2,0),""))))) -> A/C | D56: DECKAEK275 | E56: =IF($G$1="ITALIANO",VLOOKUP(D56,'DB Accessori'!$A:$P,11,0),IF($G$1="ESPAÑOL",VLOOKUP(D56,'DB Accessori'!$A:$P,10,0),IF($G$1="DEUTSCH",VLOOKUP(D56,'DB Accessori'!$A:$P,8,0),IF($G$1="FRANÇAIS",VLOOKUP(D56,'DB Accessori'!$A:$P,9,0),IF($G$1="ENGLISH",VLOOKUP(D56,'DB Accessori'!$A:$P,7,0),""))))) -> Oil bottle PAG100, R134, HFO1234yf, mechanical and electrical compressor, 6 x 250 ml | F56: =IF($G$1="ITALIANO",VLOOKUP(D56,'DB Accessori'!$A:$P,16,0),IF($G$1="ESPAÑOL",VLOOKUP(D56,'DB Accessori'!$A:$P,15,0),IF($G$1="DEUTSCH",VLOOKUP(D56,'DB Accessori'!$A:$P,13,0),IF($G$1="FRANÇAIS",VLOOKUP(D56,'DB Accessori'!$A:$P,14,0),IF($G$1="ENGLISH",VLOOKUP(D56,'DB Accessori'!$A:$P,12,0),""))))) -> Oil bottle PAG100, R134, HFO1234yf, mechanical and electrical compressor, 6 x 250 ml | G56: =IF(IF($G$1="ITALIANO",VLOOKUP(D56,'DB Accessori'!$A:$U,21,0),IF($G$1="ESPAÑOL",VLOOKUP(D56,'DB Accessori'!$A:$U,20,0),IF($G$1="DEUTSCH",VLOOKUP(D56,'DB Accessori'!$A:$U,18,0),IF($G$1="FRANÇAIS",VLOOKUP(D56,'DB Accessori'!$A:$U,19,0),IF($G$1="ENGLISH",VLOOKUP(D56,'DB Accessori'!$A:$U,17,0),"")))))=0,"",(IF($G$1="ITALIANO",VLOOKUP(D56,'DB Accessori'!$A:$U,21,0),IF($G$1="ESPAÑOL",VLOOKUP(D56,'DB Accessori'!$A:$U,20,0),IF($G$1="DEUTSCH",VLOOKUP(D56,'DB Accessori'!$A:$U,18,0),IF($G$1="FRANÇAIS",VLOOKUP(D56,'DB Accessori'!$A:$U,19,0),IF($G$1="ENGLISH",VLOOKUP(D56,'DB Accessori'!$A:$U,17,0),""))))))) -> All A/C machines | H56: =IF(I$1="Germany",VLOOKUP(D56,Prices!A:AA,16,0),VLOOKUP(D56,Prices!A:AA,3,0)) -> 16.5 | I56: =VLOOKUP(D56,Prices!A:AA,HLOOKUP(I$1&"D",Prices!A:AA,2,0),0) -> 0.4 | J56: =+$H56*(1-I56) -> 9.9
C57: =IF($G$1="ITALIANO",VLOOKUP(D57,'DB Accessori'!$A:$P,6,0),IF($G$1="ESPAÑOL",VLOOKUP(D57,'DB Accessori'!$A:$P,5,0),IF($G$1="DEUTSCH",VLOOKUP(D57,'DB Accessori'!$A:$P,3,0),IF($G$1="FRANÇAIS",VLOOKUP(D57,'DB Accessori'!$A:$P,4,0),IF($G$1="ENGLISH",VLOOKUP(D57,'DB Accessori'!$A:$P,2,0),""))))) -> A/C | D57: DECKAEK275-N | E57: =IF($G$1="ITALIANO",VLOOKUP(D57,'DB Accessori'!$A:$P,11,0),IF($G$1="ESPAÑOL",VLOOKUP(D57,'DB Accessori'!$A:$P,10,0),IF($G$1="DEUTSCH",VLOOKUP(D57,'DB Accessori'!$A:$P,8,0),IF($G$1="FRANÇAIS",VLOOKUP(D57,'DB Accessori'!$A:$P,9,0),IF($G$1="ENGLISH",VLOOKUP(D57,'DB Accessori'!$A:$P,7,0),""))))) -> Sealed oil cartridge PAG100 - 250ml for R134a, HFO1234yf mechanical and electric compressor | F57: =IF($G$1="ITALIANO",VLOOKUP(D57,'DB Accessori'!$A:$P,16,0),IF($G$1="ESPAÑOL",VLOOKUP(D57,'DB Accessori'!$A:$P,15,0),IF($G$1="DEUTSCH",VLOOKUP(D57,'DB Accessori'!$A:$P,13,0),IF($G$1="FRANÇAIS",VLOOKUP(D57,'DB Accessori'!$A:$P,14,0),IF($G$1="ENGLISH",VLOOKUP(D57,'DB Accessori'!$A:$P,12,0),""))))) -> Sealed oil cartridge PAG100 - 250ml for R134a, HFO1234yf mechanical and electric compressor | G57: =IF(IF($G$1="ITALIANO",VLOOKUP(D57,'DB Accessori'!$A:$U,21,0),IF($G$1="ESPAÑOL",VLOOKUP(D57,'DB Accessori'!$A:$U,20,0),IF($G$1="DEUTSCH",VLOOKUP(D57,'DB Accessori'!$A:$U,18,0),IF($G$1="FRANÇAIS",VLOOKUP(D57,'DB Accessori'!$A:$U,19,0),IF($G$1="ENGLISH",VLOOKUP(D57,'DB Accessori'!$A:$U,17,0),"")))))=0,"",(IF($G$1="ITALIANO",VLOOKUP(D57,'DB Accessori'!$A:$U,21,0),IF($G$1="ESPAÑOL",VLOOKUP(D57,'DB Accessori'!$A:$U,20,0),IF($G$1="DEUTSCH",VLOOKUP(D57,'DB Accessori'!$A:$U,18,0),IF($G$1="FRANÇAIS",VLOOKUP(D57,'DB Accessori'!$A:$U,19,0),IF($G$1="ENGLISH",VLOOKUP(D57,'DB Accessori'!$A:$U,17,0),""))))))) -> All A/C machines | H57: =IF(I$1="Germany",VLOOKUP(D57,Prices!A:AA,16,0),VLOOKUP(D57,Prices!A:AA,3,0)) -> 31 | I57: =VLOOKUP(D57,Prices!A:AA,HLOOKUP(I$1&"D",Prices!A:AA,2,0),0) -> 0.4 | J57: =+$H57*(1-I57) -> 18.6
C58: =IF($G$1="ITALIANO",VLOOKUP(D58,'DB Accessori'!$A:$P,6,0),IF($G$1="ESPAÑOL",VLOOKUP(D58,'DB Accessori'!$A:$P,5,0),IF($G$1="DEUTSCH",VLOOKUP(D58,'DB Accessori'!$A:$P,3,0),IF($G$1="FRANÇAIS",VLOOKUP(D58,'DB Accessori'!$A:$P,4,0),IF($G$1="ENGLISH",VLOOKUP(D58,'DB Accessori'!$A:$P,2,0),""))))) -> A/C | D58: DECKAEK276 | E58: =IF($G$1="ITALIANO",VLOOKUP(D58,'DB Accessori'!$A:$P,11,0),IF($G$1="ESPAÑOL",VLOOKUP(D58,'DB Accessori'!$A:$P,10,0),IF($G$1="DEUTSCH",VLOOKUP(D58,'DB Accessori'!$A:$P,8,0),IF($G$1="FRANÇAIS",VLOOKUP(D58,'DB Accessori'!$A:$P,9,0),IF($G$1="ENGLISH",VLOOKUP(D58,'DB Accessori'!$A:$P,7,0),""))))) -> Oil bottle PAG46, R134, HFO1234yf, mechanical and electrical compressor, 6 x 250 ml | F58: =IF($G$1="ITALIANO",VLOOKUP(D58,'DB Accessori'!$A:$P,16,0),IF($G$1="ESPAÑOL",VLOOKUP(D58,'DB Accessori'!$A:$P,15,0),IF($G$1="DEUTSCH",VLOOKUP(D58,'DB Accessori'!$A:$P,13,0),IF($G$1="FRANÇAIS",VLOOKUP(D58,'DB Accessori'!$A:$P,14,0),IF($G$1="ENGLISH",VLOOKUP(D58,'DB Accessori'!$A:$P,12,0),""))))) -> Oil bottle PAG46, R134, HFO1234yf, mechanical and electrical compressor, 6 x 250 ml | G58: =IF(IF($G$1="ITALIANO",VLOOKUP(D58,'DB Accessori'!$A:$U,21,0),IF($G$1="ESPAÑOL",VLOOKUP(D58,'DB Accessori'!$A:$U,20,0),IF($G$1="DEUTSCH",VLOOKUP(D58,'DB Accessori'!$A:$U,18,0),IF($G$1="FRANÇAIS",VLOOKUP(D58,'DB Accessori'!$A:$U,19,0),IF($G$1="ENGLISH",VLOOKUP(D58,'DB Accessori'!$A:$U,17,0),"")))))=0,"",(IF($G$1="ITALIANO",VLOOKUP(D58,'DB Accessori'!$A:$U,21,0),IF($G$1="ESPAÑOL",VLOOKUP(D58,'DB Accessori'!$A:$U,20,0),IF($G$1="DEUTSCH",VLOOKUP(D58,'DB Accessori'!$A:$U,18,0),IF($G$1="FRANÇAIS",VLOOKUP(D58,'DB Accessori'!$A:$U,19,0),IF($G$1="ENGLISH",VLOOKUP(D58,'DB Accessori'!$A:$U,17,0),""))))))) -> All A/C machines | H58: =IF(I$1="Germany",VLOOKUP(D58,Prices!A:AA,16,0),VLOOKUP(D58,Prices!A:AA,3,0)) -> 16.5 | I58: =VLOOKUP(D58,Prices!A:AA,HLOOKUP(I$1&"D",Prices!A:AA,2,0),0) -> 0.4 | J58: =+$H58*(1-I58) -> 9.9
